Workbook

Sheet README
B2: MDC 模块化数据中心 · 国内项目可研财务测算模板 v1.0（2026-09-16）
B3: 配套 MDC-KB `KB/Guideline/FEASIBILITY_Guideline.md` §F-2 第 6 章 / §F-4 / §F-7。每个国内可研复制本工作簿到 `Projects/<项目名>/可研/`，重命名为 `<项目名>_可研财务测算_v<x>.xlsx`。
B5: 铁律
B6: 1. 货币与税口径：国内方案一律人民币（含税）；海外方案一律美元（未税）。本模板为国内版，所有单价按含税输入，模型内按税率还原不含税值参与经济评价；校核 C10 锁定。
B7: 2. 单一真值源：所有输入只在 `0_参数`、`1-1_建安工程费`、`1-2_设备及软件` 三页的蓝字/黄底单元格；其余全部公式，不得手改。可研正文数字只准从 `00_指标表` 与对应附表引用。
B8: 3. 业主参数：黄底单元格（GPU/服务器单价、算力单价、售卖比例、算力设备折旧年限等）由业主/算力运营方书面提供，'来源/说明'列注明依据文件；我方不自行给 GPU 报价。
B9: 4. 出稿门禁：`13_一致性校核` 全部 OK 才可导出附表；任何 ERR 先改方案与参数，不得改公式凑数。
B11: 颜色约定
B12: 蓝字 = 输入；黄底 = 业主提供；黑字 = 本表公式；绿字 = 跨表引用；灰底 = 表头；浅绿底 = 关键结果。
B14: 填写顺序
B15: ① 0_参数 A–K 组（规模 → 负荷 → 收入 → 成本 → 折旧 → 税 → 融资 → 流动资金 → 费率 → 运营年参数） → ② 1-2 设备及软件（A 块业主价格、B 块我方口径） → ③ 1-1 建安工程费 → ④ 看 13_一致性校核 → ⑤ 看 00_指标表 → ⑥ 12_敏感性（Excel 中按 F9 重算数据表） → ⑦ 附表 1–12 导出 PDF 附于可研。
B17: 附表与可研章节对应
... B30: 示例数值参照阳高县智算中心可研（2026-04）口径设置，仅示意；新项目逐项替换。示例中模块单价、电力舱、冷源模块价格为占位数字，不代表报价。

Sheet 00_指标表
A1: 可研 1.1.10 主要技术经济指标一览表（正文唯一引用源）
A2: 本表全部为公式；可研正文与各章数字只准从本表与对应附表引用，不得另行手填
A4: 序号 | B4: 指标 | C4: 单位 | D4: 数值 | E4: 备注 / 来源表
A5: 1 | B5: 建设规模指标
A6: 1.1 | B6: 模块化算力单元数量 | C6: 套 | D6: =0_参数!$C$18 -> 4 | E6: 参数 B1
A7: 1.2 | B7: IT 总功率 | C7: kW | D7: =0_参数!$C$20 -> 2112 | E7: 参数 B3
A8: 1.3 | B8: 折合标准机架（2.5kW） | C8: 架 | D8: =0_参数!$C$22 -> 844.8 | E8: 参数 B5；备案/能评口径
A9: 1.4 | B9: 服务器台数 | C9: 台 | D9: =0_参数!$C$23 -> 168 | E9: 参数 B6【业主】
A10: 1.5 | B10: 总算力（FP16 稠密） | C10: P | D10: =0_参数!$C$25 -> 3024 | E10: 参数 B8
A11: 1.6 | B11: 配套用房建筑面积 | C11: ㎡ | D11: =0_参数!$C$30 -> 1500 | E11: 参数 C2
A12: 2 | B12: 能耗与能效
A13: 2.1 | B13: 总有功功率 | C13: kW | D13: =0_参数!$C$34 -> 2537.16 | E13: 参数 C6（供电章负荷计算）
A14: 2.2 | B14: 正常年用电量 | C14: 万kWh | D14: =INDEX(4_总成本费用!D$11:U$11,0_参数!$C$9+0_参数!$C$15) -> 1791.989 | E14: 附表 4；能评章同源
A15: 2.3 | B15: 正常年 IT 用电量 | C15: 万kWh | D15: =INDEX(4_总成本费用!D$10:U$10,0_参数!$C$9+0_参数!$C$15) -> 1498.5907 | E15: 附表 4
A16: 2.4 | B16: 设计 PUE | D16: =0_参数!$C$29 -> 1.18 | E16: 参数 C1
A17: 2.5 | B17: 正常年用水量 | C17: m³ | D17: =INDEX(4_总成本费用!D$12:U$12,0_参数!$C$9+0_参数!$C$15) -> 16000 | E17: 附表 4
A18: 2.6 | B18: WUE | C18: L/kWh | D18: =IFERROR(D17*1000/(D15*10000),0) -> 1.0676698 | E18: ＝ 用水量(L) / IT 电量(kWh)
A19: 3 | B19: 建设与运营
A20: 3.1 | B20: 建设期 | C20: 年 | D20: =0_参数!$C$9 -> 1 | E20: 参数 A4
A21: 3.2 | B21: 运营期 | C21: 年 | D21: =0_参数!$C$10 -> 10 | E21: 参数 A5
A22: 3.3 | B22: 劳动定员 | C22: 人 | D22: =0_参数!$C$67 -> 36 | E22: 参数 E14 = 可研 5.3.2
A23: 4 | B23: 投资指标
A24: 4.1 | B24: 项目总投资 | C24: 万元 | D24: =1_总投资估算!$G$33 -> 124539.38 | E24: 附表 1
A25: 4.1.1 | B25: 建设工程费 | C25: 万元 | D25: =1_总投资估算!$G$5 -> 110463.8 | E25: 附表 1
A26: 4.1.2 | B26: 工程建设其他费用 | C26: 万元 | D26: =1_总投资估算!$G$8 -> 6123.8248 | E26: 附表 1
A27: 4.1.3 | B27: 预备费 | C27: 万元 | D27: =1_总投资估算!$G$26 -> 5829.3812 | E27: 附表 1
A28: 4.1.4 | B28: 建设期利息 | C28: 万元 | D28: =1_总投资估算!$G$30 -> 1536.2551 | E28: 附表 1 / 11
A29: 4.1.5 | B29: 铺底流动资金 | C29: 万元 | D29: =1_总投资估算!$G$32 -> 586.12245 | E29: 附表 1 / 2
A30: 4.2 | B30: 其中：算力设备投资（业主提供价格） | C30: 万元 | D30: ='1-2_设备及软件'!$F$12 -> 94250 | E30: 附表 1-2 A
A31: 4.3 | B31: 其中：基础设施设备投资 | C31: 万元 | D31: ='1-2_设备及软件'!$F$22 -> 13402 | E31: 附表 1-2 B
A32: 4.4 | B32: 资金筹措：自有资金 / 长期借款 | C32: 万元 | D32: =0_参数!$C$89 -> 20000 | E32: 参数 H1；借款 = 附表 3
A33: 5 | B33: 财务指标
A34: 5.1 | B34: 营业收入（正常年，不含税） | C34: 万元 | D34: =INDEX(6_收入税金!D$11:U$11,0_参数!$C$9+0_参数!$C$15) -> 23963.774 | E34: 附表 6
A35: 5.2 | B35: 总成本费用（平均年） | C35: 万元 | D35: =4_总成本费用!$V$27 -> 15898.982 | E35: 附表 4
A36: 5.3 | B36: 利润总额（平均年） | C36: 万元 | D36: =7_利润!$V$12 -> 7798.5276 | E36: 附表 7
A37: 5.4 | B37: 所得税（平均年） | C37: 万元 | D37: =7_利润!$V$14 -> 1949.6319 | E37: 附表 7
A38: 5.5 | B38: 净利润（平均年） | C38: 万元 | D38: =7_利润!$V$15 -> 5848.8957 | E38: 附表 7
A39: 5.6 | B39: 投资利润率 | C39: % | D39: =8_现金流量!$D$39 -> 0.062618968 | E39: 附表 8
A40: 5.7 | B40: 投资利税率 | C40: % | D40: =8_现金流量!$D$40 -> 0.062618968 | E40: 附表 8
A41: 5.8 | B41: 财务内部收益率（税前） | C41: % | D41: =8_现金流量!$D$29 -> 0.10281066 | E41: 附表 8
A42: 5.8b | B42: 财务内部收益率（税后） | C42: % | D42: =8_现金流量!$D$30 -> 0.080255495 | E42: 附表 8
A43: 5.9 | B43: 财务净现值（税前，ic） | C43: 万元 | D43: =8_现金流量!$D$31 -> 12574.909 | E43: 附表 8
A44: 5.9b | B44: 财务净现值（税后） | C44: 万元 | D44: =8_现金流量!$D$32 -> 130.51575 | E44: 附表 8
A45: 5.10 | B45: 动态投资回收期（税前，含建设期） | C45: 年 | D45: =8_现金流量!$D$35 -> 10.089763 | E45: 附表 8
A46: 5.10b | B46: 动态投资回收期（税后，含建设期） | C46: 年 | D46: =8_现金流量!$D$36 -> 10.989015 | E46: 附表 8
A47: 5.11 | B47: 盈亏平衡点（正常年） | C47: % | D47: =8_现金流量!$D$38 -> 1.032887 | E47: 附表 8
A48: 5.12 | B48: 运营期最高资产负债率 | C48: % | D48: =10_资产负债!$V$27 -> 0.85134613 | E48: 附表 10
A49: 5.13 | B49: 运营期最低利息备付率 | C49: 倍 | D49: =11_还本付息!$V$25 -> -0.25672314 | E49: 附表 11
A50: 5.13b | B50: 运营期最低偿债备付率 | C50: 倍 | D50: =11_还本付息!$V$26 -> 1.2696392 | E50: 附表 11
A51: 6 | B51: 口径
A52: 6.1 | B52: 货币与税口径 | D52: =0_参数!$C$7 -> 人民币（含税） | E52: 铁律：国内人民币含税 / 海外美元未税
A53: 6.2 | B53: 价格水平基准年 | D53: =0_参数!$C$8 -> 2026

Sheet 0_参数
A1: 0 参数与假设（全模型唯一输入页）
A2: 颜色约定：蓝字 = 输入；黄底 = 业主/算力运营方提供并注明来源；黑字 = 公式；绿字 = 跨表引用。单位：万元 / 人民币（含税）
A4: A 项目与口径
A5: 编号 | B5: 参数 | C5: 数值 | D5: 单位 | E5: 来源 / 说明
A6: A1 | B6: 项目名称 | C6: 示例：XX 县模块化智算中心项目 | E6: 与可研封面一致
A7: A2 | B7: 货币与税口径（铁律） | C7: 人民币（含税） | E7: 国内方案一律人民币、含税报价；海外方案一律美元、未税。本模板为国内版，单价输入均为含税价，模型内按税率还原不含税值
A8: A3 | B8: 价格水平基准年 | C8: 2026 | D8: 年 | E8: 文本
A9: A4 | B9: 建设期 | C9: 1 | D9: 年 | E9: 1–3；MDC 模块化项目通常 1 年（工厂制造 ∥ 现场土建外线）
A10: A5 | B10: 运营期 | C10: 10 | D10: 年 | E10: ≤15；可研通常取 10 年
A11: A6 | B11: 建设投资投入比例-建设第1年 | C11: 1 | E11: 建设期各年比例之和须 = 1（校核表 C1）
A12: A7 | B12: 建设投资投入比例-建设第2年 | C12: 0
A13: A8 | B13: 建设投资投入比例-建设第3年 | C13: 0
A14: A9 | B14: 基准收益率 ic | C14: 0.08 | E14: 《建设项目经济评价方法与参数》第三版 行业基准
A15: A10 | B15: 正常年 = 运营第几年 | C15: 3 | E15: 用于盈亏平衡与指标表'正常年'取值；须 ≤ 运营期
A16: B 建设规模（与可研 1.1.10 指标表锁定）
A17: 编号 | B17: 参数 | C17: 数值 | D17: 单位 | E17: 来源 / 说明
A18: B1 | B18: 模块化算力单元数量 | C18: 4 | D18: 套 | E18: 一期模块数；分期投产比例见 D 组运营年参数
A19: B2 | B19: 单模块 IT 功率 | C19: 528 | D19: kW | E19: 产品口径
A20: B3 | B20: IT 总功率 | C20: =0_参数!$C$18*0_参数!$C$19 -> 2112 | D20: kW | E20: ＝ 模块数 × 单模块 IT 功率
A21: B4 | B21: 标准机架折算功率 | C21: 2.5 | D21: kW/架 | E21: 工信部标准机架口径
A22: B5 | B22: 折合标准机架 | C22: =0_参数!$C$20/0_参数!$C$21 -> 844.8 | D22: 架 | E22: 备案/能评口径
A23: B6 | B23: 服务器台数 | C23: 168 | D23: 台 | E23: 【业主提供】算力设备清单数量，与附表1-2 一致（校核表 C3）
A24: B7 | B24: 单台算力（FP16 稠密） | C24: 18 | D24: P | E24: 【业主提供】注明精度与稠密/稀疏
A25: B8 | B25: 总算力 | C25: =0_参数!$C$23*0_参数!$C$24 -> 3024 | D25: P
A26: B9 | B26: 可售计价单元数 | C26: =0_参数!$C$23 -> 168 | D26: 台 | E26: 默认 = 服务器台数；按机柜计价时改为机柜数
A27: C 负荷与能耗（可研'一张负荷表'，供电章 / 能评章 / 财务章同源）
A28: 编号 | B28: 参数 | C28: 数值 | D28: 单位 | E28: 来源 / 说明
A29: C1 | B29: 设计 PUE | C29: 1.18 | E29: GB 40879-2021 口径；与可研 7.4 计算值一致
A30: C2 | B30: 配套用房建筑面积 | C30: 1500 | D30: ㎡ | E30: 运维楼 / 柴发房 / 值班等
A31: C3 | B31: 配套用房单位负荷 | C31: 30 | D31: W/㎡
A32: C4 | B32: 配套用房功率 | C32: =0_参数!$C$30*0_参数!$C$31/1000 -> 45 | D32: kW
A33: C5 | B33: 配套机电功率（冷却+供配电损耗） | C33: =0_参数!$C$20*(0_参数!$C$29-1) -> 380.16 | D33: kW | E33: ＝ IT × (PUE−1)，不用 30% 平铺
A34: C6 | B34: 总有功功率 | C34: =0_参数!$C$20+0_参数!$C$32+0_参数!$C$33 -> 2537.16 | D34: kW | E34: 供电章负荷计算结论
A35: C7 | B35: 配套用房需要系数 | C35: 0.6
A36: C8 | B36: 年运行小时 | C36: 8760 | D36: h
A37: C9 | B37: 满负荷年用水量 | C37: 16000 | D37: m³ | E37: 取自可研 4.3.5 用水量表（采暖期+非采暖期）
A38: C10 | B38: 电价（含税） | C38: 0.45 | D38: 元/kWh | E38: 当地大工业/直供电价，含税
A39: C11 | B39: 电力增值税率 | C39: 0.13
A40: C12 | B40: 水价（含税） | C40: 4.5 | D40: 元/m³
A41: C13 | B41: 水增值税率 | C41: 0.09
A42: D 收入（价格参数由业主/算力运营方提供）
A43: 编号 | B43: 参数 | C43: 数值 | D43: 单位 | E43: 来源 / 说明
A44: D1 | B44: 算力单价（含税，基准值） | C44: 14 | D44: 万元/台/月 | E44: 【业主提供】同类智算中心市场价；注明来源文件
A45: D2 | B45: 单价敏感性系数 | C45: =12_敏感性!$C$6 -> 1 | E45: 由敏感性表驱动，基准 = 1.00
A46: D3 | B46: 算力单价（含税，测算值） | C46: =0_参数!$C$44*0_参数!$C$45 -> 14 | D46: 万元/台/月
A47: D4 | B47: 收入增值税率 | C47: 0.06 | E47: 信息技术服务 6%
A48: D5 | B48: 售卖比例敏感性系数 | C48: =12_敏感性!$C$7 -> 1 | E48: 基准 = 1.00
A49: D6 | B49: 电价敏感性系数 | C49: =12_敏感性!$C$8 -> 1 | E49: 基准 = 1.00
A50: D7 | B50: 算力设备价格敏感性系数 | C50: =12_敏感性!$C$9 -> 1 | E50: 基准 = 1.00
A51: D8 | B51: 基础设施设备价格敏感性系数 | C51: =12_敏感性!$C$10 -> 1 | E51: 基准 = 1.00
A52: E 成本
A53: 编号 | B53: 参数 | C53: 数值 | D53: 单位 | E53: 来源 / 说明
A54: E1 | B54: 专线数量 | C54: 2 | D54: 条
A55: E2 | B55: 专线年费（含税） | C55: 300 | D55: 万元/条/年
A56: E3 | B56: 专线增值税率 | C56: 0.06
A57: E4 | B57: 运维服务外包费（含税） | C57: 600 | D57: 万元/年 | E57: 第三方运维/驻场
A58: E5 | B58: 运维类费用增值税率 | C58: 0.06 | E58: 维保 / 软件维护 / 外包按 6% 还原
A59: E6 | B59: 软件维护费率（占软件费） | C59: 0.05
A60: E7 | B60: 机电设备维护费率（占基础设施设备费） | C60: 0.01
A61: E8 | B61: 定员-中高层管理 | C61: 5 | D61: 人
A62: E9 | B62: 定员-技术人员 | C62: 25 | D62: 人 | E62: MDC 少人值守
A63: E10 | B63: 定员-普通人员 | C63: 6 | D63: 人
A64: E11 | B64: 人均工资福利-中高层 | C64: 20 | D64: 万元/人·年
A65: E12 | B65: 人均工资福利-技术 | C65: 15 | D65: 万元/人·年
A66: E13 | B66: 人均工资福利-普通 | C66: 6 | D66: 万元/人·年
A67: E14 | B67: 定员合计 | C67: =0_参数!$C$61+0_参数!$C$62+0_参数!$C$63 -> 36 | D67: 人 | E67: ＝ 可研 5.3.2 劳动定员
A68: E15 | B68: 工资及福利总额 | C68: =0_参数!$C$61*0_参数!$C$64+0_参数!$C$62*0_参数!$C$65+0_参数!$C$63*0_参数!$C$66 -> 511 | D68: 万元/年
A69: E16 | B69: 其他管理费率（占工资） | C69: 0.2 | E69: 工会经费 / 教育经费 / 业务招待等
A70: F 折旧与摊销（分层）
A71: 编号 | B71: 参数 | C71: 数值 | D71: 单位 | E71: 来源 / 说明
A72: F1 | B72: 建筑类折旧年限 | C72: 20 | D72: 年 | E72: 配套用房 / 场地 / 基础
A73: F2 | B73: 基础设施设备折旧年限 | C73: 15 | D73: 年 | E73: 模块 / 电力舱 / 冷源 / UPS / 柴发
A74: F3 | B74: 算力设备折旧年限 | C74: 5 | D74: 年 | E74: 【业主提供】按业主会计口径确认；范例用 15 年偏乐观
A75: F4 | B75: 残值率 | C75: 0.05
A76: F5 | B76: 递延资产摊销年限 | C76: 5 | D76: 年 | E76: 培训费 / 办公家具 / 提前进场费等
A77: F6 | B77: 固定资产原值扣减可抵扣进项税 | C77: 1 | D77: 1/0 | E77: 1 = 原值按不含税计（一般纳税人）；0 = 含税入账
A78: G 税费
A79: 编号 | B79: 参数 | C79: 数值 | D79: 单位 | E79: 来源 / 说明
A80: G1 | B80: 建安工程进项税率 | C80: 0.09
A81: G2 | B81: 设备购置进项税率 | C81: 0.13
A82: G3 | B82: 城市维护建设税 | C82: 0.07 | E82: 按实缴增值税
A83: G4 | B83: 教育费附加 | C83: 0.03
A84: G5 | B84: 地方教育附加 | C84: 0.02
A85: G6 | B85: 企业所得税率 | C85: 0.25 | E85: 如享受优惠税率在此改
A86: G7 | B86: 法定盈余公积提取比例 | C86: 0.1
A87: H 融资
A88: 编号 | B88: 参数 | C88: 数值 | D88: 单位 | E88: 来源 / 说明
A89: H1 | B89: 企业自有资金（用于建设投资） | C89: 20000 | D89: 万元 | E89: 资本金
A90: H2 | B90: 长期借款利率 | C90: 0.03
A91: H3 | B91: 长期借款还款年限（等额还本） | C91: 10 | D91: 年 | E91: 自运营第 1 年起；须 ≤ 运营期
A92: H4 | B92: 建设期利息资金来源 | C92: 1 | D92: 1/0 | E92: 1 = 资本化计入贷款本金；0 = 由资本金支付
A93: H5 | B93: 流动资金借款比例 | C93: 0.7 | E93: 其余 30% 为铺底流动资金（资本金）
A94: H6 | B94: 流动资金借款利率 | C94: 0.035
A95: I 流动资金（分项详细估算法）
A96: 编号 | B96: 参数 | C96: 数值 | D96: 单位 | E96: 来源 / 说明
A97: I1 | B97: 应收账款周转天数 | C97: 30 | D97: 天
A98: I2 | B98: 存货（外购动力）周转天数 | C98: 30 | D98: 天
A99: I3 | B99: 现金周转天数 | C99: 30 | D99: 天
A100: I4 | B100: 应付账款周转天数 | C100: 30 | D100: 天
A101: I5 | B101: 一年按天数 | C101: 360 | D101: 天
...

Sheet 1_总投资估算
A1: 附表 1 总投资估算表
A2: 单位：万元（人民币，含税）。第一部分来自附表 1-1 / 1-2；其他费用按参数 J 组费率；建设期利息来自附表 11；铺底流动资金来自附表 2
A4: 序号 | B4: 工程或费用名称 | C4: 建筑工程 | D4: 安装工程 | E4: 设备购置 | F4: 其他费用 | G4: 合计 | H4: 占总投资 | I4: 资产归类 / 说明
A5: 一 | B5: 第一部分 建设工程费用 | C5: =C6+C7 -> 1891.8 | D5: =D6+D7 -> 920 | E5: =E6+E7 -> 107652 | G5: =SUM(C5:F5) -> 110463.8 | H5: =IFERROR(G5/$G$33,0) -> 0.88697886
A6: 1 | B6: 设备及软件工程 | E6: ='1-2_设备及软件'!$F$23 -> 107652 | G6: =SUM(C6:F6) -> 107652 | H6: =IFERROR(G6/$G$33,0) -> 0.86440126 | I6: 固定资产（分算力/基础设施两类，见附表5）
A7: 2 | B7: 建筑安装工程 | C7: ='1-1_建安工程费'!$G$16 -> 1891.8 | D7: ='1-1_建安工程费'!$H$16 -> 920 | G7: =SUM(C7:F7) -> 2811.8 | H7: =IFERROR(G7/$G$33,0) -> 0.022577597 | I7: 固定资产（建筑类）
A8: 二 | B8: 第二部分 工程建设其他费用 | F8: =SUM(F9:F25) -> 6123.8248 | G8: =SUM(C8:F8) -> 6123.8248 | H8: =IFERROR(G8/$G$33,0) -> 0.049171793
A9: 2.1 | B9: 土地费 | F9: =0_参数!$C$104 -> 330 | G9: =SUM(C9:F9) -> 330 | H9: =IFERROR(G9/$G$33,0) -> 0.0026497642 | I9: 固定资产
A10: 2.2 | B10: 建设单位管理费 | F10: =$G$5*0_参数!$C$105 -> 1436.0294 | G10: =SUM(C10:F10) -> 1436.0294 | H10: =IFERROR(G10/$G$33,0) -> 0.011530725 | I10: 固定资产
A11: 2.3 | B11: 工程监理费 | F11: =($C$7+$D$7+$E$6*0.4)*0_参数!$C$106 -> 596.3438 | G11: =SUM(C11:F11) -> 596.3438 | H11: =IFERROR(G11/$G$33,0) -> 0.0047883953 | I11: 固定资产
A12: 2.4 | B12: 勘察费 | F12: =($C$7+$D$7)*0_参数!$C$107 -> 11.2472 | G12: =SUM(C12:F12) -> 11.2472 | H12: =IFERROR(G12/$G$33,0) -> 9.0310388e-05 | I12: 固定资产
A13: 2.5 | B13: 设计费 | F13: =($C$7+$D$7+$E$6)*0_参数!$C$108 -> 1877.8846 | G13: =SUM(C13:F13) -> 1877.8846 | H13: =IFERROR(G13/$G$33,0) -> 0.015078641 | I13: 固定资产
A14: 2.6 | B14: 可行性研究报告编制费 | F14: =0_参数!$C$109 -> 30 | G14: =SUM(C14:F14) -> 30 | H14: =IFERROR(G14/$G$33,0) -> 0.00024088765 | I14: 固定资产
A15: 2.7 | B15: 节能报告编制费 | F15: =0_参数!$C$110 -> 50 | G15: =SUM(C15:F15) -> 50 | H15: =IFERROR(G15/$G$33,0) -> 0.00040147942 | I15: 固定资产
A16: 2.8 | B16: 环评及其他专项评价费 | F16: =0_参数!$C$111 -> 40 | G16: =SUM(C16:F16) -> 40 | H16: =IFERROR(G16/$G$33,0) -> 0.00032118354 | I16: 固定资产
A17: 2.9 | B17: 招标代理费 | F17: =$G$5*0_参数!$C$112 -> 220.9276 | G17: =SUM(C17:F17) -> 220.9276 | H17: =IFERROR(G17/$G$33,0) -> 0.0017739577 | I17: 固定资产
A18: 2.10 | B18: 场地准备及临时设施费 | F18: =($C$7+$D$7)*0_参数!$C$113 -> 22.4944 | G18: =SUM(C18:F18) -> 22.4944 | H18: =IFERROR(G18/$G$33,0) -> 0.00018062078 | I18: 固定资产
A19: 2.11 | B19: 工程保险费 | F19: =($C$7+$D$7)*0_参数!$C$114+$E$6*0_参数!$C$115 -> 379.03144 | G19: =SUM(C19:F19) -> 379.03144 | H19: =IFERROR(G19/$G$33,0) -> 0.0030434665 | I19: 固定资产
A20: 2.12 | B20: 联合试运转费 | F20: =$E$6*0_参数!$C$116 -> 1076.52 | G20: =SUM(C20:F20) -> 1076.52 | H20: =IFERROR(G20/$G$33,0) -> 0.0086440126 | I20: 固定资产
A21: 2.13 | B21: 竣工决算编制费 | F21: =$G$5*0_参数!$C$117 -> 11.04638 | G21: =SUM(C21:F21) -> 11.04638 | H21: =IFERROR(G21/$G$33,0) -> 8.8697886e-05 | I21: 固定资产
A22: 2.14 | B22: 办公家具购置费 | F22: =0_参数!$C$118 -> 5.1 | G22: =SUM(C22:F22) -> 5.1 | H22: =IFERROR(G22/$G$33,0) -> 4.0950901e-05 | I22: 递延资产
A23: 2.15 | B23: 职工培训费 | F23: =0_参数!$C$119 -> 7.2 | G23: =SUM(C23:F23) -> 7.2 | H23: =IFERROR(G23/$G$33,0) -> 5.7813037e-05 | I23: 递延资产
A24: 2.16 | B24: 提前进场费 | F24: =0_参数!$C$120 -> 30 | G24: =SUM(C24:F24) -> 30 | H24: =IFERROR(G24/$G$33,0) -> 0.00024088765 | I24: 递延资产
A25: 2.17 | B25: 其他（预留） | F25: 0 | G25: =SUM(C25:F25) -> 0 | H25: =IFERROR(G25/$G$33,0) -> 0 | I25: 固定资产
A26: 三 | B26: 第三部分 预备费 | F26: =F27+F28 -> 5829.3812 | G26: =SUM(C26:F26) -> 5829.3812 | H26: =IFERROR(G26/$G$33,0) -> 0.046807532
A27: 3.1 | B27: 基本预备费 | F27: =(G5+G8)*0_参数!$C$121 -> 5829.3812 | G27: =SUM(C27:F27) -> 5829.3812 | H27: =IFERROR(G27/$G$33,0) -> 0.046807532 | I27: 固定资产
A28: 3.2 | B28: 涨价预备费 | F28: =(G5+G8)*0_参数!$C$122 -> 0 | G28: =SUM(C28:F28) -> 0 | H28: =IFERROR(G28/$G$33,0) -> 0 | I28: 固定资产
A29: 四 | B29: 工程建设投资（建设投资）= 一 + 二 + 三 | C29: =C5 -> 1891.8 | D29: =D5 -> 920 | E29: =E5 -> 107652 | F29: =F8+F26 -> 11953.206 | G29: =SUM(C29:F29) -> 122417.01 | H29: =IFERROR(G29/$G$33,0) -> 0.98295818
A30: 五 | B30: 建设期利息 | F30: =11_还本付息!$V$9 -> 1536.2551 | G30: =SUM(C30:F30) -> 1536.2551 | H30: =IFERROR(G30/$G$33,0) -> 0.012335496 | I30: 固定资产（资本化）
A31: 六 | B31: 固定资产投资 = 四 + 五 | C31: =C29 -> 1891.8 | D31: =D29 -> 920 | E31: =E29 -> 107652 | F31: =F29+F30 -> 13489.461 | G31: =SUM(C31:F31) -> 123953.26 | H31: =IFERROR(G31/$G$33,0) -> 0.99529368
A32: 七 | B32: 铺底流动资金 | F32: =2_流动资金!$V$16 -> 586.12245 | G32: =SUM(C32:F32) -> 586.12245 | H32: =IFERROR(G32/$G$33,0) -> 0.0047063221 | I32: ＝ 正常年流动资金 × (1 − 借款比例)
A33: 八 | B33: 项目总投资 = 六 + 七 | C33: =C31 -> 1891.8 | D33: =D31 -> 920 | E33: =E31 -> 107652 | F33: =F31+F32 -> 14075.584 | G33: =SUM(C33:F33) -> 124539.38 | H33: =IFERROR(G33/$G$33,0) -> 1
B34: 构成比例 | C34: =IFERROR(C33/G33,0) -> 0.015190375 | D34: =IFERROR(D33/G33,0) -> 0.0073872214 | E34: =IFERROR(E33/G33,0) -> 0.86440126 | F34: =IFERROR(F33/G33,0) -> 0.11302114
B36: 辅助计算（供附表 5 / 6 使用）
B37: 可抵扣进项税-设备 | F37: =IF(0_参数!$C$77=1,$E$6/(1+0_参数!$C$81)*0_参数!$C$81,0) -> 12384.743
B38: 可抵扣进项税-建安 | F38: =IF(0_参数!$C$77=1,($C$7+$D$7)/(1+0_参数!$C$80)*0_参数!$C$80,0) -> 232.16697
B39: 可抵扣进项税合计（运营期初留抵） | F39: =F37+F38 -> 12616.91
B40: 其他费用中计入固定资产部分 | F40: =SUMIF(I9:I25,"固定资产",F9:F25) -> 6081.5248
B41: 其他费用中计入递延资产部分 | F41: =SUMIF(I9:I25,"递延资产",F9:F25) -> 42.3
B42: 算力设备直接费（含税） | F42: ='1-2_设备及软件'!$F$12 -> 94250
B43: 基础设施设备直接费（含税） | F43: ='1-2_设备及软件'!$F$22 -> 13402
B44: 建筑类直接费（含税）= 建安合计 | F44: =$C$7+$D$7 -> 2811.8

Sheet 1-1_建安工程费
A1: 附表 1-1 建筑安装工程费用估算表
A2: 单位：万元（人民币，含税）。MDC 项目建安只剩配套用房、模块基础、场地、管廊、外线
A4: 序号 | B4: 工程名称 | C4: 数量 | D4: 单位 | E4: 单价（万元） | F4: 类型 | G4: 建筑工程 | H4: 安装工程 | I4: 合计 | J4: 备注
A5: 1 | B5: 配套运维用房 土建（含装饰） | C5: =0_参数!$C$30 -> 1500 | D5: ㎡ | E5: 0.45 | F5: 建筑 | G5: =IF(F5="建筑",C5*E5,0) -> 675 | H5: =IF(F5="安装",C5*E5,0) -> 0 | I5: =G5+H5 -> 675 | J5: 面积联动参数 C2；示例 4500 元/㎡
A6: 2 | B6: 配套运维用房 机电安装（给排水/电/暖通/弱电/消防） | C6: =0_参数!$C$30 -> 1500 | D6: ㎡ | E6: 0.08 | F6: 安装 | G6: =IF(F6="建筑",C6*E6,0) -> 0 | H6: =IF(F6="安装",C6*E6,0) -> 120 | I6: =G6+H6 -> 120 | J6: 示例 800 元/㎡
A7: 3 | B7: 柴发房 | C7: 310 | D7: ㎡ | E7: 0.28 | F7: 建筑 | G7: =IF(F7="建筑",C7*E7,0) -> 86.8 | H7: =IF(F7="安装",C7*E7,0) -> 0 | I7: =G7+H7 -> 86.8 | J7: 示例
A8: 4 | B8: 模块基础 / 钢平台 | C8: =0_参数!$C$18 -> 4 | D8: 套 | E8: 80 | F8: 建筑 | G8: =IF(F8="建筑",C8*E8,0) -> 320 | H8: =IF(F8="安装",C8*E8,0) -> 0 | I8: =G8+H8 -> 320 | J8: 按模块满载重量与冻深设计；数量联动 B1
A9: 5 | B9: 电力舱、冷源模块基础 | C9: 6 | D9: 座 | E9: 25 | F9: 建筑 | G9: =IF(F9="建筑",C9*E9,0) -> 150 | H9: =IF(F9="安装",C9*E9,0) -> 0 | I9: =G9+H9 -> 150 | J9: 示例
A10: 6 | B10: 场地道路与硬化（含吊装场地） | C10: 8000 | D10: ㎡ | E10: 0.018 | F10: 建筑 | G10: =IF(F10="建筑",C10*E10,0) -> 144 | H10: =IF(F10="安装",C10*E10,0) -> 0 | I10: =G10+H10 -> 144 | J10: 示例 180 元/㎡
A11: 7 | B11: 综合管廊 / 管线 | C11: 280 | D11: m | E11: 0.2 | F11: 建筑 | G11: =IF(F11="建筑",C11*E11,0) -> 56 | H11: =IF(F11="安装",C11*E11,0) -> 0 | I11: =G11+H11 -> 56 | J11: 示例 2000 元/m
A12: 8 | B12: 外线接入工程（10kV/35kV 线路、开关站） | C12: 1 | D12: 项 | E12: 800 | F12: 安装 | G12: =IF(F12="建筑",C12*E12,0) -> 0 | H12: =IF(F12="安装",C12*E12,0) -> 800 | I12: =G12+H12 -> 800 | J12: 按供电方案；常为关键路径
A13: 9 | B13: 消防水池、泵房及室外消防 | C13: 1 | D13: 项 | E13: 300 | F13: 建筑 | G13: =IF(F13="建筑",C13*E13,0) -> 300 | H13: =IF(F13="安装",C13*E13,0) -> 0 | I13: =G13+H13 -> 300 | J13: 可与海绵调蓄合建
A14: 10 | B14: 海绵城市设施（透水铺装、调蓄） | C14: 1 | D14: 项 | E14: 100 | F14: 建筑 | G14: =IF(F14="建筑",C14*E14,0) -> 100 | H14: =IF(F14="安装",C14*E14,0) -> 0 | I14: =G14+H14 -> 100 | J14: 按地方专项规划要求
A15: 11 | B15: 围墙、大门、绿化 | C15: 1 | D15: 项 | E15: 60 | F15: 建筑 | G15: =IF(F15="建筑",C15*E15,0) -> 60 | H15: =IF(F15="安装",C15*E15,0) -> 0 | I15: =G15+H15 -> 60 | J15: 示例
B16: 建安工程合计 | G16: =SUM(G5:G15) -> 1891.8 | H16: =SUM(H5:H15) -> 920 | I16: =G16+H16 -> 2811.8

Sheet 1-2_设备及软件
A1: 附表 1-2 设备及软件工程投资估算表
A2: 单位：万元（人民币，含税）。A 块价格由业主/算力运营方提供（黄底），B 块为我方基础设施口径。金额 = 数量 × 单价 × 敏感性系数
A4: 序号 | B4: 设备名称 | C4: 单位 | D4: 数量 | E4: 单价（万元，含税） | F4: 金额（万元） | G4: 资产类别 | H4: 来源 / 备注
A5: A | B5: 算力设备（价格：业主提供）
A6: A1 | B6: GPU 服务器（8 卡） | C6: 台 | D6: =0_参数!$C$23 -> 168 | E6: 450 | F6: =D6*E6*0_参数!$C$50 -> 75600 | G6: 算力设备 | H6: 【业主提供】业主采购意向/报价单；数量联动参数 B6
A7: A2 | B7: 算力网络设备（IB/RoCE 交换机、线缆） | C7: 套 | D7: 1 | E7: 800 | F7: =D7*E7*0_参数!$C$50 -> 800 | G7: 算力设备 | H7: 【业主提供】业主提供
A8: A3 | B8: 存储设备（全闪 + 海量） | C8: 套 | D8: 1 | E8: 500 | F8: =D8*E8*0_参数!$C$50 -> 500 | G8: 算力设备 | H8: 【业主提供】业主提供
A9: A4 | B9: 安全设备（含等保测评） | C9: 套 | D9: 1 | E9: 150 | F9: =D9*E9*0_参数!$C$50 -> 150 | G9: 算力设备 | H9: 【业主提供】业主提供
A10: A5 | B10: 计算平台软件 | C10: 套 | D10: 1 | E10: 12000 | F10: =D10*E10*0_参数!$C$50 -> 12000 | G10: 算力设备 | H10: 【业主提供】业主提供；软件维护费按此项 × 费率
A11: A6 | B11: 系统集成与过程管理 | C11: 套 | D11: 1 | E11: 5200 | F11: =D11*E11*0_参数!$C$50 -> 5200 | G11: 算力设备 | H11: 【业主提供】业主提供
B12: A 小计 算力设备 | F12: =SUM(F6:F11) -> 94250
A14: B | B14: 基础设施设备（我方口径）
A15: B1 | B15: 模块化算力单元（含内部配电、冷却分配、监控） | C15: 套 | D15: =0_参数!$C$18 -> 4 | E15: 1800 | F15: =D15*E15*0_参数!$C$51 -> 7200 | G15: 基础设施设备 | H15: 数量联动参数 B1；单价为我方概算口径（示例）
A16: B2 | B16: 预制式电力舱（中压/变配电/低压） | C16: 套 | D16: 2 | E16: 600 | F16: =D16*E16*0_参数!$C$51 -> 1200 | G16: 基础设施设备 | H16: 示例
A17: B3 | B17: 一体化外部冷源模块（工厂 FAT） | C17: 套 | D17: 4 | E17: 300 | F17: =D17*E17*0_参数!$C$51 -> 1200 | G17: 基础设施设备 | H17: 示例
A18: B4 | B18: UPS 系统（含电池） | C18: 套 | D18: 12 | E18: 135 | F18: =D18*E18*0_参数!$C$51 -> 1620 | G18: 基础设施设备 | H18: 如采用 BESS 路线在此替换
A19: B5 | B19: 柴油发电机组 | C19: 台 | D19: 3 | E19: 220 | F19: =D19*E19*0_参数!$C$51 -> 660 | G19: 基础设施设备 | H19: 是否配置走等级论证（P 系列）
A20: B6 | B20: DCIM / 弱电智能化 / 安防 | C20: 套 | D20: 1 | E20: 1100 | F20: =D20*E20*0_参数!$C$51 -> 1100 | G20: 基础设施设备 | H20: 示例
A21: B7 | B21: 机柜及其他配套 | C21: 套 | D21: 1 | E21: 422 | F21: =D21*E21*0_参数!$C$51 -> 422 | G21: 基础设施设备 | H21: 示例
B22: B 小计 基础设施设备 | F22: =SUM(F15:F21) -> 13402
B23: 设备及软件工程合计 | F23: ='1-2_设备及软件'!$F$12+'1-2_设备及软件'!$F$22 -> 107652
B25: 注：可研正文设备方案只写通用工程口径（单模块 IT 功率、冷却方式、外形/重量）；产品商品名与型号只在本表出现一次。

Sheet 2_流动资金
A1: 附表 2 流动资金估算表（分项详细估算法）
A2: 单位：万元。周转次数 = 360 / 周转天数；铺底流动资金 = 正常年流动资金 × (1 − 流动资金借款比例)
A3: 序号 | B3: 项目 \ 年份 | C3: 单位/说明 | D3: 1 | E3: =D3+1 -> 2 | F3: =E3+1 -> 3 | G3: =F3+1 -> 4 | H3: =G3+1 -> 5 | I3: =H3+1 -> 6 | J3: =I3+1 -> 7 | K3: =J3+1 -> 8 | L3: =K3+1 -> 9 | ... U3: =T3+1 -> 18 | V3: 合计/平均
B4: 阶段 | D4: =IF(D$3<=0_参数!$C$9,"建设",IF(D$3<=0_参数!$C$9+0_参数!$C$10,"运营","")) -> 建设 | E4: =IF(E$3<=0_参数!$C$9,"建设",IF(E$3<=0_参数!$C$9+0_参数!$C$10,"运营","")) -> 运营 | F4: =IF(F$3<=0_参数!$C$9,"建设",IF(F$3<=0_参数!$C$9+0_参数!$C$10,"运营","")) -> 运营 | G4: =IF(G$3<=0_参数!$C$9,"建设",IF(G$3<=0_参数!$C$9+0_参数!$C$10,"运营","")) -> 运营 | H4: =IF(H$3<=0_参数!$C$9,"建设",IF(H$3<=0_参数!$C$9+0_参数!$C$10,"运营","")) -> 运营 | I4: =IF(I$3<=0_参数!$C$9,"建设",IF(I$3<=0_参数!$C$9+0_参数!$C$10,"运营","")) -> 运营 | J4: =IF(J$3<=0_参数!$C$9,"建设",IF(J$3<=0_参数!$C$9+0_参数!$C$10,"运营","")) -> 运营 | K4: =IF(K$3<=0_参数!$C$9,"建设",IF(K$3<=0_参数!$C$9+0_参数!$C$10,"运营","")) -> 运营 | ... U4: =IF(U$3<=0_参数!$C$9,"建设",IF(U$3<=0_参数!$C$9+0_参数!$C$10,"运营",""))
B5: 运营年序号 | D5: =IF(D$4="运营",D$3-0_参数!$C$9,0) -> 0 | E5: =IF(E$4="运营",E$3-0_参数!$C$9,0) -> 1 | F5: =IF(F$4="运营",F$3-0_参数!$C$9,0) -> 2 | G5: =IF(G$4="运营",G$3-0_参数!$C$9,0) -> 3 | H5: =IF(H$4="运营",H$3-0_参数!$C$9,0) -> 4 | I5: =IF(I$4="运营",I$3-0_参数!$C$9,0) -> 5 | J5: =IF(J$4="运营",J$3-0_参数!$C$9,0) -> 6 | K5: =IF(K$4="运营",K$3-0_参数!$C$9,0) -> 7 | ... U5: =IF(U$4="运营",U$3-0_参数!$C$9,0) -> 0
B6: 建设年序号 | D6: =IF(D$4="建设",D$3,0) -> 1 | E6: =IF(E$4="建设",E$3,0) -> 0 | F6: =IF(F$4="建设",F$3,0) -> 0 | G6: =IF(G$4="建设",G$3,0) -> 0 | H6: =IF(H$4="建设",H$3,0) -> 0 | I6: =IF(I$4="建设",I$3,0) -> 0 | J6: =IF(J$4="建设",J$3,0) -> 0 | K6: =IF(K$4="建设",K$3,0) -> 0 | ... U6: =IF(U$4="建设",U$3,0) -> 0
A7: 1.1 | B7: 应收账款 | C7: 万元 | D7: =IF(D$4="运营",6_收入税金!D$11/(0_参数!$C$101/0_参数!$C$97),0) -> 0 | E7: =IF(E$4="运营",6_收入税金!E$11/(0_参数!$C$101/0_参数!$C$97),0) -> 1775.0943 | F7: =IF(F$4="运营",6_收入税金!F$11/(0_参数!$C$101/0_参数!$C$97),0) -> 1996.9811 | G7: =IF(G$4="运营",6_收入税金!G$11/(0_参数!$C$101/0_参数!$C$97),0) -> 1996.9811 | H7: =IF(H$4="运营",6_收入税金!H$11/(0_参数!$C$101/0_参数!$C$97),0) -> 1996.9811 | I7: =IF(I$4="运营",6_收入税金!I$11/(0_参数!$C$101/0_参数!$C$97),0) -> 1996.9811 | J7: =IF(J$4="运营",6_收入税金!J$11/(0_参数!$C$101/0_参数!$C$97),0) -> 1996.9811 | K7: =IF(K$4="运营",6_收入税金!K$11/(0_参数!$C$101/0_参数!$C$97),0) -> 1996.9811 | ... U7: =IF(U$4="运营",6_收入税金!U$11/(0_参数!$C$101/0_参数!$C$97),0) -> 0
A8: 1.2 | B8: 存货（外购燃料动力） | C8: 万元 | D8: =IF(D$4="运营",4_总成本费用!D$16/(0_参数!$C$101/0_参数!$C$98),0) -> 0 | E8: =IF(E$4="运营",4_总成本费用!E$16/(0_参数!$C$101/0_参数!$C$98),0) -> 53.498705 | F8: =IF(F$4="运营",4_总成本费用!F$16/(0_参数!$C$101/0_参数!$C$98),0) -> 60.019122 | G8: =IF(G$4="运营",4_总成本费用!G$16/(0_参数!$C$101/0_参数!$C$98),0) -> 60.019122 | H8: =IF(H$4="运营",4_总成本费用!H$16/(0_参数!$C$101/0_参数!$C$98),0) -> 60.019122 | I8: =IF(I$4="运营",4_总成本费用!I$16/(0_参数!$C$101/0_参数!$C$98),0) -> 60.019122 | J8: =IF(J$4="运营",4_总成本费用!J$16/(0_参数!$C$101/0_参数!$C$98),0) -> 60.019122 | K8: =IF(K$4="运营",4_总成本费用!K$16/(0_参数!$C$101/0_参数!$C$98),0) -> 60.019122 | ... U8: =IF(U$4="运营",4_总成本费用!U$16/(0_参数!$C$101/0_参数!$C$98),0) -> 0
A9: 1.3 | B9: 现金（工资 + 其他管理费） | C9: 万元 | D9: =IF(D$4="运营",(4_总成本费用!D$17+4_总成本费用!D$22)/(0_参数!$C$101/0_参数!$C$99),0) -> 0 | E9: =IF(E$4="运营",(4_总成本费用!E$17+4_总成本费用!E$22)/(0_参数!$C$101/0_参数!$C$99),0) -> 51.1 | F9: =IF(F$4="运营",(4_总成本费用!F$17+4_总成本费用!F$22)/(0_参数!$C$101/0_参数!$C$99),0) -> 51.1 | G9: =IF(G$4="运营",(4_总成本费用!G$17+4_总成本费用!G$22)/(0_参数!$C$101/0_参数!$C$99),0) -> 51.1 | H9: =IF(H$4="运营",(4_总成本费用!H$17+4_总成本费用!H$22)/(0_参数!$C$101/0_参数!$C$99),0) -> 51.1 | I9: =IF(I$4="运营",(4_总成本费用!I$17+4_总成本费用!I$22)/(0_参数!$C$101/0_参数!$C$99),0) -> 51.1 | J9: =IF(J$4="运营",(4_总成本费用!J$17+4_总成本费用!J$22)/(0_参数!$C$101/0_参数!$C$99),0) -> 51.1 | K9: =IF(K$4="运营",(4_总成本费用!K$17+4_总成本费用!K$22)/(0_参数!$C$101/0_参数!$C$99),0) -> 51.1 | ... U9: =IF(U$4="运营",(4_总成本费用!U$17+4_总成本费用!U$22)/(0_参数!$C$101/0_参数!$C$99),0) -> 0
A10: 1 | B10: 流动资产合计 | C10: 万元 | D10: =D7+D8+D9 -> 0 | E10: =E7+E8+E9 -> 1879.693 | F10: =F7+F8+F9 -> 2108.1003 | G10: =G7+G8+G9 -> 2108.1003 | H10: =H7+H8+H9 -> 2108.1003 | I10: =I7+I8+I9 -> 2108.1003 | J10: =J7+J8+J9 -> 2108.1003 | K10: =K7+K8+K9 -> 2108.1003 | ... U10: =U7+U8+U9 -> 0
A11: 2.1 | B11: 应付账款（燃料动力 + 专线 + 外包） | C11: 万元 | D11: =IF(D$4="运营",(4_总成本费用!D$16+4_总成本费用!D$13+4_总成本费用!D$18)/(0_参数!$C$101/0_参数!$C$100),0) -> 0 | E11: =IF(E$4="运营",(4_总成本费用!E$16+4_总成本费用!E$13+4_总成本费用!E$18)/(0_参数!$C$101/0_参数!$C$100),0) -> 147.83833 | F11: =IF(F$4="运营",(4_总成本费用!F$16+4_总成本费用!F$13+4_总成本费用!F$18)/(0_参数!$C$101/0_参数!$C$100),0) -> 154.35874 | G11: =IF(G$4="运营",(4_总成本费用!G$16+4_总成本费用!G$13+4_总成本费用!G$18)/(0_参数!$C$101/0_参数!$C$100),0) -> 154.35874 | H11: =IF(H$4="运营",(4_总成本费用!H$16+4_总成本费用!H$13+4_总成本费用!H$18)/(0_参数!$C$101/0_参数!$C$100),0) -> 154.35874 | I11: =IF(I$4="运营",(4_总成本费用!I$16+4_总成本费用!I$13+4_总成本费用!I$18)/(0_参数!$C$101/0_参数!$C$100),0) -> 154.35874 | J11: =IF(J$4="运营",(4_总成本费用!J$16+4_总成本费用!J$13+4_总成本费用!J$18)/(0_参数!$C$101/0_参数!$C$100),0) -> 154.35874 | K11: =IF(K$4="运营",(4_总成本费用!K$16+4_总成本费用!K$13+4_总成本费用!K$18)/(0_参数!$C$101/0_参数!$C$100),0) -> 154.35874 | ... U11: =IF(U$4="运营",(4_总成本费用!U$16+4_总成本费用!U$13+4_总成本费用!U$18)/(0_参数!$C$101/0_参数!$C$100),0) -> 0
A12: 2 | B12: 流动负债合计 | C12: 万元 | D12: =D11 -> 0 | E12: =E11 -> 147.83833 | F12: =F11 -> 154.35874 | G12: =G11 -> 154.35874 | H12: =H11 -> 154.35874 | I12: =I11 -> 154.35874 | J12: =J11 -> 154.35874 | K12: =K11 -> 154.35874 | ... U12: =U11 -> 0
A13: 3 | B13: 流动资金 = 1 − 2 | C13: 万元 | D13: =D10-D12 -> 0 | E13: =E10-E12 -> 1731.8547 | F13: =F10-F12 -> 1953.7415 | G13: =G10-G12 -> 1953.7415 | H13: =H10-H12 -> 1953.7415 | I13: =I10-I12 -> 1953.7415 | J13: =J10-J12 -> 1953.7415 | K13: =K10-K12 -> 1953.7415 | ... U13: =U10-U12 -> 0
A14: 4 | B14: 流动资金本年增加额 | C14: 万元 | D14: =IF(D$4="运营",D13,0) -> 0 | E14: =IF(E$4="运营",E13-IF(1=0,0,D13),0) -> 1731.8547 | F14: =IF(F$4="运营",F13-IF(2=0,0,E13),0) -> 221.88679 | G14: =IF(G$4="运营",G13-IF(3=0,0,F13),0) -> 0 | H14: =IF(H$4="运营",H13-IF(4=0,0,G13),0) -> 0 | I14: =IF(I$4="运营",I13-IF(5=0,0,H13),0) -> 0 | J14: =IF(J$4="运营",J13-IF(6=0,0,I13),0) -> 0 | K14: =IF(K$4="运营",K13-IF(7=0,0,J13),0) -> 0 | L14: =IF(L$4="运营",L13-IF(8=0,0,K13),0) -> 0 | M14: =IF(M$4="运营",M13-IF(9=0,0,L13),0) -> 0 | N14: =IF(N$4="运营",N13-IF(10=0,0,M13),0) -> 0 | O14: =IF(O$4="运营",O13-IF(11=0,0,N13),0) -> 0 | P14: =IF(P$4="运营",P13-IF(12=0,0,O13),0) -> 0 | Q14: =IF(Q$4="运营",Q13-IF(13=0,0,P13),0) -> 0 | R14: =IF(R$4="运营",R13-IF(14=0,0,Q13),0) -> 0 | S14: =IF(S$4="运营",S13-IF(15=0,0,R13),0) -> 0 | T14: =IF(T$4="运营",T13-IF(16=0,0,S13),0) -> 0 | U14: =IF(U$4="运营",U13-IF(17=0,0,T13),0) -> 0 | V14: =SUM(D14:U14) -> 1953.7415
B15: 正常年流动资金 = 运营第 A10 年 | V15: =INDEX(D13:U13,0_参数!$C$9+0_参数!$C$15) -> 1953.7415
B16: 铺底流动资金 = 正常年流动资金 × (1 − 借款比例) | V16: =V15*(1-0_参数!$C$93) -> 586.12245
A17: 5 | B17: 流动资金借款本年增加 | C17: 万元 | D17: =D14*0_参数!$C$93 -> 0 | E17: =E14*0_参数!$C$93 -> 1212.2983 | F17: =F14*0_参数!$C$93 -> 155.32075 | G17: =G14*0_参数!$C$93 -> 0 | H17: =H14*0_参数!$C$93 -> 0 | I17: =I14*0_参数!$C$93 -> 0 | J17: =J14*0_参数!$C$93 -> 0 | K17: =K14*0_参数!$C$93 -> 0 | ... U17: =U14*0_参数!$C$93 -> 0 | V17: =SUM(D17:U17) -> 1367.6191
A18: 6 | B18: 流动资金自有资金本年增加 | C18: 万元 | D18: =D14*(1-0_参数!$C$93) -> 0 | E18: =E14*(1-0_参数!$C$93) -> 519.55642 | F18: =F14*(1-0_参数!$C$93) -> 66.566038 | G18: =G14*(1-0_参数!$C$93) -> 0 | H18: =H14*(1-0_参数!$C$93) -> 0 | I18: =I14*(1-0_参数!$C$93) -> 0 | J18: =J14*(1-0_参数!$C$93) -> 0 | K18: =K14*(1-0_参数!$C$93) -> 0 | ... U18: =U14*(1-0_参数!$C$93) -> 0 | V18: =SUM(D18:U18) -> 586.12245
A19: 7 | B19: 计算期末回收流动资金（供附表 8） | C19: 万元 | D19: =IF(D$3=0_参数!$C$9+0_参数!$C$10,D13,0) -> 0 | E19: =IF(E$3=0_参数!$C$9+0_参数!$C$10,E13,0) -> 0 | F19: =IF(F$3=0_参数!$C$9+0_参数!$C$10,F13,0) -> 0 | G19: =IF(G$3=0_参数!$C$9+0_参数!$C$10,G13,0) -> 0 | H19: =IF(H$3=0_参数!$C$9+0_参数!$C$10,H13,0) -> 0 | I19: =IF(I$3=0_参数!$C$9+0_参数!$C$10,I13,0) -> 0 | J19: =IF(J$3=0_参数!$C$9+0_参数!$C$10,J13,0) -> 0 | K19: =IF(K$3=0_参数!$C$9+0_参数!$C$10,K13,0) -> 0 | ... U19: =IF(U$3=0_参数!$C$9+0_参数!$C$10,U13,0) -> 0 | V19: =SUM(D19:U19) -> 1953.7415

Sheet 3_资金筹措
A1: 附表 3 投资使用计划与资金筹措表
A2: 单位：万元。建设投资按参数 A6–A8 比例分年投入；资本金优先用于建设投资，其余为长期借款
A3: 序号 | B3: 项目 \ 年份 | C3: 单位/说明 | D3: 1 | E3: =D3+1 -> 2 | F3: =E3+1 -> 3 | G3: =F3+1 -> 4 | H3: =G3+1 -> 5 | I3: =H3+1 -> 6 | J3: =I3+1 -> 7 | K3: =J3+1 -> 8 | L3: =K3+1 -> 9 | ... U3: =T3+1 -> 18 | V3: 合计/平均
B4: 阶段 | D4: =IF(D$3<=0_参数!$C$9,"建设",IF(D$3<=0_参数!$C$9+0_参数!$C$10,"运营","")) -> 建设 | E4: =IF(E$3<=0_参数!$C$9,"建设",IF(E$3<=0_参数!$C$9+0_参数!$C$10,"运营","")) -> 运营 | F4: =IF(F$3<=0_参数!$C$9,"建设",IF(F$3<=0_参数!$C$9+0_参数!$C$10,"运营","")) -> 运营 | G4: =IF(G$3<=0_参数!$C$9,"建设",IF(G$3<=0_参数!$C$9+0_参数!$C$10,"运营","")) -> 运营 | H4: =IF(H$3<=0_参数!$C$9,"建设",IF(H$3<=0_参数!$C$9+0_参数!$C$10,"运营","")) -> 运营 | I4: =IF(I$3<=0_参数!$C$9,"建设",IF(I$3<=0_参数!$C$9+0_参数!$C$10,"运营","")) -> 运营 | J4: =IF(J$3<=0_参数!$C$9,"建设",IF(J$3<=0_参数!$C$9+0_参数!$C$10,"运营","")) -> 运营 | K4: =IF(K$3<=0_参数!$C$9,"建设",IF(K$3<=0_参数!$C$9+0_参数!$C$10,"运营","")) -> 运营 | ... U4: =IF(U$3<=0_参数!$C$9,"建设",IF(U$3<=0_参数!$C$9+0_参数!$C$10,"运营",""))
B5: 运营年序号 | D5: =IF(D$4="运营",D$3-0_参数!$C$9,0) -> 0 | E5: =IF(E$4="运营",E$3-0_参数!$C$9,0) -> 1 | F5: =IF(F$4="运营",F$3-0_参数!$C$9,0) -> 2 | G5: =IF(G$4="运营",G$3-0_参数!$C$9,0) -> 3 | H5: =IF(H$4="运营",H$3-0_参数!$C$9,0) -> 4 | I5: =IF(I$4="运营",I$3-0_参数!$C$9,0) -> 5 | J5: =IF(J$4="运营",J$3-0_参数!$C$9,0) -> 6 | K5: =IF(K$4="运营",K$3-0_参数!$C$9,0) -> 7 | ... U5: =IF(U$4="运营",U$3-0_参数!$C$9,0) -> 0
B6: 建设年序号 | D6: =IF(D$4="建设",D$3,0) -> 1 | E6: =IF(E$4="建设",E$3,0) -> 0 | F6: =IF(F$4="建设",F$3,0) -> 0 | G6: =IF(G$4="建设",G$3,0) -> 0 | H6: =IF(H$4="建设",H$3,0) -> 0 | I6: =IF(I$4="建设",I$3,0) -> 0 | J6: =IF(J$4="建设",J$3,0) -> 0 | K6: =IF(K$4="建设",K$3,0) -> 0 | ... U6: =IF(U$4="建设",U$3,0) -> 0
B7: 建设投资年投入比例 | D7: =IF(D$6=1,0_参数!$C$11,IF(D$6=2,0_参数!$C$12,IF(D$6=3,0_参数!$C$13,0))) -> 1 | E7: =IF(E$6=1,0_参数!$C$11,IF(E$6=2,0_参数!$C$12,IF(E$6=3,0_参数!$C$13,0))) -> 0 | F7: =IF(F$6=1,0_参数!$C$11,IF(F$6=2,0_参数!$C$12,IF(F$6=3,0_参数!$C$13,0))) -> 0 | G7: =IF(G$6=1,0_参数!$C$11,IF(G$6=2,0_参数!$C$12,IF(G$6=3,0_参数!$C$13,0))) -> 0 | H7: =IF(H$6=1,0_参数!$C$11,IF(H$6=2,0_参数!$C$12,IF(H$6=3,0_参数!$C$13,0))) -> 0 | I7: =IF(I$6=1,0_参数!$C$11,IF(I$6=2,0_参数!$C$12,IF(I$6=3,0_参数!$C$13,0))) -> 0 | J7: =IF(J$6=1,0_参数!$C$11,IF(J$6=2,0_参数!$C$12,IF(J$6=3,0_参数!$C$13,0))) -> 0 | K7: =IF(K$6=1,0_参数!$C$11,IF(K$6=2,0_参数!$C$12,IF(K$6=3,0_参数!$C$13,0))) -> 0 | ... U7: =IF(U$6=1,0_参数!$C$11,IF(U$6=2,0_参数!$C$12,IF(U$6=3,0_参数!$C$13,0))) -> 0 | V7: =SUM(D7:U7) -> 1
A8: 1.1 | B8: 建设投资 | C8: 万元 | D8: =1_总投资估算!$G$29*D7 -> 122417.01 | E8: =1_总投资估算!$G$29*E7 -> 0 | F8: =1_总投资估算!$G$29*F7 -> 0 | G8: =1_总投资估算!$G$29*G7 -> 0 | H8: =1_总投资估算!$G$29*H7 -> 0 | I8: =1_总投资估算!$G$29*I7 -> 0 | J8: =1_总投资估算!$G$29*J7 -> 0 | K8: =1_总投资估算!$G$29*K7 -> 0 | ... U8: =1_总投资估算!$G$29*U7 -> 0 | V8: =SUM(D8:U8) -> 122417.01
A9: 1.2 | B9: 建设期借款利息 | C9: 万元 | D9: =11_还本付息!D$9 -> 1536.2551 | E9: =11_还本付息!E$9 -> 0 | F9: =11_还本付息!F$9 -> 0 | G9: =11_还本付息!G$9 -> 0 | H9: =11_还本付息!H$9 -> 0 | I9: =11_还本付息!I$9 -> 0 | J9: =11_还本付息!J$9 -> 0 | K9: =11_还本付息!K$9 -> 0 | ... U9: =11_还本付息!U$9 -> 0 | V9: =SUM(D9:U9) -> 1536.2551
A10: 1.3 | B10: 新增流动资金 | C10: 万元 | D10: =2_流动资金!D$14 -> 0 | E10: =2_流动资金!E$14 -> 1731.8547 | F10: =2_流动资金!F$14 -> 221.88679 | G10: =2_流动资金!G$14 -> 0 | H10: =2_流动资金!H$14 -> 0 | I10: =2_流动资金!I$14 -> 0 | J10: =2_流动资金!J$14 -> 0 | K10: =2_流动资金!K$14 -> 0 | ... U10: =2_流动资金!U$14 -> 0 | V10: =SUM(D10:U10) -> 1953.7415
A11: 1 | B11: 总资金（含全部流动资金） | C11: 万元 | D11: =D8+D9+D10 -> 123953.26 | E11: =E8+E9+E10 -> 1731.8547 | F11: =F8+F9+F10 -> 221.88679 | G11: =G8+G9+G10 -> 0 | H11: =H8+H9+H10 -> 0 | I11: =I8+I9+I10 -> 0 | J11: =J8+J9+J10 -> 0 | K11: =K8+K9+K10 -> 0 | ... U11: =U8+U9+U10 -> 0 | V11: =SUM(D11:U11) -> 125907
A12: 2.1.1 | B12: 资本金-用于建设投资 | C12: 万元 | D12: =MIN(0_参数!$C$89,1_总投资估算!$G$29)*D7 -> 20000 | E12: =MIN(0_参数!$C$89,1_总投资估算!$G$29)*E7 -> 0 | F12: =MIN(0_参数!$C$89,1_总投资估算!$G$29)*F7 -> 0 | G12: =MIN(0_参数!$C$89,1_总投资估算!$G$29)*G7 -> 0 | H12: =MIN(0_参数!$C$89,1_总投资估算!$G$29)*H7 -> 0 | I12: =MIN(0_参数!$C$89,1_总投资估算!$G$29)*I7 -> 0 | J12: =MIN(0_参数!$C$89,1_总投资估算!$G$29)*J7 -> 0 | K12: =MIN(0_参数!$C$89,1_总投资估算!$G$29)*K7 -> 0 | ... U12: =MIN(0_参数!$C$89,1_总投资估算!$G$29)*U7 -> 0 | V12: =SUM(D12:U12) -> 20000
A13: 2.1.2 | B13: 资本金-用于建设期利息 | C13: 万元 | D13: =IF(0_参数!$C$92=0,D9,0) -> 0 | E13: =IF(0_参数!$C$92=0,E9,0) -> 0 | F13: =IF(0_参数!$C$92=0,F9,0) -> 0 | G13: =IF(0_参数!$C$92=0,G9,0) -> 0 | H13: =IF(0_参数!$C$92=0,H9,0) -> 0 | I13: =IF(0_参数!$C$92=0,I9,0) -> 0 | J13: =IF(0_参数!$C$92=0,J9,0) -> 0 | K13: =IF(0_参数!$C$92=0,K9,0) -> 0 | ... U13: =IF(0_参数!$C$92=0,U9,0) -> 0 | V13: =SUM(D13:U13) -> 0
A14: 2.1.3 | B14: 资本金-用于流动资金 | C14: 万元 | D14: =2_流动资金!D$18 -> 0 | E14: =2_流动资金!E$18 -> 519.55642 | F14: =2_流动资金!F$18 -> 66.566038 | G14: =2_流动资金!G$18 -> 0 | H14: =2_流动资金!H$18 -> 0 | I14: =2_流动资金!I$18 -> 0 | J14: =2_流动资金!J$18 -> 0 | K14: =2_流动资金!K$18 -> 0 | ... U14: =2_流动资金!U$18 -> 0 | V14: =SUM(D14:U14) -> 586.12245
A15: 2.1 | B15: 企业自筹资本金 小计 | C15: 万元 | D15: =D12+D13+D14 -> 20000 | E15: =E12+E13+E14 -> 519.55642 | F15: =F12+F13+F14 -> 66.566038 | G15: =G12+G13+G14 -> 0 | H15: =H12+H13+H14 -> 0 | I15: =I12+I13+I14 -> 0 | J15: =J12+J13+J14 -> 0 | K15: =K12+K13+K14 -> 0 | ... U15: =U12+U13+U14 -> 0 | V15: =SUM(D15:U15) -> 20586.122
A16: 2.2.1 | B16: 长期借款（建设投资） | C16: 万元 | D16: =D8-D12 -> 102417.01 | E16: =E8-E12 -> 0 | F16: =F8-F12 -> 0 | G16: =G8-G12 -> 0 | H16: =H8-H12 -> 0 | I16: =I8-I12 -> 0 | J16: =J8-J12 -> 0 | K16: =K8-K12 -> 0 | ... U16: =U8-U12 -> 0 | V16: =SUM(D16:U16) -> 102417.01
A17: 2.2.2 | B17: 长期借款（资本化建设期利息） | C17: 万元 | D17: =IF(0_参数!$C$92=1,D9,0) -> 1536.2551 | E17: =IF(0_参数!$C$92=1,E9,0) -> 0 | F17: =IF(0_参数!$C$92=1,F9,0) -> 0 | G17: =IF(0_参数!$C$92=1,G9,0) -> 0 | H17: =IF(0_参数!$C$92=1,H9,0) -> 0 | I17: =IF(0_参数!$C$92=1,I9,0) -> 0 | J17: =IF(0_参数!$C$92=1,J9,0) -> 0 | K17: =IF(0_参数!$C$92=1,K9,0) -> 0 | ... U17: =IF(0_参数!$C$92=1,U9,0) -> 0 | V17: =SUM(D17:U17) -> 1536.2551
A18: 2.2.3 | B18: 流动资金借款 | C18: 万元 | D18: =2_流动资金!D$17 -> 0 | E18: =2_流动资金!E$17 -> 1212.2983 | F18: =2_流动资金!F$17 -> 155.32075 | G18: =2_流动资金!G$17 -> 0 | H18: =2_流动资金!H$17 -> 0 | I18: =2_流动资金!I$17 -> 0 | J18: =2_流动资金!J$17 -> 0 | K18: =2_流动资金!K$17 -> 0 | ... U18: =2_流动资金!U$17 -> 0 | V18: =SUM(D18:U18) -> 1367.6191
A19: 2.2 | B19: 债务资金 小计 | C19: 万元 | D19: =D16+D17+D18 -> 103953.26 | E19: =E16+E17+E18 -> 1212.2983 | F19: =F16+F17+F18 -> 155.32075 | G19: =G16+G17+G18 -> 0 | H19: =H16+H17+H18 -> 0 | I19: =I16+I17+I18 -> 0 | J19: =J16+J17+J18 -> 0 | K19: =K16+K17+K18 -> 0 | ... U19: =U16+U17+U18 -> 0 | V19: =SUM(D19:U19) -> 105320.88
A20: 2 | B20: 资金筹措合计 | C20: 万元 | D20: =D15+D19 -> 123953.26 | E20: =E15+E19 -> 1731.8547 | F20: =F15+F19 -> 221.88679 | G20: =G15+G19 -> 0 | H20: =H15+H19 -> 0 | I20: =I15+I19 -> 0 | J20: =J15+J19 -> 0 | K20: =K15+K19 -> 0 | ... U20: =U15+U19 -> 0 | V20: =SUM(D20:U20) -> 125907
B21: 校核：筹措 − 总资金（应为 0） | C21: 万元 | D21: =D20-D11 -> 0 | E21: =E20-E11 -> 0 | F21: =F20-F11 -> 0 | G21: =G20-G11 -> 0 | H21: =H20-H11 -> 0 | I21: =I20-I11 -> 0 | J21: =J20-J11 -> 0 | K21: =K20-K11 -> 0 | ... U21: =U20-U11 -> 0 | V21: =SUM(D21:U21) -> 0

Sheet 4_总成本费用
A1: 附表 4 总成本费用估算表
A2: 单位：万元（人民币，不含税；含税输入按参数税率还原）
A3: 序号 | B3: 项目 \ 年份 | C3: 单位/说明 | D3: 1 | E3: =D3+1 -> 2 | F3: =E3+1 -> 3 | G3: =F3+1 -> 4 | H3: =G3+1 -> 5 | I3: =H3+1 -> 6 | J3: =I3+1 -> 7 | K3: =J3+1 -> 8 | L3: =K3+1 -> 9 | ... U3: =T3+1 -> 18 | V3: 合计/平均
B4: 阶段 | D4: =IF(D$3<=0_参数!$C$9,"建设",IF(D$3<=0_参数!$C$9+0_参数!$C$10,"运营","")) -> 建设 | E4: =IF(E$3<=0_参数!$C$9,"建设",IF(E$3<=0_参数!$C$9+0_参数!$C$10,"运营","")) -> 运营 | F4: =IF(F$3<=0_参数!$C$9,"建设",IF(F$3<=0_参数!$C$9+0_参数!$C$10,"运营","")) -> 运营 | G4: =IF(G$3<=0_参数!$C$9,"建设",IF(G$3<=0_参数!$C$9+0_参数!$C$10,"运营","")) -> 运营 | H4: =IF(H$3<=0_参数!$C$9,"建设",IF(H$3<=0_参数!$C$9+0_参数!$C$10,"运营","")) -> 运营 | I4: =IF(I$3<=0_参数!$C$9,"建设",IF(I$3<=0_参数!$C$9+0_参数!$C$10,"运营","")) -> 运营 | J4: =IF(J$3<=0_参数!$C$9,"建设",IF(J$3<=0_参数!$C$9+0_参数!$C$10,"运营","")) -> 运营 | K4: =IF(K$3<=0_参数!$C$9,"建设",IF(K$3<=0_参数!$C$9+0_参数!$C$10,"运营","")) -> 运营 | ... U4: =IF(U$3<=0_参数!$C$9,"建设",IF(U$3<=0_参数!$C$9+0_参数!$C$10,"运营",""))
B5: 运营年序号 | D5: =IF(D$4="运营",D$3-0_参数!$C$9,0) -> 0 | E5: =IF(E$4="运营",E$3-0_参数!$C$9,0) -> 1 | F5: =IF(F$4="运营",F$3-0_参数!$C$9,0) -> 2 | G5: =IF(G$4="运营",G$3-0_参数!$C$9,0) -> 3 | H5: =IF(H$4="运营",H$3-0_参数!$C$9,0) -> 4 | I5: =IF(I$4="运营",I$3-0_参数!$C$9,0) -> 5 | J5: =IF(J$4="运营",J$3-0_参数!$C$9,0) -> 6 | K5: =IF(K$4="运营",K$3-0_参数!$C$9,0) -> 7 | ... U5: =IF(U$4="运营",U$3-0_参数!$C$9,0) -> 0
B6: 建设年序号 | D6: =IF(D$4="建设",D$3,0) -> 1 | E6: =IF(E$4="建设",E$3,0) -> 0 | F6: =IF(F$4="建设",F$3,0) -> 0 | G6: =IF(G$4="建设",G$3,0) -> 0 | H6: =IF(H$4="建设",H$3,0) -> 0 | I6: =IF(I$4="建设",I$3,0) -> 0 | J6: =IF(J$4="建设",J$3,0) -> 0 | K6: =IF(K$4="建设",K$3,0) -> 0 | ... U6: =IF(U$4="建设",U$3,0) -> 0
B7: 投产比例 | D7: =IF(D$5>0,INDEX(0_参数!$D$126:$R$126,D$5),0) -> 0 | E7: =IF(E$5>0,INDEX(0_参数!$D$126:$R$126,E$5),0) -> 1 | F7: =IF(F$5>0,INDEX(0_参数!$D$126:$R$126,F$5),0) -> 1 | G7: =IF(G$5>0,INDEX(0_参数!$D$126:$R$126,G$5),0) -> 1 | H7: =IF(H$5>0,INDEX(0_参数!$D$126:$R$126,H$5),0) -> 1 | I7: =IF(I$5>0,INDEX(0_参数!$D$126:$R$126,I$5),0) -> 1 | J7: =IF(J$5>0,INDEX(0_参数!$D$126:$R$126,J$5),0) -> 1 | K7: =IF(K$5>0,INDEX(0_参数!$D$126:$R$126,K$5),0) -> 1 | ... U7: =IF(U$5>0,INDEX(0_参数!$D$126:$R$126,U$5),0) -> 0
B8: 售卖比例（含敏感性） | D8: =MIN(1,IF(D$5>0,INDEX(0_参数!$D$127:$R$127,D$5),0)*0_参数!$C$48) -> 0 | E8: =MIN(1,IF(E$5>0,INDEX(0_参数!$D$127:$R$127,E$5),0)*0_参数!$C$48) -> 0.8 | F8: =MIN(1,IF(F$5>0,INDEX(0_参数!$D$127:$R$127,F$5),0)*0_参数!$C$48) -> 0.9 | G8: =MIN(1,IF(G$5>0,INDEX(0_参数!$D$127:$R$127,G$5),0)*0_参数!$C$48) -> 0.9 | H8: =MIN(1,IF(H$5>0,INDEX(0_参数!$D$127:$R$127,H$5),0)*0_参数!$C$48) -> 0.9 | I8: =MIN(1,IF(I$5>0,INDEX(0_参数!$D$127:$R$127,I$5),0)*0_参数!$C$48) -> 0.9 | J8: =MIN(1,IF(J$5>0,INDEX(0_参数!$D$127:$R$127,J$5),0)*0_参数!$C$48) -> 0.9 | K8: =MIN(1,IF(K$5>0,INDEX(0_参数!$D$127:$R$127,K$5),0)*0_参数!$C$48) -> 0.9 | ... U8: =MIN(1,IF(U$5>0,INDEX(0_参数!$D$127:$R$127,U$5),0)*0_参数!$C$48) -> 0
B9: IT 运行负载率 | D9: =IF(D$5>0,INDEX(0_参数!$D$128:$R$128,D$5),0) -> 0 | E9: =IF(E$5>0,INDEX(0_参数!$D$128:$R$128,E$5),0) -> 0.9 | F9: =IF(F$5>0,INDEX(0_参数!$D$128:$R$128,F$5),0) -> 0.9 | G9: =IF(G$5>0,INDEX(0_参数!$D$128:$R$128,G$5),0) -> 0.9 | H9: =IF(H$5>0,INDEX(0_参数!$D$128:$R$128,H$5),0) -> 0.9 | I9: =IF(I$5>0,INDEX(0_参数!$D$128:$R$128,I$5),0) -> 0.9 | J9: =IF(J$5>0,INDEX(0_参数!$D$128:$R$128,J$5),0) -> 0.9 | K9: =IF(K$5>0,INDEX(0_参数!$D$128:$R$128,K$5),0) -> 0.9 | ... U9: =IF(U$5>0,INDEX(0_参数!$D$128:$R$128,U$5),0) -> 0
B10: IT 年用电量 | C10: 万kWh | D10: =IF(D$4="运营",0_参数!$C$20*D7*D8*D9*0_参数!$C$36/10000,0) -> 0 | E10: =IF(E$4="运营",0_参数!$C$20*E7*E8*E9*0_参数!$C$36/10000,0) -> 1332.0806 | F10: =IF(F$4="运营",0_参数!$C$20*F7*F8*F9*0_参数!$C$36/10000,0) -> 1498.5907 | G10: =IF(G$4="运营",0_参数!$C$20*G7*G8*G9*0_参数!$C$36/10000,0) -> 1498.5907 | H10: =IF(H$4="运营",0_参数!$C$20*H7*H8*H9*0_参数!$C$36/10000,0) -> 1498.5907 | I10: =IF(I$4="运营",0_参数!$C$20*I7*I8*I9*0_参数!$C$36/10000,0) -> 1498.5907 | J10: =IF(J$4="运营",0_参数!$C$20*J7*J8*J9*0_参数!$C$36/10000,0) -> 1498.5907 | K10: =IF(K$4="运营",0_参数!$C$20*K7*K8*K9*0_参数!$C$36/10000,0) -> 1498.5907 | ... U10: =IF(U$4="运营",0_参数!$C$20*U7*U8*U9*0_参数!$C$36/10000,0) -> 0 | V10: =IFERROR(SUMIF(D$4:U$4,"运营",D10:U10)/0_参数!$C$10,0) -> 1481.9397
B11: 项目年总用电量 | C11: 万kWh | D11: =IF(D$4="运营",D10*0_参数!$C$29+0_参数!$C$32*0_参数!$C$35*0_参数!$C$36/10000,0) -> 0 | E11: =IF(E$4="运营",E10*0_参数!$C$29+0_参数!$C$32*0_参数!$C$35*0_参数!$C$36/10000,0) -> 1595.5072 | F11: =IF(F$4="运营",F10*0_参数!$C$29+0_参数!$C$32*0_参数!$C$35*0_参数!$C$36/10000,0) -> 1791.989 | G11: =IF(G$4="运营",G10*0_参数!$C$29+0_参数!$C$32*0_参数!$C$35*0_参数!$C$36/10000,0) -> 1791.989 | H11: =IF(H$4="运营",H10*0_参数!$C$29+0_参数!$C$32*0_参数!$C$35*0_参数!$C$36/10000,0) -> 1791.989 | I11: =IF(I$4="运营",I10*0_参数!$C$29+0_参数!$C$32*0_参数!$C$35*0_参数!$C$36/10000,0) -> 1791.989 | J11: =IF(J$4="运营",J10*0_参数!$C$29+0_参数!$C$32*0_参数!$C$35*0_参数!$C$36/10000,0) -> 1791.989 | K11: =IF(K$4="运营",K10*0_参数!$C$29+0_参数!$C$32*0_参数!$C$35*0_参数!$C$36/10000,0) -> 1791.989 | ... U11: =IF(U$4="运营",U10*0_参数!$C$29+0_参数!$C$32*0_参数!$C$35*0_参数!$C$36/10000,0) -> 0 | V11: =IFERROR(SUMIF(D$4:U$4,"运营",D11:U11)/0_参数!$C$10,0) -> 1772.3409
B12: 年用水量 | C12: m³ | D12: =IF(D$4="运营",0_参数!$C$37*D7,0) -> 0 | E12: =IF(E$4="运营",0_参数!$C$37*E7,0) -> 16000 | F12: =IF(F$4="运营",0_参数!$C$37*F7,0) -> 16000 | G12: =IF(G$4="运营",0_参数!$C$37*G7,0) -> 16000 | H12: =IF(H$4="运营",0_参数!$C$37*H7,0) -> 16000 | I12: =IF(I$4="运营",0_参数!$C$37*I7,0) -> 16000 | J12: =IF(J$4="运营",0_参数!$C$37*J7,0) -> 16000 | K12: =IF(K$4="运营",0_参数!$C$37*K7,0) -> 16000 | ... U12: =IF(U$4="运营",0_参数!$C$37*U7,0) -> 0 | V12: =IFERROR(SUMIF(D$4:U$4,"运营",D12:U12)/0_参数!$C$10,0) -> 16000
A13: 1 | B13: 专线及网络带宽费 | C13: 万元 | D13: =IF(D$4="运营",0_参数!$C$54*0_参数!$C$55/(1+0_参数!$C$56),0) -> 0 | E13: =IF(E$4="运营",0_参数!$C$54*0_参数!$C$55/(1+0_参数!$C$56),0) -> 566.03774 | F13: =IF(F$4="运营",0_参数!$C$54*0_参数!$C$55/(1+0_参数!$C$56),0) -> 566.03774 | G13: =IF(G$4="运营",0_参数!$C$54*0_参数!$C$55/(1+0_参数!$C$56),0) -> 566.03774 | H13: =IF(H$4="运营",0_参数!$C$54*0_参数!$C$55/(1+0_参数!$C$56),0) -> 566.03774 | I13: =IF(I$4="运营",0_参数!$C$54*0_参数!$C$55/(1+0_参数!$C$56),0) -> 566.03774 | J13: =IF(J$4="运营",0_参数!$C$54*0_参数!$C$55/(1+0_参数!$C$56),0) -> 566.03774 | K13: =IF(K$4="运营",0_参数!$C$54*0_参数!$C$55/(1+0_参数!$C$56),0) -> 566.03774 | ... U13: =IF(U$4="运营",0_参数!$C$54*0_参数!$C$55/(1+0_参数!$C$56),0) -> 0 | V13: =IFERROR(SUMIF(D$4:U$4,"运营",D13:U13)/0_参数!$C$10,0) -> 566.03774
A14: 2.1 | B14: 外购电力 | C14: 万元 | D14: =D11*0_参数!$C$38*0_参数!$C$49/(1+0_参数!$C$39) -> 0 | E14: =E11*0_参数!$C$38*0_参数!$C$49/(1+0_参数!$C$39) -> 635.37896 | F14: =F11*0_参数!$C$38*0_参数!$C$49/(1+0_参数!$C$39) -> 713.62396 | G14: =G11*0_参数!$C$38*0_参数!$C$49/(1+0_参数!$C$39) -> 713.62396 | H14: =H11*0_参数!$C$38*0_参数!$C$49/(1+0_参数!$C$39) -> 713.62396 | I14: =I11*0_参数!$C$38*0_参数!$C$49/(1+0_参数!$C$39) -> 713.62396 | J14: =J11*0_参数!$C$38*0_参数!$C$49/(1+0_参数!$C$39) -> 713.62396 | K14: =K11*0_参数!$C$38*0_参数!$C$49/(1+0_参数!$C$39) -> 713.62396 | ... U14: =U11*0_参数!$C$38*0_参数!$C$49/(1+0_参数!$C$39) -> 0 | V14: =IFERROR(SUMIF(D$4:U$4,"运营",D14:U14)/0_参数!$C$10,0) -> 705.79946
A15: 2.2 | B15: 外购水 | C15: 万元 | D15: =D12*0_参数!$C$40/(1+0_参数!$C$41)/10000 -> 0 | E15: =E12*0_参数!$C$40/(1+0_参数!$C$41)/10000 -> 6.6055046 | F15: =F12*0_参数!$C$40/(1+0_参数!$C$41)/10000 -> 6.6055046 | G15: =G12*0_参数!$C$40/(1+0_参数!$C$41)/10000 -> 6.6055046 | H15: =H12*0_参数!$C$40/(1+0_参数!$C$41)/10000 -> 6.6055046 | I15: =I12*0_参数!$C$40/(1+0_参数!$C$41)/10000 -> 6.6055046 | J15: =J12*0_参数!$C$40/(1+0_参数!$C$41)/10000 -> 6.6055046 | K15: =K12*0_参数!$C$40/(1+0_参数!$C$41)/10000 -> 6.6055046 | ... U15: =U12*0_参数!$C$40/(1+0_参数!$C$41)/10000 -> 0 | V15: =IFERROR(SUMIF(D$4:U$4,"运营",D15:U15)/0_参数!$C$10,0) -> 6.6055046
A16: 2 | B16: 外购燃料及动力 小计 | C16: 万元 | D16: =D14+D15 -> 0 | E16: =E14+E15 -> 641.98446 | F16: =F14+F15 -> 720.22946 | G16: =G14+G15 -> 720.22946 | H16: =H14+H15 -> 720.22946 | I16: =I14+I15 -> 720.22946 | J16: =J14+J15 -> 720.22946 | K16: =K14+K15 -> 720.22946 | ... U16: =U14+U15 -> 0 | V16: =IFERROR(SUMIF(D$4:U$4,"运营",D16:U16)/0_参数!$C$10,0) -> 712.40496
A17: 3 | B17: 工资及福利费 | C17: 万元 | D17: =IF(D$4="运营",0_参数!$C$68,0) -> 0 | E17: =IF(E$4="运营",0_参数!$C$68,0) -> 511 | F17: =IF(F$4="运营",0_参数!$C$68,0) -> 511 | G17: =IF(G$4="运营",0_参数!$C$68,0) -> 511 | H17: =IF(H$4="运营",0_参数!$C$68,0) -> 511 | I17: =IF(I$4="运营",0_参数!$C$68,0) -> 511 | J17: =IF(J$4="运营",0_参数!$C$68,0) -> 511 | K17: =IF(K$4="运营",0_参数!$C$68,0) -> 511 | ... U17: =IF(U$4="运营",0_参数!$C$68,0) -> 0 | V17: =IFERROR(SUMIF(D$4:U$4,"运营",D17:U17)/0_参数!$C$10,0) -> 511
A18: 4 | B18: 运维服务外包费 | C18: 万元 | D18: =IF(D$4="运营",0_参数!$C$57/(1+0_参数!$C$58),0) -> 0 | E18: =IF(E$4="运营",0_参数!$C$57/(1+0_参数!$C$58),0) -> 566.03774 | F18: =IF(F$4="运营",0_参数!$C$57/(1+0_参数!$C$58),0) -> 566.03774 | G18: =IF(G$4="运营",0_参数!$C$57/(1+0_参数!$C$58),0) -> 566.03774 | H18: =IF(H$4="运营",0_参数!$C$57/(1+0_参数!$C$58),0) -> 566.03774 | I18: =IF(I$4="运营",0_参数!$C$57/(1+0_参数!$C$58),0) -> 566.03774 | J18: =IF(J$4="运营",0_参数!$C$57/(1+0_参数!$C$58),0) -> 566.03774 | K18: =IF(K$4="运营",0_参数!$C$57/(1+0_参数!$C$58),0) -> 566.03774 | ... U18: =IF(U$4="运营",0_参数!$C$57/(1+0_参数!$C$58),0) -> 0 | V18: =IFERROR(SUMIF(D$4:U$4,"运营",D18:U18)/0_参数!$C$10,0) -> 566.03774
A19: 5 | B19: 硬件设备维保费 | C19: 万元 | D19: ='1-2_设备及软件'!$F$12/(1+0_参数!$C$58)*IF(D$5>0,INDEX(0_参数!$D$129:$R$129,D$5),0) -> 0 | E19: ='1-2_设备及软件'!$F$12/(1+0_参数!$C$58)*IF(E$5>0,INDEX(0_参数!$D$129:$R$129,E$5),0) -> 0 | F19: ='1-2_设备及软件'!$F$12/(1+0_参数!$C$58)*IF(F$5>0,INDEX(0_参数!$D$129:$R$129,F$5),0) -> 0 | G19: ='1-2_设备及软件'!$F$12/(1+0_参数!$C$58)*IF(G$5>0,INDEX(0_参数!$D$129:$R$129,G$5),0) -> 0 | H19: ='1-2_设备及软件'!$F$12/(1+0_参数!$C$58)*IF(H$5>0,INDEX(0_参数!$D$129:$R$129,H$5),0) -> 889.15094 | I19: ='1-2_设备及软件'!$F$12/(1+0_参数!$C$58)*IF(I$5>0,INDEX(0_参数!$D$129:$R$129,I$5),0) -> 889.15094 | J19: ='1-2_设备及软件'!$F$12/(1+0_参数!$C$58)*IF(J$5>0,INDEX(0_参数!$D$129:$R$129,J$5),0) -> 889.15094 | K19: ='1-2_设备及软件'!$F$12/(1+0_参数!$C$58)*IF(K$5>0,INDEX(0_参数!$D$129:$R$129,K$5),0) -> 1778.3019 | ... U19: ='1-2_设备及软件'!$F$12/(1+0_参数!$C$58)*IF(U$5>0,INDEX(0_参数!$D$129:$R$129,U$5),0) -> 0 | V19: =IFERROR(SUMIF(D$4:U$4,"运营",D19:U19)/0_参数!$C$10,0) -> 978.06604
A20: 6 | B20: 软件更新维护费 | C20: 万元 | D20: =IF(D$4="运营",'1-2_设备及软件'!$F$10/(1+0_参数!$C$58)*0_参数!$C$59,0) -> 0 | E20: =IF(E$4="运营",'1-2_设备及软件'!$F$10/(1+0_参数!$C$58)*0_参数!$C$59,0) -> 566.03774 | F20: =IF(F$4="运营",'1-2_设备及软件'!$F$10/(1+0_参数!$C$58)*0_参数!$C$59,0) -> 566.03774 | G20: =IF(G$4="运营",'1-2_设备及软件'!$F$10/(1+0_参数!$C$58)*0_参数!$C$59,0) -> 566.03774 | H20: =IF(H$4="运营",'1-2_设备及软件'!$F$10/(1+0_参数!$C$58)*0_参数!$C$59,0) -> 566.03774 | I20: =IF(I$4="运营",'1-2_设备及软件'!$F$10/(1+0_参数!$C$58)*0_参数!$C$59,0) -> 566.03774 | J20: =IF(J$4="运营",'1-2_设备及软件'!$F$10/(1+0_参数!$C$58)*0_参数!$C$59,0) -> 566.03774 | K20: =IF(K$4="运营",'1-2_设备及软件'!$F$10/(1+0_参数!$C$58)*0_参数!$C$59,0) -> 566.03774 | ... U20: =IF(U$4="运营",'1-2_设备及软件'!$F$10/(1+0_参数!$C$58)*0_参数!$C$59,0) -> 0 | V20: =IFERROR(SUMIF(D$4:U$4,"运营",D20:U20)/0_参数!$C$10,0) -> 566.03774
A21: 7 | B21: 机电设备维护费 | C21: 万元 | D21: =IF(D$4="运营",'1-2_设备及软件'!$F$22/(1+0_参数!$C$58)*0_参数!$C$60,0) -> 0 | E21: =IF(E$4="运营",'1-2_设备及软件'!$F$22/(1+0_参数!$C$58)*0_参数!$C$60,0) -> 126.43396 | F21: =IF(F$4="运营",'1-2_设备及软件'!$F$22/(1+0_参数!$C$58)*0_参数!$C$60,0) -> 126.43396 | G21: =IF(G$4="运营",'1-2_设备及软件'!$F$22/(1+0_参数!$C$58)*0_参数!$C$60,0) -> 126.43396 | H21: =IF(H$4="运营",'1-2_设备及软件'!$F$22/(1+0_参数!$C$58)*0_参数!$C$60,0) -> 126.43396 | I21: =IF(I$4="运营",'1-2_设备及软件'!$F$22/(1+0_参数!$C$58)*0_参数!$C$60,0) -> 126.43396 | J21: =IF(J$4="运营",'1-2_设备及软件'!$F$22/(1+0_参数!$C$58)*0_参数!$C$60,0) -> 126.43396 | K21: =IF(K$4="运营",'1-2_设备及软件'!$F$22/(1+0_参数!$C$58)*0_参数!$C$60,0) -> 126.43396 | ... U21: =IF(U$4="运营",'1-2_设备及软件'!$F$22/(1+0_参数!$C$58)*0_参数!$C$60,0) -> 0 | V21: =IFERROR(SUMIF(D$4:U$4,"运营",D21:U21)/0_参数!$C$10,0) -> 126.43396
A22: 8 | B22: 其他管理费用 | C22: 万元 | D22: =D17*0_参数!$C$69 -> 0 | E22: =E17*0_参数!$C$69 -> 102.2 | F22: =F17*0_参数!$C$69 -> 102.2 | G22: =G17*0_参数!$C$69 -> 102.2 | H22: =H17*0_参数!$C$69 -> 102.2 | I22: =I17*0_参数!$C$69 -> 102.2 | J22: =J17*0_参数!$C$69 -> 102.2 | K22: =K17*0_参数!$C$69 -> 102.2 | ... U22: =U17*0_参数!$C$69 -> 0 | V22: =IFERROR(SUMIF(D$4:U$4,"运营",D22:U22)/0_参数!$C$10,0) -> 102.2
A23: 9 | B23: 经营成本 = 1~8 | C23: 万元 | D23: =D13+D16+D17+D18+D19+D20+D21+D22 -> 0 | E23: =E13+E16+E17+E18+E19+E20+E21+E22 -> 3079.7316 | F23: =F13+F16+F17+F18+F19+F20+F21+F22 -> 3157.9766 | G23: =G13+G16+G17+G18+G19+G20+G21+G22 -> 3157.9766 | H23: =H13+H16+H17+H18+H19+H20+H21+H22 -> 4047.1276 | I23: =I13+I16+I17+I18+I19+I20+I21+I22 -> 4047.1276 | J23: =J13+J16+J17+J18+J19+J20+J21+J22 -> 4047.1276 | K23: =K13+K16+K17+K18+K19+K20+K21+K22 -> 4936.2785 | ... U23: =U13+U16+U17+U18+U19+U20+U21+U22 -> 0 | V23: =IFERROR(SUMIF(D$4:U$4,"运营",D23:U23)/0_参数!$C$10,0) -> 4128.2182
A24: 10 | B24: 折旧费 | C24: 万元 | D24: =5_折旧摊销!D$27 -> 0 | E24: =5_折旧摊销!E$27 -> 19019.003 | F24: =5_折旧摊销!F$27 -> 19019.003 | G24: =5_折旧摊销!G$27 -> 19019.003 | H24: =5_折旧摊销!H$27 -> 19019.003 | I24: =5_折旧摊销!I$27 -> 19019.003 | J24: =5_折旧摊销!J$27 -> 993.74712 | K24: =5_折旧摊销!K$27 -> 993.74712 | ... U24: =5_折旧摊销!U$27 -> 0 | V24: =IFERROR(SUMIF(D$4:U$4,"运营",D24:U24)/0_参数!$C$10,0) -> 10006.375
A25: 11 | B25: 摊销费 | C25: 万元 | D25: =5_折旧摊销!D$31 -> 0 | E25: =5_折旧摊销!E$31 -> 8.46 | F25: =5_折旧摊销!F$31 -> 8.46 | G25: =5_折旧摊销!G$31 -> 8.46 | H25: =5_折旧摊销!H$31 -> 8.46 | I25: =5_折旧摊销!I$31 -> 8.46 | J25: =5_折旧摊销!J$31 -> 0 | K25: =5_折旧摊销!K$31 -> 0 | ... U25: =5_折旧摊销!U$31 -> 0 | V25: =IFERROR(SUMIF(D$4:U$4,"运营",D25:U25)/0_参数!$C$10,0) -> 4.23
A26: 12 | B26: 利息支出（长期 + 流动资金借款） | C26: 万元 | D26: =IF(D$4="运营",11_还本付息!D$10+11_还本付息!D$19,0) -> 0 | E26: =IF(E$4="运营",11_还本付息!E$10+11_还本付息!E$19,0) -> 3139.8131 | F26: =IF(F$4="运营",11_还本付息!F$10+11_还本付息!F$19,0) -> 2851.8866 | G26: =IF(G$4="运营",11_还本付息!G$10+11_还本付息!G$19,0) -> 2542.7449 | H26: =IF(H$4="运营",11_还本付息!H$10+11_还本付息!H$19,0) -> 2230.8852 | I26: =IF(I$4="运营",11_还本付息!I$10+11_还本付息!I$19,0) -> 1919.0254 | J26: =IF(J$4="运营",11_还本付息!J$10+11_还本付息!J$19,0) -> 1607.1656 | K26: =IF(K$4="运营",11_还本付息!K$10+11_还本付息!K$19,0) -> 1295.3058 | ... U26: =IF(U$4="运营",11_还本付息!U$10+11_还本付息!U$19,0) -> 0 | V26: =IFERROR(SUMIF(D$4:U$4,"运营",D26:U26)/0_参数!$C$10,0) -> 1760.1585
A27: 13 | B27: 总成本费用 = 9 + 10 + 11 + 12 | C27: 万元 | D27: =D23+D24+D25+D26 -> 0 | E27: =E23+E24+E25+E26 -> 25247.008 | F27: =F23+F24+F25+F26 -> 25037.326 | G27: =G23+G24+G25+G26 -> 24728.185 | H27: =H23+H24+H25+H26 -> 25305.476 | I27: =I23+I24+I25+I26 -> 24993.616 | J27: =J23+J24+J25+J26 -> 6648.0403 | K27: =K23+K24+K25+K26 -> 7225.3314 | ... U27: =U23+U24+U25+U26 -> 0 | V27: =IFERROR(SUMIF(D$4:U$4,"运营",D27:U27)/0_参数!$C$10,0) -> 15898.982
B28: 其中：可变成本（燃料动力） | C28: 万元 | D28: =D16 -> 0 | E28: =E16 -> 641.98446 | F28: =F16 -> 720.22946 | G28: =G16 -> 720.22946 | H28: =H16 -> 720.22946 | I28: =I16 -> 720.22946 | J28: =J16 -> 720.22946 | K28: =K16 -> 720.22946 | ... U28: =U16 -> 0 | V28: =IFERROR(SUMIF(D$4:U$4,"运营",D28:U28)/0_参数!$C$10,0) -> 712.40496
B29: 其中：固定成本 | C29: 万元 | D29: =D27-D28 -> 0 | E29: =E27-E28 -> 24605.023 | F29: =F27-F28 -> 24317.097 | G29: =G27-G28 -> 24007.955 | H29: =H27-H28 -> 24585.246 | I29: =I27-I28 -> 24273.387 | J29: =J27-J28 -> 5927.8108 | K29: =K27-K28 -> 6505.102 | ... U29: =U27-U28 -> 0 | V29: =IFERROR(SUMIF(D$4:U$4,"运营",D29:U29)/0_参数!$C$10,0) -> 15186.577
B30: 经营进项税额（供附表 6） | C30: 万元 | D30: =D14*0_参数!$C$39+D15*0_参数!$C$41+D13*0_参数!$C$56+(D18+D19+D20+D21)*0_参数!$C$58 -> 0 | E30: =E14*0_参数!$C$39+E15*0_参数!$C$41+E13*0_参数!$C$56+(E18+E19+E20+E21)*0_参数!$C$58 -> 192.66659 | F30: =F14*0_参数!$C$39+F15*0_参数!$C$41+F13*0_参数!$C$56+(F18+F19+F20+F21)*0_参数!$C$58 -> 202.83844 | G30: =G14*0_参数!$C$39+G15*0_参数!$C$41+G13*0_参数!$C$56+(G18+G19+G20+G21)*0_参数!$C$58 -> 202.83844 | H30: =H14*0_参数!$C$39+H15*0_参数!$C$41+H13*0_参数!$C$56+(H18+H19+H20+H21)*0_参数!$C$58 -> 256.1875 | I30: =I14*0_参数!$C$39+I15*0_参数!$C$41+I13*0_参数!$C$56+(I18+I19+I20+I21)*0_参数!$C$58 -> 256.1875 | J30: =J14*0_参数!$C$39+J15*0_参数!$C$41+J13*0_参数!$C$56+(J18+J19+J20+J21)*0_参数!$C$58 -> 256.1875 | K30: =K14*0_参数!$C$39+K15*0_参数!$C$41+K13*0_参数!$C$56+(K18+K19+K20+K21)*0_参数!$C$58 -> 309.53655 | ... U30: =U14*0_参数!$C$39+U15*0_参数!$C$41+U13*0_参数!$C$56+(U18+U19+U20+U21)*0_参数!$C$58 -> 0 | V30: =IFERROR(SUMIF(D$4:U$4,"运营",D30:U30)/0_参数!$C$10,0) -> 260.50522

Sheet 5_折旧摊销
A1: 附表 5 固定资产折旧与无形及递延资产摊销估算表
A2: 单位：万元。原值 = 直接费（按参数 F6 决定是否扣减进项税）+ 分摊的其他费用 / 预备费 / 建设期利息（按直接费占比分摊）；分三类折旧年限
A3: 序号 | B3: 项目 \ 年份 | C3: 单位/说明 | D3: 1 | E3: =D3+1 -> 2 | F3: =E3+1 -> 3 | G3: =F3+1 -> 4 | H3: =G3+1 -> 5 | I3: =H3+1 -> 6 | J3: =I3+1 -> 7 | K3: =J3+1 -> 8 | L3: =K3+1 -> 9 | ... U3: =T3+1 -> 18 | V3: 合计/平均
B4: 阶段 | D4: =IF(D$3<=0_参数!$C$9,"建设",IF(D$3<=0_参数!$C$9+0_参数!$C$10,"运营","")) -> 建设 | E4: =IF(E$3<=0_参数!$C$9,"建设",IF(E$3<=0_参数!$C$9+0_参数!$C$10,"运营","")) -> 运营 | F4: =IF(F$3<=0_参数!$C$9,"建设",IF(F$3<=0_参数!$C$9+0_参数!$C$10,"运营","")) -> 运营 | G4: =IF(G$3<=0_参数!$C$9,"建设",IF(G$3<=0_参数!$C$9+0_参数!$C$10,"运营","")) -> 运营 | H4: =IF(H$3<=0_参数!$C$9,"建设",IF(H$3<=0_参数!$C$9+0_参数!$C$10,"运营","")) -> 运营 | I4: =IF(I$3<=0_参数!$C$9,"建设",IF(I$3<=0_参数!$C$9+0_参数!$C$10,"运营","")) -> 运营 | J4: =IF(J$3<=0_参数!$C$9,"建设",IF(J$3<=0_参数!$C$9+0_参数!$C$10,"运营","")) -> 运营 | K4: =IF(K$3<=0_参数!$C$9,"建设",IF(K$3<=0_参数!$C$9+0_参数!$C$10,"运营","")) -> 运营 | ... U4: =IF(U$3<=0_参数!$C$9,"建设",IF(U$3<=0_参数!$C$9+0_参数!$C$10,"运营",""))
B5: 运营年序号 | D5: =IF(D$4="运营",D$3-0_参数!$C$9,0) -> 0 | E5: =IF(E$4="运营",E$3-0_参数!$C$9,0) -> 1 | F5: =IF(F$4="运营",F$3-0_参数!$C$9,0) -> 2 | G5: =IF(G$4="运营",G$3-0_参数!$C$9,0) -> 3 | H5: =IF(H$4="运营",H$3-0_参数!$C$9,0) -> 4 | I5: =IF(I$4="运营",I$3-0_参数!$C$9,0) -> 5 | J5: =IF(J$4="运营",J$3-0_参数!$C$9,0) -> 6 | K5: =IF(K$4="运营",K$3-0_参数!$C$9,0) -> 7 | ... U5: =IF(U$4="运营",U$3-0_参数!$C$9,0) -> 0
B6: 建设年序号 | D6: =IF(D$4="建设",D$3,0) -> 1 | E6: =IF(E$4="建设",E$3,0) -> 0 | F6: =IF(F$4="建设",F$3,0) -> 0 | G6: =IF(G$4="建设",G$3,0) -> 0 | H6: =IF(H$4="建设",H$3,0) -> 0 | I6: =IF(I$4="建设",I$3,0) -> 0 | J6: =IF(J$4="建设",J$3,0) -> 0 | K6: =IF(K$4="建设",K$3,0) -> 0 | ... U6: =IF(U$4="建设",U$3,0) -> 0
B7: 原值计算
B8: 建筑类直接费（净税） | C8: =1_总投资估算!$F$44-1_总投资估算!$F$38 -> 2579.633
B9: 基础设施设备直接费（净税） | C9: =1_总投资估算!$F$43-IF(0_参数!$C$77=1,1_总投资估算!$F$43/(1+0_参数!$C$81)*0_参数!$C$81,0) -> 11860.177
B10: 算力设备直接费（净税） | C10: =1_总投资估算!$F$42-IF(0_参数!$C$77=1,1_总投资估算!$F$42/(1+0_参数!$C$81)*0_参数!$C$81,0) -> 83407.08
B11: 待分摊费用 = 其他费用(固定资产) + 预备费 + 建设期利息 | C11: =1_总投资估算!$F$40+1_总投资估算!$G$26+1_总投资估算!$G$30 -> 13447.161
B12: 建筑类原值 | C12: =C8+C11*C8/(C8+C9+C10) -> 2934.1537
B13: 基础设施设备原值 | C13: =C9+C11*C9/(C8+C9+C10) -> 13490.129
B14: 算力设备原值 | C14: =C10+C11*C10/(C8+C9+C10) -> 94869.768
B15: 固定资产原值合计 | C15: =C12+C13+C14 -> 111294.05
B16: 递延资产原值 | C16: =1_总投资估算!$F$41 -> 42.3
A18: 1 | B18: 建筑类 折旧费 | C18: 万元 | D18: =IF(AND(D$4="运营",D$5<=0_参数!$C$72),5_折旧摊销!$C$12*(1-0_参数!$C$75)/0_参数!$C$72,0) -> 0 | E18: =IF(AND(E$4="运营",E$5<=0_参数!$C$72),5_折旧摊销!$C$12*(1-0_参数!$C$75)/0_参数!$C$72,0) -> 139.3723 | F18: =IF(AND(F$4="运营",F$5<=0_参数!$C$72),5_折旧摊销!$C$12*(1-0_参数!$C$75)/0_参数!$C$72,0) -> 139.3723 | G18: =IF(AND(G$4="运营",G$5<=0_参数!$C$72),5_折旧摊销!$C$12*(1-0_参数!$C$75)/0_参数!$C$72,0) -> 139.3723 | H18: =IF(AND(H$4="运营",H$5<=0_参数!$C$72),5_折旧摊销!$C$12*(1-0_参数!$C$75)/0_参数!$C$72,0) -> 139.3723 | I18: =IF(AND(I$4="运营",I$5<=0_参数!$C$72),5_折旧摊销!$C$12*(1-0_参数!$C$75)/0_参数!$C$72,0) -> 139.3723 | J18: =IF(AND(J$4="运营",J$5<=0_参数!$C$72),5_折旧摊销!$C$12*(1-0_参数!$C$75)/0_参数!$C$72,0) -> 139.3723 | K18: =IF(AND(K$4="运营",K$5<=0_参数!$C$72),5_折旧摊销!$C$12*(1-0_参数!$C$75)/0_参数!$C$72,0) -> 139.3723 | ... U18: =IF(AND(U$4="运营",U$5<=0_参数!$C$72),5_折旧摊销!$C$12*(1-0_参数!$C$75)/0_参数!$C$72,0) -> 0 | V18: =SUM(D18:U18) -> 1393.723
B19: 建筑类 期末净值 | C19: 万元 | D19: =IF(D$4="",0,5_折旧摊销!$C$12-SUM($D18:D18)) -> 2934.1537 | E19: =IF(E$4="",0,5_折旧摊销!$C$12-SUM($D18:E18)) -> 2794.7814 | F19: =IF(F$4="",0,5_折旧摊销!$C$12-SUM($D18:F18)) -> 2655.4091 | G19: =IF(G$4="",0,5_折旧摊销!$C$12-SUM($D18:G18)) -> 2516.0368 | H19: =IF(H$4="",0,5_折旧摊销!$C$12-SUM($D18:H18)) -> 2376.6645 | I19: =IF(I$4="",0,5_折旧摊销!$C$12-SUM($D18:I18)) -> 2237.2922 | J19: =IF(J$4="",0,5_折旧摊销!$C$12-SUM($D18:J18)) -> 2097.9199 | K19: =IF(K$4="",0,5_折旧摊销!$C$12-SUM($D18:K18)) -> 1958.5476 | ... U19: =IF(U$4="",0,5_折旧摊销!$C$12-SUM($D18:U18)) -> 0 | V19: =INDEX(D19:U19,0_参数!$C$9+0_参数!$C$10) -> 1540.4307
A20: 2 | B20: 基础设施设备 折旧费 | C20: 万元 | D20: =IF(AND(D$4="运营",D$5<=0_参数!$C$73),5_折旧摊销!$C$13*(1-0_参数!$C$75)/0_参数!$C$73,0) -> 0 | E20: =IF(AND(E$4="运营",E$5<=0_参数!$C$73),5_折旧摊销!$C$13*(1-0_参数!$C$75)/0_参数!$C$73,0) -> 854.37482 | F20: =IF(AND(F$4="运营",F$5<=0_参数!$C$73),5_折旧摊销!$C$13*(1-0_参数!$C$75)/0_参数!$C$73,0) -> 854.37482 | G20: =IF(AND(G$4="运营",G$5<=0_参数!$C$73),5_折旧摊销!$C$13*(1-0_参数!$C$75)/0_参数!$C$73,0) -> 854.37482 | H20: =IF(AND(H$4="运营",H$5<=0_参数!$C$73),5_折旧摊销!$C$13*(1-0_参数!$C$75)/0_参数!$C$73,0) -> 854.37482 | I20: =IF(AND(I$4="运营",I$5<=0_参数!$C$73),5_折旧摊销!$C$13*(1-0_参数!$C$75)/0_参数!$C$73,0) -> 854.37482 | J20: =IF(AND(J$4="运营",J$5<=0_参数!$C$73),5_折旧摊销!$C$13*(1-0_参数!$C$75)/0_参数!$C$73,0) -> 854.37482 | K20: =IF(AND(K$4="运营",K$5<=0_参数!$C$73),5_折旧摊销!$C$13*(1-0_参数!$C$75)/0_参数!$C$73,0) -> 854.37482 | ... U20: =IF(AND(U$4="运营",U$5<=0_参数!$C$73),5_折旧摊销!$C$13*(1-0_参数!$C$75)/0_参数!$C$73,0) -> 0 | V20: =SUM(D20:U20) -> 8543.7482
B21: 基础设施设备 期末净值 | C21: 万元 | D21: =IF(D$4="",0,5_折旧摊销!$C$13-SUM($D20:D20)) -> 13490.129 | E21: =IF(E$4="",0,5_折旧摊销!$C$13-SUM($D20:E20)) -> 12635.754 | F21: =IF(F$4="",0,5_折旧摊销!$C$13-SUM($D20:F20)) -> 11781.379 | G21: =IF(G$4="",0,5_折旧摊销!$C$13-SUM($D20:G20)) -> 10927.004 | H21: =IF(H$4="",0,5_折旧摊销!$C$13-SUM($D20:H20)) -> 10072.629 | I21: =IF(I$4="",0,5_折旧摊销!$C$13-SUM($D20:I20)) -> 9218.2547 | J21: =IF(J$4="",0,5_折旧摊销!$C$13-SUM($D20:J20)) -> 8363.8798 | K21: =IF(K$4="",0,5_折旧摊销!$C$13-SUM($D20:K20)) -> 7509.505 | ... U21: =IF(U$4="",0,5_折旧摊销!$C$13-SUM($D20:U20)) -> 0 | V21: =INDEX(D21:U21,0_参数!$C$9+0_参数!$C$10) -> 4946.3805
A22: 3 | B22: 算力设备 折旧费 | C22: 万元 | D22: =IF(AND(D$4="运营",D$5<=0_参数!$C$74),5_折旧摊销!$C$14*(1-0_参数!$C$75)/0_参数!$C$74,0) -> 0 | E22: =IF(AND(E$4="运营",E$5<=0_参数!$C$74),5_折旧摊销!$C$14*(1-0_参数!$C$75)/0_参数!$C$74,0) -> 18025.256 | F22: =IF(AND(F$4="运营",F$5<=0_参数!$C$74),5_折旧摊销!$C$14*(1-0_参数!$C$75)/0_参数!$C$74,0) -> 18025.256 | G22: =IF(AND(G$4="运营",G$5<=0_参数!$C$74),5_折旧摊销!$C$14*(1-0_参数!$C$75)/0_参数!$C$74,0) -> 18025.256 | H22: =IF(AND(H$4="运营",H$5<=0_参数!$C$74),5_折旧摊销!$C$14*(1-0_参数!$C$75)/0_参数!$C$74,0) -> 18025.256 | I22: =IF(AND(I$4="运营",I$5<=0_参数!$C$74),5_折旧摊销!$C$14*(1-0_参数!$C$75)/0_参数!$C$74,0) -> 18025.256 | J22: =IF(AND(J$4="运营",J$5<=0_参数!$C$74),5_折旧摊销!$C$14*(1-0_参数!$C$75)/0_参数!$C$74,0) -> 0 | K22: =IF(AND(K$4="运营",K$5<=0_参数!$C$74),5_折旧摊销!$C$14*(1-0_参数!$C$75)/0_参数!$C$74,0) -> 0 | ... U22: =IF(AND(U$4="运营",U$5<=0_参数!$C$74),5_折旧摊销!$C$14*(1-0_参数!$C$75)/0_参数!$C$74,0) -> 0 | V22: =SUM(D22:U22) -> 90126.28
B23: 算力设备 期末净值 | C23: 万元 | D23: =IF(D$4="",0,5_折旧摊销!$C$14-SUM($D22:D22)) -> 94869.768 | E23: =IF(E$4="",0,5_折旧摊销!$C$14-SUM($D22:E22)) -> 76844.512 | F23: =IF(F$4="",0,5_折旧摊销!$C$14-SUM($D22:F22)) -> 58819.256 | G23: =IF(G$4="",0,5_折旧摊销!$C$14-SUM($D22:G22)) -> 40794 | H23: =IF(H$4="",0,5_折旧摊销!$C$14-SUM($D22:H22)) -> 22768.744 | I23: =IF(I$4="",0,5_折旧摊销!$C$14-SUM($D22:I22)) -> 4743.4884 | J23: =IF(J$4="",0,5_折旧摊销!$C$14-SUM($D22:J22)) -> 4743.4884 | K23: =IF(K$4="",0,5_折旧摊销!$C$14-SUM($D22:K22)) -> 4743.4884 | ... U23: =IF(U$4="",0,5_折旧摊销!$C$14-SUM($D22:U22)) -> 0 | V23: =INDEX(D23:U23,0_参数!$C$9+0_参数!$C$10) -> 4743.4884
B24: （预留）
B25: （预留）
B26: （预留）
A27: 4 | B27: 固定资产折旧费合计 | C27: 万元 | D27: =D18+D20+D22 -> 0 | E27: =E18+E20+E22 -> 19019.003 | F27: =F18+F20+F22 -> 19019.003 | G27: =G18+G20+G22 -> 19019.003 | H27: =H18+H20+H22 -> 19019.003 | I27: =I18+I20+I22 -> 19019.003 | J27: =J18+J20+J22 -> 993.74712 | K27: =K18+K20+K22 -> 993.74712 | ... U27: =U18+U20+U22 -> 0 | V27: =SUM(D27:U27) -> 100063.75
B28: 固定资产期末净值合计 | C28: 万元 | D28: =D19+D21+D23 -> 111294.05 | E28: =E19+E21+E23 -> 92275.048 | F28: =F19+F21+F23 -> 73256.045 | G28: =G19+G21+G23 -> 54237.041 | H28: =H19+H21+H23 -> 35218.038 | I28: =I19+I21+I23 -> 16199.035 | J28: =J19+J21+J23 -> 15205.288 | K28: =K19+K21+K23 -> 14211.541 | ... U28: =U19+U21+U23 -> 0 | V28: =INDEX(D28:U28,0_参数!$C$9+0_参数!$C$10) -> 11230.3
B29: 计算期末固定资产余值（供附表 8 回收） | C29: 万元 | D29: =IF(D$3=0_参数!$C$9+0_参数!$C$10,D28,0) -> 0 | E29: =IF(E$3=0_参数!$C$9+0_参数!$C$10,E28,0) -> 0 | F29: =IF(F$3=0_参数!$C$9+0_参数!$C$10,F28,0) -> 0 | G29: =IF(G$3=0_参数!$C$9+0_参数!$C$10,G28,0) -> 0 | H29: =IF(H$3=0_参数!$C$9+0_参数!$C$10,H28,0) -> 0 | I29: =IF(I$3=0_参数!$C$9+0_参数!$C$10,I28,0) -> 0 | J29: =IF(J$3=0_参数!$C$9+0_参数!$C$10,J28,0) -> 0 | K29: =IF(K$3=0_参数!$C$9+0_参数!$C$10,K28,0) -> 0 | ... U29: =IF(U$3=0_参数!$C$9+0_参数!$C$10,U28,0) -> 0 | V29: =SUM(D29:U29) -> 11230.3
B30: （预留）
A31: 5 | B31: 递延资产摊销费 | C31: 万元 | D31: =IF(AND(D$4="运营",D$5<=0_参数!$C$76),5_折旧摊销!$C$16/0_参数!$C$76,0) -> 0 | E31: =IF(AND(E$4="运营",E$5<=0_参数!$C$76),5_折旧摊销!$C$16/0_参数!$C$76,0) -> 8.46 | F31: =IF(AND(F$4="运营",F$5<=0_参数!$C$76),5_折旧摊销!$C$16/0_参数!$C$76,0) -> 8.46 | G31: =IF(AND(G$4="运营",G$5<=0_参数!$C$76),5_折旧摊销!$C$16/0_参数!$C$76,0) -> 8.46 | H31: =IF(AND(H$4="运营",H$5<=0_参数!$C$76),5_折旧摊销!$C$16/0_参数!$C$76,0) -> 8.46 | I31: =IF(AND(I$4="运营",I$5<=0_参数!$C$76),5_折旧摊销!$C$16/0_参数!$C$76,0) -> 8.46 | J31: =IF(AND(J$4="运营",J$5<=0_参数!$C$76),5_折旧摊销!$C$16/0_参数!$C$76,0) -> 0 | K31: =IF(AND(K$4="运营",K$5<=0_参数!$C$76),5_折旧摊销!$C$16/0_参数!$C$76,0) -> 0 | ... U31: =IF(AND(U$4="运营",U$5<=0_参数!$C$76),5_折旧摊销!$C$16/0_参数!$C$76,0) -> 0 | V31: =SUM(D31:U31) -> 42.3
B32: 递延资产期末净值 | C32: 万元 | D32: =IF(D$4="",0,5_折旧摊销!$C$16-SUM($D31:D31)) -> 42.3 | E32: =IF(E$4="",0,5_折旧摊销!$C$16-SUM($D31:E31)) -> 33.84 | F32: =IF(F$4="",0,5_折旧摊销!$C$16-SUM($D31:F31)) -> 25.38 | G32: =IF(G$4="",0,5_折旧摊销!$C$16-SUM($D31:G31)) -> 16.92 | H32: =IF(H$4="",0,5_折旧摊销!$C$16-SUM($D31:H31)) -> 8.46 | I32: =IF(I$4="",0,5_折旧摊销!$C$16-SUM($D31:I31)) -> 0 | J32: =IF(J$4="",0,5_折旧摊销!$C$16-SUM($D31:J31)) -> 0 | K32: =IF(K$4="",0,5_折旧摊销!$C$16-SUM($D31:K31)) -> 0 | ... U32: =IF(U$4="",0,5_折旧摊销!$C$16-SUM($D31:U31)) -> 0 | V32: =INDEX(D32:U32,0_参数!$C$9+0_参数!$C$10) -> 0

Sheet 6_收入税金
A1: 附表 6 营业收入、增值税及税金附加估算表
A2: 单位：万元。收入 = 可售单元 × 投产比例 × 售卖比例 × 单价 × 12；含税→不含税按参数 D4 还原；增值税按销项 − 进项 − 期初留抵计算
A3: 序号 | B3: 项目 \ 年份 | C3: 单位/说明 | D3: 1 | E3: =D3+1 -> 2 | F3: =E3+1 -> 3 | G3: =F3+1 -> 4 | H3: =G3+1 -> 5 | I3: =H3+1 -> 6 | J3: =I3+1 -> 7 | K3: =J3+1 -> 8 | L3: =K3+1 -> 9 | ... U3: =T3+1 -> 18 | V3: 合计/平均
B4: 阶段 | D4: =IF(D$3<=0_参数!$C$9,"建设",IF(D$3<=0_参数!$C$9+0_参数!$C$10,"运营","")) -> 建设 | E4: =IF(E$3<=0_参数!$C$9,"建设",IF(E$3<=0_参数!$C$9+0_参数!$C$10,"运营","")) -> 运营 | F4: =IF(F$3<=0_参数!$C$9,"建设",IF(F$3<=0_参数!$C$9+0_参数!$C$10,"运营","")) -> 运营 | G4: =IF(G$3<=0_参数!$C$9,"建设",IF(G$3<=0_参数!$C$9+0_参数!$C$10,"运营","")) -> 运营 | H4: =IF(H$3<=0_参数!$C$9,"建设",IF(H$3<=0_参数!$C$9+0_参数!$C$10,"运营","")) -> 运营 | I4: =IF(I$3<=0_参数!$C$9,"建设",IF(I$3<=0_参数!$C$9+0_参数!$C$10,"运营","")) -> 运营 | J4: =IF(J$3<=0_参数!$C$9,"建设",IF(J$3<=0_参数!$C$9+0_参数!$C$10,"运营","")) -> 运营 | K4: =IF(K$3<=0_参数!$C$9,"建设",IF(K$3<=0_参数!$C$9+0_参数!$C$10,"运营","")) -> 运营 | ... U4: =IF(U$3<=0_参数!$C$9,"建设",IF(U$3<=0_参数!$C$9+0_参数!$C$10,"运营",""))
B5: 运营年序号 | D5: =IF(D$4="运营",D$3-0_参数!$C$9,0) -> 0 | E5: =IF(E$4="运营",E$3-0_参数!$C$9,0) -> 1 | F5: =IF(F$4="运营",F$3-0_参数!$C$9,0) -> 2 | G5: =IF(G$4="运营",G$3-0_参数!$C$9,0) -> 3 | H5: =IF(H$4="运营",H$3-0_参数!$C$9,0) -> 4 | I5: =IF(I$4="运营",I$3-0_参数!$C$9,0) -> 5 | J5: =IF(J$4="运营",J$3-0_参数!$C$9,0) -> 6 | K5: =IF(K$4="运营",K$3-0_参数!$C$9,0) -> 7 | ... U5: =IF(U$4="运营",U$3-0_参数!$C$9,0) -> 0
B6: 建设年序号 | D6: =IF(D$4="建设",D$3,0) -> 1 | E6: =IF(E$4="建设",E$3,0) -> 0 | F6: =IF(F$4="建设",F$3,0) -> 0 | G6: =IF(G$4="建设",G$3,0) -> 0 | H6: =IF(H$4="建设",H$3,0) -> 0 | I6: =IF(I$4="建设",I$3,0) -> 0 | J6: =IF(J$4="建设",J$3,0) -> 0 | K6: =IF(K$4="建设",K$3,0) -> 0 | ... U6: =IF(U$4="建设",U$3,0) -> 0
A7: 1 | B7: 可售计价单元（投运） | C7: 台 | D7: =IF(D$4="运营",0_参数!$C$26*4_总成本费用!D$7,0) -> 0 | E7: =IF(E$4="运营",0_参数!$C$26*4_总成本费用!E$7,0) -> 168 | F7: =IF(F$4="运营",0_参数!$C$26*4_总成本费用!F$7,0) -> 168 | G7: =IF(G$4="运营",0_参数!$C$26*4_总成本费用!G$7,0) -> 168 | H7: =IF(H$4="运营",0_参数!$C$26*4_总成本费用!H$7,0) -> 168 | I7: =IF(I$4="运营",0_参数!$C$26*4_总成本费用!I$7,0) -> 168 | J7: =IF(J$4="运营",0_参数!$C$26*4_总成本费用!J$7,0) -> 168 | K7: =IF(K$4="运营",0_参数!$C$26*4_总成本费用!K$7,0) -> 168 | ... U7: =IF(U$4="运营",0_参数!$C$26*4_总成本费用!U$7,0) -> 0
A8: 2 | B8: 售卖比例 | D8: =4_总成本费用!D$8 -> 0 | E8: =4_总成本费用!E$8 -> 0.8 | F8: =4_总成本费用!F$8 -> 0.9 | G8: =4_总成本费用!G$8 -> 0.9 | H8: =4_总成本费用!H$8 -> 0.9 | I8: =4_总成本费用!I$8 -> 0.9 | J8: =4_总成本费用!J$8 -> 0.9 | K8: =4_总成本费用!K$8 -> 0.9 | ... U8: =4_总成本费用!U$8 -> 0
A9: 3 | B9: 算力单价（含税） | C9: 万元/台/月 | D9: =IF(D$4="运营",0_参数!$C$46,0) -> 0 | E9: =IF(E$4="运营",0_参数!$C$46,0) -> 14 | F9: =IF(F$4="运营",0_参数!$C$46,0) -> 14 | G9: =IF(G$4="运营",0_参数!$C$46,0) -> 14 | H9: =IF(H$4="运营",0_参数!$C$46,0) -> 14 | I9: =IF(I$4="运营",0_参数!$C$46,0) -> 14 | J9: =IF(J$4="运营",0_参数!$C$46,0) -> 14 | K9: =IF(K$4="运营",0_参数!$C$46,0) -> 14 | ... U9: =IF(U$4="运营",0_参数!$C$46,0) -> 0
A10: 4 | B10: 营业收入（含税） | C10: 万元 | D10: =D7*D8*D9*12 -> 0 | E10: =E7*E8*E9*12 -> 22579.2 | F10: =F7*F8*F9*12 -> 25401.6 | G10: =G7*G8*G9*12 -> 25401.6 | H10: =H7*H8*H9*12 -> 25401.6 | I10: =I7*I8*I9*12 -> 25401.6 | J10: =J7*J8*J9*12 -> 25401.6 | K10: =K7*K8*K9*12 -> 25401.6 | ... U10: =U7*U8*U9*12 -> 0 | V10: =IFERROR(SUMIF(D$4:U$4,"运营",D10:U10)/0_参数!$C$10,0) -> 25119.36
A11: 5 | B11: 营业收入（不含税） | C11: 万元 | D11: =D10/(1+0_参数!$C$47) -> 0 | E11: =E10/(1+0_参数!$C$47) -> 21301.132 | F11: =F10/(1+0_参数!$C$47) -> 23963.774 | G11: =G10/(1+0_参数!$C$47) -> 23963.774 | H11: =H10/(1+0_参数!$C$47) -> 23963.774 | I11: =I10/(1+0_参数!$C$47) -> 23963.774 | J11: =J10/(1+0_参数!$C$47) -> 23963.774 | K11: =K10/(1+0_参数!$C$47) -> 23963.774 | ... U11: =U10/(1+0_参数!$C$47) -> 0 | V11: =IFERROR(SUMIF(D$4:U$4,"运营",D11:U11)/0_参数!$C$10,0) -> 23697.509
A12: 6 | B12: 增值税销项税额 | C12: 万元 | D12: =D11*0_参数!$C$47 -> 0 | E12: =E11*0_参数!$C$47 -> 1278.0679 | F12: =F11*0_参数!$C$47 -> 1437.8264 | G12: =G11*0_参数!$C$47 -> 1437.8264 | H12: =H11*0_参数!$C$47 -> 1437.8264 | I12: =I11*0_参数!$C$47 -> 1437.8264 | J12: =J11*0_参数!$C$47 -> 1437.8264 | K12: =K11*0_参数!$C$47 -> 1437.8264 | ... U12: =U11*0_参数!$C$47 -> 0 | V12: =IFERROR(SUMIF(D$4:U$4,"运营",D12:U12)/0_参数!$C$10,0) -> 1421.8506
A13: 7 | B13: 增值税进项税额（经营） | C13: 万元 | D13: =4_总成本费用!D$30 -> 0 | E13: =4_总成本费用!E$30 -> 192.66659 | F13: =4_总成本费用!F$30 -> 202.83844 | G13: =4_总成本费用!G$30 -> 202.83844 | H13: =4_总成本费用!H$30 -> 256.1875 | I13: =4_总成本费用!I$30 -> 256.1875 | J13: =4_总成本费用!J$30 -> 256.1875 | K13: =4_总成本费用!K$30 -> 309.53655 | ... U13: =4_总成本费用!U$30 -> 0 | V13: =IFERROR(SUMIF(D$4:U$4,"运营",D13:U13)/0_参数!$C$10,0) -> 260.50522
A14: 8 | B14: 期初留抵进项税额 | C14: 万元 | D14: =IF(D$5=1,1_总投资估算!$F$39,0) -> 0 | E14: =IF(E$5=1,1_总投资估算!$F$39,IF(E$4="运营",D16,0)) -> 12616.91 | F14: =IF(F$5=1,1_总投资估算!$F$39,IF(F$4="运营",E16,0)) -> 11531.509 | G14: =IF(G$5=1,1_总投资估算!$F$39,IF(G$4="运营",F16,0)) -> 10296.521 | H14: =IF(H$5=1,1_总投资估算!$F$39,IF(H$4="运营",G16,0)) -> 9061.5331 | I14: =IF(I$5=1,1_总投资估算!$F$39,IF(I$4="运营",H16,0)) -> 7879.8941 | J14: =IF(J$5=1,1_总投资估算!$F$39,IF(J$4="运营",I16,0)) -> 6698.2552 | K14: =IF(K$5=1,1_总投资估算!$F$39,IF(K$4="运营",J16,0)) -> 5516.6163 | L14: =IF(L$5=1,1_总投资估算!$F$39,IF(L$4="运营",K16,0)) -> 4388.3264 | ... U14: =IF(U$5=1,1_总投资估算!$F$39,IF(U$4="运营",T16,0)) -> 0
A15: 9 | B15: 应纳增值税 | C15: 万元 | D15: =MAX(0,D12-D13-D14) -> 0 | E15: =MAX(0,E12-E13-E14) -> 0 | F15: =MAX(0,F12-F13-F14) -> 0 | G15: =MAX(0,G12-G13-G14) -> 0 | H15: =MAX(0,H12-H13-H14) -> 0 | I15: =MAX(0,I12-I13-I14) -> 0 | J15: =MAX(0,J12-J13-J14) -> 0 | K15: =MAX(0,K12-K13-K14) -> 0 | ... U15: =MAX(0,U12-U13-U14) -> 0 | V15: =IFERROR(SUMIF(D$4:U$4,"运营",D15:U15)/0_参数!$C$10,0) -> 0
A16: 10 | B16: 期末留抵进项税额 | C16: 万元 | D16: =IF(D$4="运营",MAX(0,D14+D13-D12),0) -> 0 | E16: =IF(E$4="运营",MAX(0,E14+E13-E12),0) -> 11531.509 | F16: =IF(F$4="运营",MAX(0,F14+F13-F12),0) -> 10296.521 | G16: =IF(G$4="运营",MAX(0,G14+G13-G12),0) -> 9061.5331 | H16: =IF(H$4="运营",MAX(0,H14+H13-H12),0) -> 7879.8941 | I16: =IF(I$4="运营",MAX(0,I14+I13-I12),0) -> 6698.2552 | J16: =IF(J$4="运营",MAX(0,J14+J13-J12),0) -> 5516.6163 | K16: =IF(K$4="运营",MAX(0,K14+K13-K12),0) -> 4388.3264 | ... U16: =IF(U$4="运营",MAX(0,U14+U13-U12),0) -> 0
A17: 11 | B17: 税金及附加（城建税+教育费附加+地方教育附加） | C17: 万元 | D17: =D15*(0_参数!$C$82+0_参数!$C$83+0_参数!$C$84) -> 0 | E17: =E15*(0_参数!$C$82+0_参数!$C$83+0_参数!$C$84) -> 0 | F17: =F15*(0_参数!$C$82+0_参数!$C$83+0_参数!$C$84) -> 0 | G17: =G15*(0_参数!$C$82+0_参数!$C$83+0_参数!$C$84) -> 0 | H17: =H15*(0_参数!$C$82+0_参数!$C$83+0_参数!$C$84) -> 0 | I17: =I15*(0_参数!$C$82+0_参数!$C$83+0_参数!$C$84) -> 0 | J17: =J15*(0_参数!$C$82+0_参数!$C$83+0_参数!$C$84) -> 0 | K17: =K15*(0_参数!$C$82+0_参数!$C$83+0_参数!$C$84) -> 0 | ... U17: =U15*(0_参数!$C$82+0_参数!$C$83+0_参数!$C$84) -> 0 | V17: =IFERROR(SUMIF(D$4:U$4,"运营",D17:U17)/0_参数!$C$10,0) -> 0

Sheet 7_利润
A1: 附表 7 利润与利润分配表
A2: 单位：万元
A3: 序号 | B3: 项目 \ 年份 | C3: 单位/说明 | D3: 1 | E3: =D3+1 -> 2 | F3: =E3+1 -> 3 | G3: =F3+1 -> 4 | H3: =G3+1 -> 5 | I3: =H3+1 -> 6 | J3: =I3+1 -> 7 | K3: =J3+1 -> 8 | L3: =K3+1 -> 9 | ... U3: =T3+1 -> 18 | V3: 合计/平均
B4: 阶段 | D4: =IF(D$3<=0_参数!$C$9,"建设",IF(D$3<=0_参数!$C$9+0_参数!$C$10,"运营","")) -> 建设 | E4: =IF(E$3<=0_参数!$C$9,"建设",IF(E$3<=0_参数!$C$9+0_参数!$C$10,"运营","")) -> 运营 | F4: =IF(F$3<=0_参数!$C$9,"建设",IF(F$3<=0_参数!$C$9+0_参数!$C$10,"运营","")) -> 运营 | G4: =IF(G$3<=0_参数!$C$9,"建设",IF(G$3<=0_参数!$C$9+0_参数!$C$10,"运营","")) -> 运营 | H4: =IF(H$3<=0_参数!$C$9,"建设",IF(H$3<=0_参数!$C$9+0_参数!$C$10,"运营","")) -> 运营 | I4: =IF(I$3<=0_参数!$C$9,"建设",IF(I$3<=0_参数!$C$9+0_参数!$C$10,"运营","")) -> 运营 | J4: =IF(J$3<=0_参数!$C$9,"建设",IF(J$3<=0_参数!$C$9+0_参数!$C$10,"运营","")) -> 运营 | K4: =IF(K$3<=0_参数!$C$9,"建设",IF(K$3<=0_参数!$C$9+0_参数!$C$10,"运营","")) -> 运营 | ... U4: =IF(U$3<=0_参数!$C$9,"建设",IF(U$3<=0_参数!$C$9+0_参数!$C$10,"运营",""))
B5: 运营年序号 | D5: =IF(D$4="运营",D$3-0_参数!$C$9,0) -> 0 | E5: =IF(E$4="运营",E$3-0_参数!$C$9,0) -> 1 | F5: =IF(F$4="运营",F$3-0_参数!$C$9,0) -> 2 | G5: =IF(G$4="运营",G$3-0_参数!$C$9,0) -> 3 | H5: =IF(H$4="运营",H$3-0_参数!$C$9,0) -> 4 | I5: =IF(I$4="运营",I$3-0_参数!$C$9,0) -> 5 | J5: =IF(J$4="运营",J$3-0_参数!$C$9,0) -> 6 | K5: =IF(K$4="运营",K$3-0_参数!$C$9,0) -> 7 | ... U5: =IF(U$4="运营",U$3-0_参数!$C$9,0) -> 0
B6: 建设年序号 | D6: =IF(D$4="建设",D$3,0) -> 1 | E6: =IF(E$4="建设",E$3,0) -> 0 | F6: =IF(F$4="建设",F$3,0) -> 0 | G6: =IF(G$4="建设",G$3,0) -> 0 | H6: =IF(H$4="建设",H$3,0) -> 0 | I6: =IF(I$4="建设",I$3,0) -> 0 | J6: =IF(J$4="建设",J$3,0) -> 0 | K6: =IF(K$4="建设",K$3,0) -> 0 | ... U6: =IF(U$4="建设",U$3,0) -> 0
A7: 1 | B7: 营业收入（不含税） | C7: 万元 | D7: =6_收入税金!D$11 -> 0 | E7: =6_收入税金!E$11 -> 21301.132 | F7: =6_收入税金!F$11 -> 23963.774 | G7: =6_收入税金!G$11 -> 23963.774 | H7: =6_收入税金!H$11 -> 23963.774 | I7: =6_收入税金!I$11 -> 23963.774 | J7: =6_收入税金!J$11 -> 23963.774 | K7: =6_收入税金!K$11 -> 23963.774 | ... U7: =6_收入税金!U$11 -> 0 | V7: =IFERROR(SUMIF(D$4:U$4,"运营",D7:U7)/0_参数!$C$10,0) -> 23697.509
A8: 2 | B8: 税金及附加 | C8: 万元 | D8: =6_收入税金!D$17 -> 0 | E8: =6_收入税金!E$17 -> 0 | F8: =6_收入税金!F$17 -> 0 | G8: =6_收入税金!G$17 -> 0 | H8: =6_收入税金!H$17 -> 0 | I8: =6_收入税金!I$17 -> 0 | J8: =6_收入税金!J$17 -> 0 | K8: =6_收入税金!K$17 -> 0 | ... U8: =6_收入税金!U$17 -> 0 | V8: =IFERROR(SUMIF(D$4:U$4,"运营",D8:U8)/0_参数!$C$10,0) -> 0
A9: 3 | B9: 总成本费用 | C9: 万元 | D9: =4_总成本费用!D$27 -> 0 | E9: =4_总成本费用!E$27 -> 25247.008 | F9: =4_总成本费用!F$27 -> 25037.326 | G9: =4_总成本费用!G$27 -> 24728.185 | H9: =4_总成本费用!H$27 -> 25305.476 | I9: =4_总成本费用!I$27 -> 24993.616 | J9: =4_总成本费用!J$27 -> 6648.0403 | K9: =4_总成本费用!K$27 -> 7225.3314 | ... U9: =4_总成本费用!U$27 -> 0 | V9: =IFERROR(SUMIF(D$4:U$4,"运营",D9:U9)/0_参数!$C$10,0) -> 15898.982
A10: 4 | B10: 补贴收入 | C10: 如有政府补贴按年填入（蓝字） | D10: =0 -> 0 | E10: =0 -> 0 | F10: =0 -> 0 | G10: =0 -> 0 | H10: =0 -> 0 | I10: =0 -> 0 | J10: =0 -> 0 | K10: =0 -> 0 | ... U10: =0 -> 0 | V10: =IFERROR(SUMIF(D$4:U$4,"运营",D10:U10)/0_参数!$C$10,0) -> 0
B11: （预留）
A12: 5 | B12: 利润总额 = 1 − 2 − 3 + 4 | C12: 万元 | D12: =D7-D8-D9+D10 -> 0 | E12: =E7-E8-E9+E10 -> -3945.8757 | F12: =F7-F8-F9+F10 -> -1073.5528 | G12: =G7-G8-G9+G10 -> -764.4111 | H12: =H7-H8-H9+H10 -> -1341.7023 | I12: =I7-I8-I9+I10 -> -1029.8425 | J12: =J7-J8-J9+J10 -> 17315.733 | K12: =K7-K8-K9+K10 -> 16738.442 | ... U12: =U7-U8-U9+U10 -> 0 | V12: =IFERROR(SUMIF(D$4:U$4,"运营",D12:U12)/0_参数!$C$10,0) -> 7798.5276
A13: 6 | B13: 应纳税所得额（弥补以前年度亏损后） | C13: 万元 | D13: =IF(D$4="运营",MAX(0,D12),0) -> 0 | E13: =IF(E$4="运营",MAX(0,E12+MIN(0,D30)),0) -> 0 | F13: =IF(F$4="运营",MAX(0,F12+MIN(0,E30)),0) -> 0 | G13: =IF(G$4="运营",MAX(0,G12+MIN(0,F30)),0) -> 0 | H13: =IF(H$4="运营",MAX(0,H12+MIN(0,G30)),0) -> 0 | I13: =IF(I$4="运营",MAX(0,I12+MIN(0,H30)),0) -> 0 | J13: =IF(J$4="运营",MAX(0,J12+MIN(0,I30)),0) -> 9160.349 | K13: =IF(K$4="运营",MAX(0,K12+MIN(0,J30)),0) -> 16738.442 | L13: =IF(L$4="运营",MAX(0,L12+MIN(0,K30)),0) -> 17050.302 | ... U13: =IF(U$4="运营",MAX(0,U12+MIN(0,T30)),0) -> 0 | V13: =IFERROR(SUMIF(D$4:U$4,"运营",D13:U13)/0_参数!$C$10,0) -> 7798.5276
A14: 7 | B14: 所得税 | C14: 万元 | D14: =D13*0_参数!$C$85 -> 0 | E14: =E13*0_参数!$C$85 -> 0 | F14: =F13*0_参数!$C$85 -> 0 | G14: =G13*0_参数!$C$85 -> 0 | H14: =H13*0_参数!$C$85 -> 0 | I14: =I13*0_参数!$C$85 -> 0 | J14: =J13*0_参数!$C$85 -> 2290.0872 | K14: =K13*0_参数!$C$85 -> 4184.6105 | ... U14: =U13*0_参数!$C$85 -> 0 | V14: =IFERROR(SUMIF(D$4:U$4,"运营",D14:U14)/0_参数!$C$10,0) -> 1949.6319
A15: 8 | B15: 净利润 = 5 − 7 | C15: 万元 | D15: =D12-D14 -> 0 | E15: =E12-E14 -> -3945.8757 | F15: =F12-F14 -> -1073.5528 | G15: =G12-G14 -> -764.4111 | H15: =H12-H14 -> -1341.7023 | I15: =I12-I14 -> -1029.8425 | J15: =J12-J14 -> 15025.646 | K15: =K12-K14 -> 12553.832 | ... U15: =U12-U14 -> 0 | V15: =IFERROR(SUMIF(D$4:U$4,"运营",D15:U15)/0_参数!$C$10,0) -> 5848.8957
A16: 9 | B16: 提取法定盈余公积金 | C16: 万元 | D16: =MAX(0,D15)*0_参数!$C$86 -> 0 | E16: =MAX(0,E15)*0_参数!$C$86 -> 0 | F16: =MAX(0,F15)*0_参数!$C$86 -> 0 | G16: =MAX(0,G15)*0_参数!$C$86 -> 0 | H16: =MAX(0,H15)*0_参数!$C$86 -> 0 | I16: =MAX(0,I15)*0_参数!$C$86 -> 0 | J16: =MAX(0,J15)*0_参数!$C$86 -> 1502.5646 | K16: =MAX(0,K15)*0_参数!$C$86 -> 1255.3832 | ... U16: =MAX(0,U15)*0_参数!$C$86 -> 0 | V16: =SUM(D16:U16) -> 6664.4342
B17: 累计盈余公积金 | C17: 万元 | D17: =D16 -> 0 | E17: =IF(1=0,E16,D17+E16) -> 0 | F17: =IF(2=0,F16,E17+F16) -> 0 | G17: =IF(3=0,G16,F17+G16) -> 0 | H17: =IF(4=0,H16,G17+H16) -> 0 | I17: =IF(5=0,I16,H17+I16) -> 0 | J17: =IF(6=0,J16,I17+J16) -> 1502.5646 | K17: =IF(7=0,K16,J17+K16) -> 2757.9478 | L17: =IF(8=0,L16,K17+L16) -> 4036.7204 | M17: =IF(9=0,M16,L17+M16) -> 5338.8825 | N17: =IF(10=0,N16,M17+N16) -> 6664.4342 | O17: =IF(11=0,O16,N17+O16) -> 6664.4342 | P17: =IF(12=0,P16,O17+P16) -> 6664.4342 | Q17: =IF(13=0,Q16,P17+Q16) -> 6664.4342 | R17: =IF(14=0,R16,Q17+R16) -> 6664.4342 | S17: =IF(15=0,S16,R17+S16) -> 6664.4342 | T17: =IF(16=0,T16,S17+T16) -> 6664.4342 | U17: =IF(17=0,U16,T17+U16) -> 6664.4342 | V17: =INDEX(D17:U17,0_参数!$C$9+0_参数!$C$10) -> 6664.4342
A18: 10 | B18: 可供投资者分配利润 | C18: 万元 | D18: =D15-D16 -> 0 | E18: =E15-E16 -> -3945.8757 | F18: =F15-F16 -> -1073.5528 | G18: =G15-G16 -> -764.4111 | H18: =H15-H16 -> -1341.7023 | I18: =I15-I16 -> -1029.8425 | J18: =J15-J16 -> 13523.081 | K18: =K15-K16 -> 11298.448 | ... U18: =U15-U16 -> 0 | V18: =SUM(D18:U18) -> 51824.523
B19: 累计未分配利润 | C19: 万元 | D19: =D18 -> 0 | E19: =IF(1=0,E18,D19+E18) -> -3945.8757 | F19: =IF(2=0,F18,E19+F18) -> -5019.4285 | G19: =IF(3=0,G18,F19+G18) -> -5783.8396 | H19: =IF(4=0,H18,G19+H18) -> -7125.5418 | I19: =IF(5=0,I18,H19+I18) -> -8155.3843 | J19: =IF(6=0,J18,I19+J18) -> 5367.6971 | K19: =IF(7=0,K18,J19+K18) -> 16666.146 | L19: =IF(8=0,L18,K19+L18) -> 28175.099 | M19: =IF(9=0,M18,L19+M18) -> 39894.559 | N19: =IF(10=0,N18,M19+N18) -> 51824.523 | O19: =IF(11=0,O18,N19+O18) -> 51824.523 | P19: =IF(12=0,P18,O19+P18) -> 51824.523 | Q19: =IF(13=0,Q18,P19+Q18) -> 51824.523 | R19: =IF(14=0,R18,Q19+R18) -> 51824.523 | S19: =IF(15=0,S18,R19+S18) -> 51824.523 | T19: =IF(16=0,T18,S19+T18) -> 51824.523 | U19: =IF(17=0,U18,T19+U18) -> 51824.523 | V19: =INDEX(D19:U19,0_参数!$C$9+0_参数!$C$10) -> 51824.523
B20: 息税前利润 EBIT = 利润总额 + 利息 | C20: 万元 | D20: =D12+4_总成本费用!D$26 -> 0 | E20: =E12+4_总成本费用!E$26 -> -806.06267 | F20: =F12+4_总成本费用!F$26 -> 1778.3338 | G20: =G12+4_总成本费用!G$26 -> 1778.3338 | H20: =H12+4_总成本费用!H$26 -> 889.18289 | I20: =I12+4_总成本费用!I$26 -> 889.18289 | J20: =J12+4_总成本费用!J$26 -> 18922.899 | K20: =K12+4_总成本费用!K$26 -> 18033.748 | ... U20: =U12+4_总成本费用!U$26 -> 0 | V20: =IFERROR(SUMIF(D$4:U$4,"运营",D20:U20)/0_参数!$C$10,0) -> 9558.6861
B21: 调整所得税（供附表 8）= EBIT × 税率 | C21: 万元 | D21: =IF(D$4="运营",MAX(0,D20)*0_参数!$C$85,0) -> 0 | E21: =IF(E$4="运营",MAX(0,E20)*0_参数!$C$85,0) -> 0 | F21: =IF(F$4="运营",MAX(0,F20)*0_参数!$C$85,0) -> 444.58346 | G21: =IF(G$4="运营",MAX(0,G20)*0_参数!$C$85,0) -> 444.58346 | H21: =IF(H$4="运营",MAX(0,H20)*0_参数!$C$85,0) -> 222.29572 | I21: =IF(I$4="运营",MAX(0,I20)*0_参数!$C$85,0) -> 222.29572 | J21: =IF(J$4="运营",MAX(0,J20)*0_参数!$C$85,0) -> 4730.7247 | K21: =IF(K$4="运营",MAX(0,K20)*0_参数!$C$85,0) -> 4508.437 | ... U21: =IF(U$4="运营",MAX(0,U20)*0_参数!$C$85,0) -> 0 | V21: =IFERROR(SUMIF(D$4:U$4,"运营",D21:U21)/0_参数!$C$10,0) -> 2409.8231
B22: （预留）
B23: （预留）
B24: （预留）
B25: （预留）
B26: （预留）
B27: （预留）
B28: （预留）
B29: （预留）
B30: 累计可弥补亏损额（负数表示尚有亏损未弥补） | C30: 万元 | D30: =MIN(0,D12) -> 0 | E30: =IF(1=0,MIN(0,E12),MIN(0,D30+E12)) -> -3945.8757 | F30: =IF(2=0,MIN(0,F12),MIN(0,E30+F12)) -> -5019.4285 | G30: =IF(3=0,MIN(0,G12),MIN(0,F30+G12)) -> -5783.8396 | H30: =IF(4=0,MIN(0,H12),MIN(0,G30+H12)) -> -7125.5418 | I30: =IF(5=0,MIN(0,I12),MIN(0,H30+I12)) -> -8155.3843 | J30: =IF(6=0,MIN(0,J12),MIN(0,I30+J12)) -> 0 | K30: =IF(7=0,MIN(0,K12),MIN(0,J30+K12)) -> 0 | L30: =IF(8=0,MIN(0,L12),MIN(0,K30+L12)) -> 0 | M30: =IF(9=0,MIN(0,M12),MIN(0,L30+M12)) -> 0 | N30: =IF(10=0,MIN(0,N12),MIN(0,M30+N12)) -> 0 | O30: =IF(11=0,MIN(0,O12),MIN(0,N30+O12)) -> 0 | P30: =IF(12=0,MIN(0,P12),MIN(0,O30+P12)) -> 0 | Q30: =IF(13=0,MIN(0,Q12),MIN(0,P30+Q12)) -> 0 | R30: =IF(14=0,MIN(0,R12),MIN(0,Q30+R12)) -> 0 | S30: =IF(15=0,MIN(0,S12),MIN(0,R30+S12)) -> 0 | T30: =IF(16=0,MIN(0,T12),MIN(0,S30+T12)) -> 0 | U30: =IF(17=0,MIN(0,U12),MIN(0,T30+U12)) -> 0

Sheet 8_现金流量
A1: 附表 8 项目投资现金流量表（全部投资，不含融资）
A2: 单位：万元。IRR / NPV / 动态回收期由本表计算；BEP 取正常年
A3: 序号 | B3: 项目 \ 年份 | C3: 单位/说明 | D3: 1 | E3: =D3+1 -> 2 | F3: =E3+1 -> 3 | G3: =F3+1 -> 4 | H3: =G3+1 -> 5 | I3: =H3+1 -> 6 | J3: =I3+1 -> 7 | K3: =J3+1 -> 8 | L3: =K3+1 -> 9 | ... U3: =T3+1 -> 18 | V3: 合计/平均
B4: 阶段 | D4: =IF(D$3<=0_参数!$C$9,"建设",IF(D$3<=0_参数!$C$9+0_参数!$C$10,"运营","")) -> 建设 | E4: =IF(E$3<=0_参数!$C$9,"建设",IF(E$3<=0_参数!$C$9+0_参数!$C$10,"运营","")) -> 运营 | F4: =IF(F$3<=0_参数!$C$9,"建设",IF(F$3<=0_参数!$C$9+0_参数!$C$10,"运营","")) -> 运营 | G4: =IF(G$3<=0_参数!$C$9,"建设",IF(G$3<=0_参数!$C$9+0_参数!$C$10,"运营","")) -> 运营 | H4: =IF(H$3<=0_参数!$C$9,"建设",IF(H$3<=0_参数!$C$9+0_参数!$C$10,"运营","")) -> 运营 | I4: =IF(I$3<=0_参数!$C$9,"建设",IF(I$3<=0_参数!$C$9+0_参数!$C$10,"运营","")) -> 运营 | J4: =IF(J$3<=0_参数!$C$9,"建设",IF(J$3<=0_参数!$C$9+0_参数!$C$10,"运营","")) -> 运营 | K4: =IF(K$3<=0_参数!$C$9,"建设",IF(K$3<=0_参数!$C$9+0_参数!$C$10,"运营","")) -> 运营 | ... U4: =IF(U$3<=0_参数!$C$9,"建设",IF(U$3<=0_参数!$C$9+0_参数!$C$10,"运营",""))
B5: 运营年序号 | D5: =IF(D$4="运营",D$3-0_参数!$C$9,0) -> 0 | E5: =IF(E$4="运营",E$3-0_参数!$C$9,0) -> 1 | F5: =IF(F$4="运营",F$3-0_参数!$C$9,0) -> 2 | G5: =IF(G$4="运营",G$3-0_参数!$C$9,0) -> 3 | H5: =IF(H$4="运营",H$3-0_参数!$C$9,0) -> 4 | I5: =IF(I$4="运营",I$3-0_参数!$C$9,0) -> 5 | J5: =IF(J$4="运营",J$3-0_参数!$C$9,0) -> 6 | K5: =IF(K$4="运营",K$3-0_参数!$C$9,0) -> 7 | ... U5: =IF(U$4="运营",U$3-0_参数!$C$9,0) -> 0
B6: 建设年序号 | D6: =IF(D$4="建设",D$3,0) -> 1 | E6: =IF(E$4="建设",E$3,0) -> 0 | F6: =IF(F$4="建设",F$3,0) -> 0 | G6: =IF(G$4="建设",G$3,0) -> 0 | H6: =IF(H$4="建设",H$3,0) -> 0 | I6: =IF(I$4="建设",I$3,0) -> 0 | J6: =IF(J$4="建设",J$3,0) -> 0 | K6: =IF(K$4="建设",K$3,0) -> 0 | ... U6: =IF(U$4="建设",U$3,0) -> 0
A7: 1.1 | B7: 营业收入（不含税） | C7: 万元 | D7: =6_收入税金!D$11 -> 0 | E7: =6_收入税金!E$11 -> 21301.132 | F7: =6_收入税金!F$11 -> 23963.774 | G7: =6_收入税金!G$11 -> 23963.774 | H7: =6_收入税金!H$11 -> 23963.774 | I7: =6_收入税金!I$11 -> 23963.774 | J7: =6_收入税金!J$11 -> 23963.774 | K7: =6_收入税金!K$11 -> 23963.774 | ... U7: =6_收入税金!U$11 -> 0 | V7: =SUM(D7:U7) -> 236975.09
A8: 1.2 | B8: 补贴收入 | C8: 万元 | D8: =7_利润!D$10 -> 0 | E8: =7_利润!E$10 -> 0 | F8: =7_利润!F$10 -> 0 | G8: =7_利润!G$10 -> 0 | H8: =7_利润!H$10 -> 0 | I8: =7_利润!I$10 -> 0 | J8: =7_利润!J$10 -> 0 | K8: =7_利润!K$10 -> 0 | ... U8: =7_利润!U$10 -> 0 | V8: =SUM(D8:U8) -> 0
A9: 1.3 | B9: 回收固定资产余值 | C9: 万元 | D9: =5_折旧摊销!D$29 -> 0 | E9: =5_折旧摊销!E$29 -> 0 | F9: =5_折旧摊销!F$29 -> 0 | G9: =5_折旧摊销!G$29 -> 0 | H9: =5_折旧摊销!H$29 -> 0 | I9: =5_折旧摊销!I$29 -> 0 | J9: =5_折旧摊销!J$29 -> 0 | K9: =5_折旧摊销!K$29 -> 0 | ... U9: =5_折旧摊销!U$29 -> 0 | V9: =SUM(D9:U9) -> 11230.3
A10: 1.4 | B10: 回收流动资金 | C10: 万元 | D10: =2_流动资金!D$19 -> 0 | E10: =2_流动资金!E$19 -> 0 | F10: =2_流动资金!F$19 -> 0 | G10: =2_流动资金!G$19 -> 0 | H10: =2_流动资金!H$19 -> 0 | I10: =2_流动资金!I$19 -> 0 | J10: =2_流动资金!J$19 -> 0 | K10: =2_流动资金!K$19 -> 0 | ... U10: =2_流动资金!U$19 -> 0 | V10: =SUM(D10:U10) -> 1953.7415
A11: 1 | B11: 现金流入 | C11: 万元 | D11: =D7+D8+D9+D10 -> 0 | E11: =E7+E8+E9+E10 -> 21301.132 | F11: =F7+F8+F9+F10 -> 23963.774 | G11: =G7+G8+G9+G10 -> 23963.774 | H11: =H7+H8+H9+H10 -> 23963.774 | I11: =I7+I8+I9+I10 -> 23963.774 | J11: =J7+J8+J9+J10 -> 23963.774 | K11: =K7+K8+K9+K10 -> 23963.774 | ... U11: =U7+U8+U9+U10 -> 0 | V11: =SUM(D11:U11) -> 250159.14
A12: 2.1 | B12: 建设投资（不含建设期利息） | C12: 万元 | D12: =3_资金筹措!D$8 -> 122417.01 | E12: =3_资金筹措!E$8 -> 0 | F12: =3_资金筹措!F$8 -> 0 | G12: =3_资金筹措!G$8 -> 0 | H12: =3_资金筹措!H$8 -> 0 | I12: =3_资金筹措!I$8 -> 0 | J12: =3_资金筹措!J$8 -> 0 | K12: =3_资金筹措!K$8 -> 0 | ... U12: =3_资金筹措!U$8 -> 0 | V12: =SUM(D12:U12) -> 122417.01
A13: 2.2 | B13: 流动资金 | C13: 万元 | D13: =2_流动资金!D$14 -> 0 | E13: =2_流动资金!E$14 -> 1731.8547 | F13: =2_流动资金!F$14 -> 221.88679 | G13: =2_流动资金!G$14 -> 0 | H13: =2_流动资金!H$14 -> 0 | I13: =2_流动资金!I$14 -> 0 | J13: =2_流动资金!J$14 -> 0 | K13: =2_流动资金!K$14 -> 0 | ... U13: =2_流动资金!U$14 -> 0 | V13: =SUM(D13:U13) -> 1953.7415
A14: 2.3 | B14: 经营成本 | C14: 万元 | D14: =4_总成本费用!D$23 -> 0 | E14: =4_总成本费用!E$23 -> 3079.7316 | F14: =4_总成本费用!F$23 -> 3157.9766 | G14: =4_总成本费用!G$23 -> 3157.9766 | H14: =4_总成本费用!H$23 -> 4047.1276 | I14: =4_总成本费用!I$23 -> 4047.1276 | J14: =4_总成本费用!J$23 -> 4047.1276 | K14: =4_总成本费用!K$23 -> 4936.2785 | ... U14: =4_总成本费用!U$23 -> 0 | V14: =SUM(D14:U14) -> 41282.182
A15: 2.4 | B15: 税金及附加 | C15: 万元 | D15: =6_收入税金!D$17 -> 0 | E15: =6_收入税金!E$17 -> 0 | F15: =6_收入税金!F$17 -> 0 | G15: =6_收入税金!G$17 -> 0 | H15: =6_收入税金!H$17 -> 0 | I15: =6_收入税金!I$17 -> 0 | J15: =6_收入税金!J$17 -> 0 | K15: =6_收入税金!K$17 -> 0 | ... U15: =6_收入税金!U$17 -> 0 | V15: =SUM(D15:U15) -> 0
A16: 2.5 | B16: 维持运营投资 | C16: 如有中期设备更新在此填入 | D16: =0 -> 0 | E16: =0 -> 0 | F16: =0 -> 0 | G16: =0 -> 0 | H16: =0 -> 0 | I16: =0 -> 0 | J16: =0 -> 0 | K16: =0 -> 0 | ... U16: =0 -> 0 | V16: =SUM(D16:U16) -> 0
A17: 2 | B17: 现金流出 | C17: 万元 | D17: =D12+D13+D14+D15+D16 -> 122417.01 | E17: =E12+E13+E14+E15+E16 -> 4811.5863 | F17: =F12+F13+F14+F15+F16 -> 3379.8634 | G17: =G12+G13+G14+G15+G16 -> 3157.9766 | H17: =H12+H13+H14+H15+H16 -> 4047.1276 | I17: =I12+I13+I14+I15+I16 -> 4047.1276 | J17: =J12+J13+J14+J15+J16 -> 4047.1276 | K17: =K12+K13+K14+K15+K16 -> 4936.2785 | ... U17: =U12+U13+U14+U15+U16 -> 0 | V17: =SUM(D17:U17) -> 165652.93
A18: 3 | B18: 所得税前净现金流量 | C18: 万元 | D18: =D11-D17 -> -122417.01 | E18: =E11-E17 -> 16489.546 | F18: =F11-F17 -> 20583.91 | G18: =G11-G17 -> 20805.797 | H18: =H11-H17 -> 19916.646 | I18: =I11-I17 -> 19916.646 | J18: =J11-J17 -> 19916.646 | K18: =K11-K17 -> 19027.495 | ... U18: =U11-U17 -> 0 | V18: =SUM(D18:U18) -> 84506.206
A19: 4 | B19: 所得税前累计净现金流量 | C19: 万元 | D19: =D18 -> -122417.01 | E19: =IF(1=0,E18,D19+E18) -> -105927.46 | F19: =IF(2=0,F18,E19+F18) -> -85343.55 | G19: =IF(3=0,G18,F19+G18) -> -64537.753 | H19: =IF(4=0,H18,G19+H18) -> -44621.107 | I19: =IF(5=0,I18,H19+I18) -> -24704.461 | J19: =IF(6=0,J18,I19+J18) -> -4787.8152 | K19: =IF(7=0,K18,J19+K18) -> 14239.68 | L19: =IF(8=0,L18,K19+L18) -> 33267.175 | M19: =IF(9=0,M18,L19+M18) -> 52294.67 | N19: =IF(10=0,N18,M19+N18) -> 84506.206 | O19: =IF(11=0,O18,N19+O18) -> 84506.206 | P19: =IF(12=0,P18,O19+P18) -> 84506.206 | Q19: =IF(13=0,Q18,P19+Q18) -> 84506.206 | R19: =IF(14=0,R18,Q19+R18) -> 84506.206 | S19: =IF(15=0,S18,R19+S18) -> 84506.206 | T19: =IF(16=0,T18,S19+T18) -> 84506.206 | U19: =IF(17=0,U18,T19+U18) -> 84506.206
A20: 5 | B20: 调整所得税 | C20: 万元 | D20: =7_利润!D$21 -> 0 | E20: =7_利润!E$21 -> 0 | F20: =7_利润!F$21 -> 444.58346 | G20: =7_利润!G$21 -> 444.58346 | H20: =7_利润!H$21 -> 222.29572 | I20: =7_利润!I$21 -> 222.29572 | J20: =7_利润!J$21 -> 4730.7247 | K20: =7_利润!K$21 -> 4508.437 | ... U20: =7_利润!U$21 -> 0 | V20: =SUM(D20:U20) -> 24098.231
A21: 6 | B21: 所得税后净现金流量 | C21: 万元 | D21: =D18-D20 -> -122417.01 | E21: =E18-E20 -> 16489.546 | F21: =F18-F20 -> 20139.327 | G21: =G18-G20 -> 20361.213 | H21: =H18-H20 -> 19694.35 | I21: =I18-I20 -> 19694.35 | J21: =J18-J20 -> 15185.921 | K21: =K18-K20 -> 14519.058 | ... U21: =U18-U20 -> 0 | V21: =SUM(D21:U21) -> 60407.975
A22: 7 | B22: 所得税后累计净现金流量 | C22: 万元 | D22: =D21 -> -122417.01 | E22: =IF(1=0,E21,D22+E21) -> -105927.46 | F22: =IF(2=0,F21,E22+F21) -> -85788.134 | G22: =IF(3=0,G21,F22+G21) -> -65426.92 | H22: =IF(4=0,H21,G22+H21) -> -45732.57 | I22: =IF(5=0,I21,H22+I21) -> -26038.22 | J22: =IF(6=0,J21,I22+J21) -> -10852.298 | K22: =IF(7=0,K21,J22+K21) -> 3666.7598 | L22: =IF(8=0,L21,K22+L21) -> 18185.818 | M22: =IF(9=0,M21,L22+M21) -> 32704.876 | N22: =IF(10=0,N21,M22+N21) -> 60407.975 | O22: =IF(11=0,O21,N22+O21) -> 60407.975 | P22: =IF(12=0,P21,O22+P21) -> 60407.975 | Q22: =IF(13=0,Q21,P22+Q21) -> 60407.975 | R22: =IF(14=0,R21,Q22+R21) -> 60407.975 | S22: =IF(15=0,S21,R22+S21) -> 60407.975 | T22: =IF(16=0,T21,S22+T21) -> 60407.975 | U22: =IF(17=0,U21,T22+U21) -> 60407.975
B23: 折现系数 1/(1+ic)^t | D23: =IF(D$4="",0,1/(1+0_参数!$C$14)^D$3) -> 0.92592593 | E23: =IF(E$4="",0,1/(1+0_参数!$C$14)^E$3) -> 0.85733882 | F23: =IF(F$4="",0,1/(1+0_参数!$C$14)^F$3) -> 0.79383224 | G23: =IF(G$4="",0,1/(1+0_参数!$C$14)^G$3) -> 0.73502985 | H23: =IF(H$4="",0,1/(1+0_参数!$C$14)^H$3) -> 0.6805832 | I23: =IF(I$4="",0,1/(1+0_参数!$C$14)^I$3) -> 0.63016963 | J23: =IF(J$4="",0,1/(1+0_参数!$C$14)^J$3) -> 0.5834904 | K23: =IF(K$4="",0,1/(1+0_参数!$C$14)^K$3) -> 0.54026888 | ... U23: =IF(U$4="",0,1/(1+0_参数!$C$14)^U$3) -> 0
B24: 税前折现净现金流量 | C24: 万元 | D24: =D18*D23 -> -113349.08 | E24: =E18*E23 -> 14137.128 | F24: =F18*F23 -> 16340.172 | G24: =G18*G23 -> 15292.882 | H24: =H18*H23 -> 13554.935 | I24: =I18*I23 -> 12550.865 | J24: =J18*J23 -> 11621.172 | K24: =K18*K23 -> 10279.964 | ... U24: =U18*U23 -> 0 | V24: =SUM(D24:U24) -> 12574.909
B25: 税前累计折现净现金流量 | C25: 万元 | D25: =D24 -> -113349.08 | E25: =IF(1=0,E24,D25+E24) -> -99211.952 | F25: =IF(2=0,F24,E25+F24) -> -82871.78 | G25: =IF(3=0,G24,F25+G24) -> -67578.899 | H25: =IF(4=0,H24,G25+H24) -> -54023.964 | I25: =IF(5=0,I24,H25+I24) -> -41473.099 | J25: =IF(6=0,J24,I25+J24) -> -29851.927 | K25: =IF(7=0,K24,J25+K24) -> -19571.963 | L25: =IF(8=0,L24,K25+L24) -> -10053.479 | M25: =IF(9=0,M24,L25+M24) -> -1240.0669 | N25: =IF(10=0,N24,M25+N24) -> 12574.909 | O25: =IF(11=0,O24,N25+O24) -> 12574.909 | P25: =IF(12=0,P24,O25+P24) -> 12574.909 | Q25: =IF(13=0,Q24,P25+Q24) -> 12574.909 | R25: =IF(14=0,R24,Q25+R24) -> 12574.909 | S25: =IF(15=0,S24,R25+S24) -> 12574.909 | T25: =IF(16=0,T24,S25+T24) -> 12574.909 | U25: =IF(17=0,U24,T25+U24) -> 12574.909
B26: 税后折现净现金流量 | C26: 万元 | D26: =D21*D23 -> -113349.08 | E26: =E21*E23 -> 14137.128 | F26: =F21*F23 -> 15987.247 | G26: =G21*G23 -> 14966.1 | H26: =H21*H23 -> 13403.644 | I26: =I21*I23 -> 12410.781 | J26: =J21*J23 -> 8860.8392 | K26: =K21*K23 -> 7844.1953 | ... U26: =U21*U23 -> 0 | V26: =SUM(D26:U26) -> 130.51575
B27: 税后累计折现净现金流量 | C27: 万元 | D27: =D26 -> -113349.08 | E27: =IF(1=0,E26,D27+E26) -> -99211.952 | F27: =IF(2=0,F26,E27+F26) -> -83224.705 | G27: =IF(3=0,G26,F27+G26) -> -68258.605 | H27: =IF(4=0,H26,G27+H26) -> -54854.962 | I27: =IF(5=0,I26,H27+I26) -> -42444.18 | J27: =IF(6=0,J26,I27+J26) -> -33583.341 | K27: =IF(7=0,K26,J27+K26) -> -25739.146 | L27: =IF(8=0,L26,K27+L26) -> -18476.002 | M27: =IF(9=0,M26,L27+M26) -> -11750.869 | N27: =IF(10=0,N26,M27+N26) -> 130.51575 | O27: =IF(11=0,O26,N27+O26) -> 130.51575 | P27: =IF(12=0,P26,O27+P26) -> 130.51575 | Q27: =IF(13=0,Q26,P27+Q26) -> 130.51575 | R27: =IF(14=0,R26,Q27+R26) -> 130.51575 | S27: =IF(15=0,S26,R27+S26) -> 130.51575 | T27: =IF(16=0,T26,S27+T26) -> 130.51575 | U27: =IF(17=0,U26,T27+U26) -> 130.51575
B28: 评价指标
B29: 财务内部收益率（税前） | D29: =IFERROR(IRR(D18:U18),0) -> 0.10281066
B30: 财务内部收益率（税后） | D30: =IFERROR(IRR(D21:U21),0) -> 0.080255495
B31: 财务净现值（税前，ic） | D31: =NPV(0_参数!$C$14,D18:U18) -> 12574.909
B32: 财务净现值（税后，ic） | D32: =NPV(0_参数!$C$14,D21:U21) -> 130.51575
B33: 静态投资回收期（税前，含建设期） | D33: =IFERROR(COUNTIF(D19:U19,"<0")+(-INDEX(D19:U19,COUNTIF(D19:U19,"<0")))/INDEX(D18:U18,COUNTIF(D19:U19,"<0")+1),"未回收") -> 7.2516261
B34: 静态投资回收期（税后，含建设期） | D34: =IFERROR(COUNTIF(D22:U22,"<0")+(-INDEX(D22:U22,COUNTIF(D22:U22,"<0")))/INDEX(D21:U21,COUNTIF(D22:U22,"<0")+1),"未回收") -> 7.747452
B35: 动态投资回收期（税前，含建设期） | D35: =IFERROR(COUNTIF(D25:U25,"<0")+(-INDEX(D25:U25,COUNTIF(D25:U25,"<0")))/INDEX(D24:U24,COUNTIF(D25:U25,"<0")+1),"未回收") -> 10.089763
B36: 动态投资回收期（税后，含建设期） | D36: =IFERROR(COUNTIF(D27:U27,"<0")+(-INDEX(D27:U27,COUNTIF(D27:U27,"<0")))/INDEX(D26:U26,COUNTIF(D27:U27,"<0")+1),"未回收") -> 10.989015
B38: 盈亏平衡点（正常年，生产能力利用率）= 固定成本 / (收入 − 可变成本 − 税金附加) | D38: =IFERROR(INDEX(4_总成本费用!D$29:U$29,0_参数!$C$9+0_参数!$C$15)/(INDEX(6_收入税金!D$11:U$11,0_参数!$C$9+0_参数!$C$15)-INDEX(4_总成本费用!D$28:U$28,0_参数!$C$9+0_参数!$C$15)-INDEX(6_收入税金!D$17:U$17,0_参数!$C$9+0_参数!$C$15)),0) -> 1.032887
B39: 投资利润率（平均年利润总额 / 总投资） | D39: =IFERROR(7_利润!$V$12/1_总投资估算!$G$33,0) -> 0.062618968
B40: 投资利税率（(平均年利润总额 + 税金附加 + 应纳增值税) / 总投资） | D40: =IFERROR((7_利润!$V$12+6_收入税金!$V$17+6_收入税金!$V$15)/1_总投资估算!$G$33,0) -> 0.062618968

Sheet 9_财务计划现金流量
A1: 附表 9 财务计划现金流量表（含融资）
A2: 单位：万元。累计盈余资金须全程 ≥ 0（校核 C7）
A3: 序号 | B3: 项目 \ 年份 | C3: 单位/说明 | D3: 1 | E3: =D3+1 -> 2 | F3: =E3+1 -> 3 | G3: =F3+1 -> 4 | H3: =G3+1 -> 5 | I3: =H3+1 -> 6 | J3: =I3+1 -> 7 | K3: =J3+1 -> 8 | L3: =K3+1 -> 9 | ... U3: =T3+1 -> 18 | V3: 合计/平均
B4: 阶段 | D4: =IF(D$3<=0_参数!$C$9,"建设",IF(D$3<=0_参数!$C$9+0_参数!$C$10,"运营","")) -> 建设 | E4: =IF(E$3<=0_参数!$C$9,"建设",IF(E$3<=0_参数!$C$9+0_参数!$C$10,"运营","")) -> 运营 | F4: =IF(F$3<=0_参数!$C$9,"建设",IF(F$3<=0_参数!$C$9+0_参数!$C$10,"运营","")) -> 运营 | G4: =IF(G$3<=0_参数!$C$9,"建设",IF(G$3<=0_参数!$C$9+0_参数!$C$10,"运营","")) -> 运营 | H4: =IF(H$3<=0_参数!$C$9,"建设",IF(H$3<=0_参数!$C$9+0_参数!$C$10,"运营","")) -> 运营 | I4: =IF(I$3<=0_参数!$C$9,"建设",IF(I$3<=0_参数!$C$9+0_参数!$C$10,"运营","")) -> 运营 | J4: =IF(J$3<=0_参数!$C$9,"建设",IF(J$3<=0_参数!$C$9+0_参数!$C$10,"运营","")) -> 运营 | K4: =IF(K$3<=0_参数!$C$9,"建设",IF(K$3<=0_参数!$C$9+0_参数!$C$10,"运营","")) -> 运营 | ... U4: =IF(U$3<=0_参数!$C$9,"建设",IF(U$3<=0_参数!$C$9+0_参数!$C$10,"运营",""))
B5: 运营年序号 | D5: =IF(D$4="运营",D$3-0_参数!$C$9,0) -> 0 | E5: =IF(E$4="运营",E$3-0_参数!$C$9,0) -> 1 | F5: =IF(F$4="运营",F$3-0_参数!$C$9,0) -> 2 | G5: =IF(G$4="运营",G$3-0_参数!$C$9,0) -> 3 | H5: =IF(H$4="运营",H$3-0_参数!$C$9,0) -> 4 | I5: =IF(I$4="运营",I$3-0_参数!$C$9,0) -> 5 | J5: =IF(J$4="运营",J$3-0_参数!$C$9,0) -> 6 | K5: =IF(K$4="运营",K$3-0_参数!$C$9,0) -> 7 | ... U5: =IF(U$4="运营",U$3-0_参数!$C$9,0) -> 0
B6: 建设年序号 | D6: =IF(D$4="建设",D$3,0) -> 1 | E6: =IF(E$4="建设",E$3,0) -> 0 | F6: =IF(F$4="建设",F$3,0) -> 0 | G6: =IF(G$4="建设",G$3,0) -> 0 | H6: =IF(H$4="建设",H$3,0) -> 0 | I6: =IF(I$4="建设",I$3,0) -> 0 | J6: =IF(J$4="建设",J$3,0) -> 0 | K6: =IF(K$4="建设",K$3,0) -> 0 | ... U6: =IF(U$4="建设",U$3,0) -> 0
A7: 1.1.1 | B7: 营业收入（不含税） | C7: 万元 | D7: =6_收入税金!D$11 -> 0 | E7: =6_收入税金!E$11 -> 21301.132 | F7: =6_收入税金!F$11 -> 23963.774 | G7: =6_收入税金!G$11 -> 23963.774 | H7: =6_收入税金!H$11 -> 23963.774 | I7: =6_收入税金!I$11 -> 23963.774 | J7: =6_收入税金!J$11 -> 23963.774 | K7: =6_收入税金!K$11 -> 23963.774 | ... U7: =6_收入税金!U$11 -> 0 | V7: =SUM(D7:U7) -> 236975.09
A8: 1.1.2 | B8: 增值税销项税额 | C8: 万元 | D8: =6_收入税金!D$12 -> 0 | E8: =6_收入税金!E$12 -> 1278.0679 | F8: =6_收入税金!F$12 -> 1437.8264 | G8: =6_收入税金!G$12 -> 1437.8264 | H8: =6_收入税金!H$12 -> 1437.8264 | I8: =6_收入税金!I$12 -> 1437.8264 | J8: =6_收入税金!J$12 -> 1437.8264 | K8: =6_收入税金!K$12 -> 1437.8264 | ... U8: =6_收入税金!U$12 -> 0 | V8: =SUM(D8:U8) -> 14218.506
A9: 1.1.3 | B9: 补贴收入 | C9: 万元 | D9: =7_利润!D$10 -> 0 | E9: =7_利润!E$10 -> 0 | F9: =7_利润!F$10 -> 0 | G9: =7_利润!G$10 -> 0 | H9: =7_利润!H$10 -> 0 | I9: =7_利润!I$10 -> 0 | J9: =7_利润!J$10 -> 0 | K9: =7_利润!K$10 -> 0 | ... U9: =7_利润!U$10 -> 0 | V9: =SUM(D9:U9) -> 0
A10: 1.1 | B10: 经营活动现金流入 | C10: 万元 | D10: =D7+D8+D9 -> 0 | E10: =E7+E8+E9 -> 22579.2 | F10: =F7+F8+F9 -> 25401.6 | G10: =G7+G8+G9 -> 25401.6 | H10: =H7+H8+H9 -> 25401.6 | I10: =I7+I8+I9 -> 25401.6 | J10: =J7+J8+J9 -> 25401.6 | K10: =K7+K8+K9 -> 25401.6 | ... U10: =U7+U8+U9 -> 0 | V10: =SUM(D10:U10) -> 251193.6
A11: 1.2.1 | B11: 经营成本 | C11: 万元 | D11: =4_总成本费用!D$23 -> 0 | E11: =4_总成本费用!E$23 -> 3079.7316 | F11: =4_总成本费用!F$23 -> 3157.9766 | G11: =4_总成本费用!G$23 -> 3157.9766 | H11: =4_总成本费用!H$23 -> 4047.1276 | I11: =4_总成本费用!I$23 -> 4047.1276 | J11: =4_总成本费用!J$23 -> 4047.1276 | K11: =4_总成本费用!K$23 -> 4936.2785 | ... U11: =4_总成本费用!U$23 -> 0 | V11: =SUM(D11:U11) -> 41282.182
A12: 1.2.2 | B12: 增值税进项税额（经营） | C12: 万元 | D12: =6_收入税金!D$13 -> 0 | E12: =6_收入税金!E$13 -> 192.66659 | F12: =6_收入税金!F$13 -> 202.83844 | G12: =6_收入税金!G$13 -> 202.83844 | H12: =6_收入税金!H$13 -> 256.1875 | I12: =6_收入税金!I$13 -> 256.1875 | J12: =6_收入税金!J$13 -> 256.1875 | K12: =6_收入税金!K$13 -> 309.53655 | ... U12: =6_收入税金!U$13 -> 0 | V12: =SUM(D12:U12) -> 2605.0522
A13: 1.2.3 | B13: 税金及附加 | C13: 万元 | D13: =6_收入税金!D$17 -> 0 | E13: =6_收入税金!E$17 -> 0 | F13: =6_收入税金!F$17 -> 0 | G13: =6_收入税金!G$17 -> 0 | H13: =6_收入税金!H$17 -> 0 | I13: =6_收入税金!I$17 -> 0 | J13: =6_收入税金!J$17 -> 0 | K13: =6_收入税金!K$17 -> 0 | ... U13: =6_收入税金!U$17 -> 0 | V13: =SUM(D13:U13) -> 0
A14: 1.2.4 | B14: 应纳增值税 | C14: 万元 | D14: =6_收入税金!D$15 -> 0 | E14: =6_收入税金!E$15 -> 0 | F14: =6_收入税金!F$15 -> 0 | G14: =6_收入税金!G$15 -> 0 | H14: =6_收入税金!H$15 -> 0 | I14: =6_收入税金!I$15 -> 0 | J14: =6_收入税金!J$15 -> 0 | K14: =6_收入税金!K$15 -> 0 | ... U14: =6_收入税金!U$15 -> 0 | V14: =SUM(D14:U14) -> 0
A15: 1.2.5 | B15: 所得税 | C15: 万元 | D15: =7_利润!D$14 -> 0 | E15: =7_利润!E$14 -> 0 | F15: =7_利润!F$14 -> 0 | G15: =7_利润!G$14 -> 0 | H15: =7_利润!H$14 -> 0 | I15: =7_利润!I$14 -> 0 | J15: =7_利润!J$14 -> 2290.0872 | K15: =7_利润!K$14 -> 4184.6105 | ... U15: =7_利润!U$14 -> 0 | V15: =SUM(D15:U15) -> 19496.319
A16: 1.2 | B16: 经营活动现金流出 | C16: 万元 | D16: =SUM(D11:D15) -> 0 | E16: =SUM(E11:E15) -> 3272.3982 | F16: =SUM(F11:F15) -> 3360.8151 | G16: =SUM(G11:G15) -> 3360.8151 | H16: =SUM(H11:H15) -> 4303.3151 | I16: =SUM(I11:I15) -> 4303.3151 | J16: =SUM(J11:J15) -> 6593.4023 | K16: =SUM(K11:K15) -> 9430.4256 | ... U16: =SUM(U11:U15) -> 0 | V16: =SUM(D16:U16) -> 63383.553
A17: 1 | B17: 经营活动净现金流量 | C17: 万元 | D17: =D10-D16 -> 0 | E17: =E10-E16 -> 19306.802 | F17: =F10-F16 -> 22040.785 | G17: =G10-G16 -> 22040.785 | H17: =H10-H16 -> 21098.285 | I17: =I10-I16 -> 21098.285 | J17: =J10-J16 -> 18808.198 | K17: =K10-K16 -> 15971.174 | ... U17: =U10-U16 -> 0 | V17: =SUM(D17:U17) -> 187810.05
A18: 2.1 | B18: 建设投资 | C18: 万元 | D18: =3_资金筹措!D$8 -> 122417.01 | E18: =3_资金筹措!E$8 -> 0 | F18: =3_资金筹措!F$8 -> 0 | G18: =3_资金筹措!G$8 -> 0 | H18: =3_资金筹措!H$8 -> 0 | I18: =3_资金筹措!I$8 -> 0 | J18: =3_资金筹措!J$8 -> 0 | K18: =3_资金筹措!K$8 -> 0 | ... U18: =3_资金筹措!U$8 -> 0 | V18: =SUM(D18:U18) -> 122417.01
A19: 2.2 | B19: 流动资金 | C19: 万元 | D19: =2_流动资金!D$14 -> 0 | E19: =2_流动资金!E$14 -> 1731.8547 | F19: =2_流动资金!F$14 -> 221.88679 | G19: =2_流动资金!G$14 -> 0 | H19: =2_流动资金!H$14 -> 0 | I19: =2_流动资金!I$14 -> 0 | J19: =2_流动资金!J$14 -> 0 | K19: =2_流动资金!K$14 -> 0 | ... U19: =2_流动资金!U$14 -> 0 | V19: =SUM(D19:U19) -> 1953.7415
A20: 2.3 | B20: 维持运营投资 | C20: 万元 | D20: =8_现金流量!D$16 -> 0 | E20: =8_现金流量!E$16 -> 0 | F20: =8_现金流量!F$16 -> 0 | G20: =8_现金流量!G$16 -> 0 | H20: =8_现金流量!H$16 -> 0 | I20: =8_现金流量!I$16 -> 0 | J20: =8_现金流量!J$16 -> 0 | K20: =8_现金流量!K$16 -> 0 | ... U20: =8_现金流量!U$16 -> 0 | V20: =SUM(D20:U20) -> 0
A21: 2 | B21: 投资活动净现金流量 | C21: 万元 | D21: =-(D18+D19+D20) -> -122417.01 | E21: =-(E18+E19+E20) -> -1731.8547 | F21: =-(F18+F19+F20) -> -221.88679 | G21: =-(G18+G19+G20) -> 0 | H21: =-(H18+H19+H20) -> 0 | I21: =-(I18+I19+I20) -> 0 | J21: =-(J18+J19+J20) -> 0 | K21: =-(K18+K19+K20) -> 0 | ... U21: =-(U18+U19+U20) -> 0 | V21: =SUM(D21:U21) -> -124370.75
A22: 3.1.1 | B22: 项目资本金投入 | C22: 万元 | D22: =3_资金筹措!D$15 -> 20000 | E22: =3_资金筹措!E$15 -> 519.55642 | F22: =3_资金筹措!F$15 -> 66.566038 | G22: =3_资金筹措!G$15 -> 0 | H22: =3_资金筹措!H$15 -> 0 | I22: =3_资金筹措!I$15 -> 0 | J22: =3_资金筹措!J$15 -> 0 | K22: =3_资金筹措!K$15 -> 0 | ... U22: =3_资金筹措!U$15 -> 0 | V22: =SUM(D22:U22) -> 20586.122
A23: 3.1.2 | B23: 建设投资借款（含资本化利息） | C23: 万元 | D23: =3_资金筹措!D$16+3_资金筹措!D$17 -> 103953.26 | E23: =3_资金筹措!E$16+3_资金筹措!E$17 -> 0 | F23: =3_资金筹措!F$16+3_资金筹措!F$17 -> 0 | G23: =3_资金筹措!G$16+3_资金筹措!G$17 -> 0 | H23: =3_资金筹措!H$16+3_资金筹措!H$17 -> 0 | I23: =3_资金筹措!I$16+3_资金筹措!I$17 -> 0 | J23: =3_资金筹措!J$16+3_资金筹措!J$17 -> 0 | K23: =3_资金筹措!K$16+3_资金筹措!K$17 -> 0 | ... U23: =3_资金筹措!U$16+3_资金筹措!U$17 -> 0 | V23: =SUM(D23:U23) -> 103953.26
A24: 3.1.3 | B24: 流动资金借款 | C24: 万元 | D24: =3_资金筹措!D$18 -> 0 | E24: =3_资金筹措!E$18 -> 1212.2983 | F24: =3_资金筹措!F$18 -> 155.32075 | G24: =3_资金筹措!G$18 -> 0 | H24: =3_资金筹措!H$18 -> 0 | I24: =3_资金筹措!I$18 -> 0 | J24: =3_资金筹措!J$18 -> 0 | K24: =3_资金筹措!K$18 -> 0 | ... U24: =3_资金筹措!U$18 -> 0 | V24: =SUM(D24:U24) -> 1367.6191
A25: 3.1 | B25: 筹资活动现金流入 | C25: 万元 | D25: =D22+D23+D24 -> 123953.26 | E25: =E22+E23+E24 -> 1731.8547 | F25: =F22+F23+F24 -> 221.88679 | G25: =G22+G23+G24 -> 0 | H25: =H22+H23+H24 -> 0 | I25: =I22+I23+I24 -> 0 | J25: =J22+J23+J24 -> 0 | K25: =K22+K23+K24 -> 0 | ... U25: =U22+U23+U24 -> 0 | V25: =SUM(D25:U25) -> 125907
A26: 3.2.1 | B26: 各种利息支出（含建设期） | C26: 万元 | D26: =11_还本付息!D$9+11_还本付息!D$10+11_还本付息!D$19 -> 1536.2551 | E26: =11_还本付息!E$9+11_还本付息!E$10+11_还本付息!E$19 -> 3139.8131 | F26: =11_还本付息!F$9+11_还本付息!F$10+11_还本付息!F$19 -> 2851.8866 | G26: =11_还本付息!G$9+11_还本付息!G$10+11_还本付息!G$19 -> 2542.7449 | H26: =11_还本付息!H$9+11_还本付息!H$10+11_还本付息!H$19 -> 2230.8852 | I26: =11_还本付息!I$9+11_还本付息!I$10+11_还本付息!I$19 -> 1919.0254 | J26: =11_还本付息!J$9+11_还本付息!J$10+11_还本付息!J$19 -> 1607.1656 | K26: =11_还本付息!K$9+11_还本付息!K$10+11_还本付息!K$19 -> 1295.3058 | ... U26: =11_还本付息!U$9+11_还本付息!U$10+11_还本付息!U$19 -> 0 | V26: =SUM(D26:U26) -> 19137.84
A27: 3.2.2 | B27: 偿还债务本金 | C27: 万元 | D27: =11_还本付息!D$11+11_还本付息!D$17 -> 0 | E27: =11_还本付息!E$11+11_还本付息!E$17 -> 10395.326 | F27: =11_还本付息!F$11+11_还本付息!F$17 -> 10395.326 | G27: =11_还本付息!G$11+11_还本付息!G$17 -> 10395.326 | H27: =11_还本付息!H$11+11_还本付息!H$17 -> 10395.326 | I27: =11_还本付息!I$11+11_还本付息!I$17 -> 10395.326 | J27: =11_还本付息!J$11+11_还本付息!J$17 -> 10395.326 | K27: =11_还本付息!K$11+11_还本付息!K$17 -> 10395.326 | ... U27: =11_还本付息!U$11+11_还本付息!U$17 -> 0 | V27: =SUM(D27:U27) -> 105320.88
A28: 3.2.3 | B28: 应付利润（股利分配） | C28: 万元 | D28: =0 -> 0 | E28: =0 -> 0 | F28: =0 -> 0 | G28: =0 -> 0 | H28: =0 -> 0 | I28: =0 -> 0 | J28: =0 -> 0 | K28: =0 -> 0 | ... U28: =0 -> 0 | V28: =SUM(D28:U28) -> 0
A29: 3.2 | B29: 筹资活动现金流出 | C29: 万元 | D29: =D26+D27+D28 -> 1536.2551 | E29: =E26+E27+E28 -> 13535.139 | F29: =F26+F27+F28 -> 13247.213 | G29: =G26+G27+G28 -> 12938.071 | H29: =H26+H27+H28 -> 12626.211 | I29: =I26+I27+I28 -> 12314.351 | J29: =J26+J27+J28 -> 12002.492 | K29: =K26+K27+K28 -> 11690.632 | ... U29: =U26+U27+U28 -> 0 | V29: =SUM(D29:U29) -> 124458.72
A30: 3 | B30: 筹资活动净现金流量 | C30: 万元 | D30: =D25-D29 -> 122417.01 | E30: =E25-E29 -> -11803.284 | F30: =F25-F29 -> -13025.326 | G30: =G25-G29 -> -12938.071 | H30: =H25-H29 -> -12626.211 | I30: =I25-I29 -> -12314.351 | J30: =J25-J29 -> -12002.492 | K30: =K25-K29 -> -11690.632 | ... U30: =U25-U29 -> 0 | V30: =SUM(D30:U30) -> 1448.2822
A31: 4 | B31: 净现金流量 | C31: 万元 | D31: =D17+D21+D30 -> 0 | E31: =E17+E21+E30 -> 5771.6626 | F31: =F17+F21+F30 -> 8793.5722 | G31: =G17+G21+G30 -> 9102.7139 | H31: =H17+H21+H30 -> 8472.0737 | I31: =I17+I21+I30 -> 8783.9334 | J31: =J17+J21+J30 -> 6805.706 | K31: =K17+K21+K30 -> 4280.5425 | ... U31: =U17+U21+U30 -> 0 | V31: =SUM(D31:U31) -> 64887.582
A32: 5 | B32: 累计盈余资金 | C32: 万元 | D32: =D31 -> 0 | E32: =IF(1=0,E31,D32+E31) -> 5771.6626 | F32: =IF(2=0,F31,E32+F31) -> 14565.235 | G32: =IF(3=0,G31,F32+G31) -> 23667.949 | H32: =IF(4=0,H31,G32+H31) -> 32140.022 | I32: =IF(5=0,I31,H32+I31) -> 40923.956 | J32: =IF(6=0,J31,I32+J31) -> 47729.662 | K32: =IF(7=0,K31,J32+K31) -> 52010.204 | L32: =IF(8=0,L31,K32+L31) -> 56524.642 | M32: =IF(9=0,M31,L32+M31) -> 61272.974 | N32: =IF(10=0,N31,M32+N31) -> 64887.582 | O32: =IF(11=0,O31,N32+O31) -> 64887.582 | P32: =IF(12=0,P31,O32+P31) -> 64887.582 | Q32: =IF(13=0,Q31,P32+Q31) -> 64887.582 | R32: =IF(14=0,R31,Q32+R31) -> 64887.582 | S32: =IF(15=0,S31,R32+S31) -> 64887.582 | T32: =IF(16=0,T31,S32+T31) -> 64887.582 | U32: =IF(17=0,U31,T32+U31) -> 64887.582 | V32: =INDEX(D32:U32,0_参数!$C$9+0_参数!$C$10) -> 64887.582

Sheet 10_资产负债
A1: 附表 10 资产负债表（简化）
A2: 单位：万元。资产 = 负债 + 所有者权益，差额行应为 0（校核 C6）
A3: 序号 | B3: 项目 \ 年份 | C3: 单位/说明 | D3: 1 | E3: =D3+1 -> 2 | F3: =E3+1 -> 3 | G3: =F3+1 -> 4 | H3: =G3+1 -> 5 | I3: =H3+1 -> 6 | J3: =I3+1 -> 7 | K3: =J3+1 -> 8 | L3: =K3+1 -> 9 | ... U3: =T3+1 -> 18 | V3: 合计/平均
B4: 阶段 | D4: =IF(D$3<=0_参数!$C$9,"建设",IF(D$3<=0_参数!$C$9+0_参数!$C$10,"运营","")) -> 建设 | E4: =IF(E$3<=0_参数!$C$9,"建设",IF(E$3<=0_参数!$C$9+0_参数!$C$10,"运营","")) -> 运营 | F4: =IF(F$3<=0_参数!$C$9,"建设",IF(F$3<=0_参数!$C$9+0_参数!$C$10,"运营","")) -> 运营 | G4: =IF(G$3<=0_参数!$C$9,"建设",IF(G$3<=0_参数!$C$9+0_参数!$C$10,"运营","")) -> 运营 | H4: =IF(H$3<=0_参数!$C$9,"建设",IF(H$3<=0_参数!$C$9+0_参数!$C$10,"运营","")) -> 运营 | I4: =IF(I$3<=0_参数!$C$9,"建设",IF(I$3<=0_参数!$C$9+0_参数!$C$10,"运营","")) -> 运营 | J4: =IF(J$3<=0_参数!$C$9,"建设",IF(J$3<=0_参数!$C$9+0_参数!$C$10,"运营","")) -> 运营 | K4: =IF(K$3<=0_参数!$C$9,"建设",IF(K$3<=0_参数!$C$9+0_参数!$C$10,"运营","")) -> 运营 | ... U4: =IF(U$3<=0_参数!$C$9,"建设",IF(U$3<=0_参数!$C$9+0_参数!$C$10,"运营",""))
B5: 运营年序号 | D5: =IF(D$4="运营",D$3-0_参数!$C$9,0) -> 0 | E5: =IF(E$4="运营",E$3-0_参数!$C$9,0) -> 1 | F5: =IF(F$4="运营",F$3-0_参数!$C$9,0) -> 2 | G5: =IF(G$4="运营",G$3-0_参数!$C$9,0) -> 3 | H5: =IF(H$4="运营",H$3-0_参数!$C$9,0) -> 4 | I5: =IF(I$4="运营",I$3-0_参数!$C$9,0) -> 5 | J5: =IF(J$4="运营",J$3-0_参数!$C$9,0) -> 6 | K5: =IF(K$4="运营",K$3-0_参数!$C$9,0) -> 7 | ... U5: =IF(U$4="运营",U$3-0_参数!$C$9,0) -> 0
B6: 建设年序号 | D6: =IF(D$4="建设",D$3,0) -> 1 | E6: =IF(E$4="建设",E$3,0) -> 0 | F6: =IF(F$4="建设",F$3,0) -> 0 | G6: =IF(G$4="建设",G$3,0) -> 0 | H6: =IF(H$4="建设",H$3,0) -> 0 | I6: =IF(I$4="建设",I$3,0) -> 0 | J6: =IF(J$4="建设",J$3,0) -> 0 | K6: =IF(K$4="建设",K$3,0) -> 0 | ... U6: =IF(U$4="建设",U$3,0) -> 0
A7: 1.1.1 | B7: 货币资金（累计盈余资金 + 现金周转） | C7: 万元 | D7: =9_财务计划现金流量!D$32+2_流动资金!D$9 -> 0 | E7: =9_财务计划现金流量!E$32+2_流动资金!E$9 -> 5822.7626 | F7: =9_财务计划现金流量!F$32+2_流动资金!F$9 -> 14616.335 | G7: =9_财务计划现金流量!G$32+2_流动资金!G$9 -> 23719.049 | H7: =9_财务计划现金流量!H$32+2_流动资金!H$9 -> 32191.122 | I7: =9_财务计划现金流量!I$32+2_流动资金!I$9 -> 40975.056 | J7: =9_财务计划现金流量!J$32+2_流动资金!J$9 -> 47780.762 | K7: =9_财务计划现金流量!K$32+2_流动资金!K$9 -> 52061.304 | ... U7: =9_财务计划现金流量!U$32+2_流动资金!U$9 -> 64887.582
A8: 1.1.2 | B8: 应收账款 | C8: 万元 | D8: =2_流动资金!D$7 -> 0 | E8: =2_流动资金!E$7 -> 1775.0943 | F8: =2_流动资金!F$7 -> 1996.9811 | G8: =2_流动资金!G$7 -> 1996.9811 | H8: =2_流动资金!H$7 -> 1996.9811 | I8: =2_流动资金!I$7 -> 1996.9811 | J8: =2_流动资金!J$7 -> 1996.9811 | K8: =2_流动资金!K$7 -> 1996.9811 | ... U8: =2_流动资金!U$7 -> 0
A9: 1.1.3 | B9: 存货 | C9: 万元 | D9: =2_流动资金!D$8 -> 0 | E9: =2_流动资金!E$8 -> 53.498705 | F9: =2_流动资金!F$8 -> 60.019122 | G9: =2_流动资金!G$8 -> 60.019122 | H9: =2_流动资金!H$8 -> 60.019122 | I9: =2_流动资金!I$8 -> 60.019122 | J9: =2_流动资金!J$8 -> 60.019122 | K9: =2_流动资金!K$8 -> 60.019122 | ... U9: =2_流动资金!U$8 -> 0
A10: 1.1 | B10: 流动资产合计 | C10: 万元 | D10: =D7+D8+D9 -> 0 | E10: =E7+E8+E9 -> 7651.3557 | F10: =F7+F8+F9 -> 16673.335 | G10: =G7+G8+G9 -> 25776.049 | H10: =H7+H8+H9 -> 34248.123 | I10: =I7+I8+I9 -> 43032.056 | J10: =J7+J8+J9 -> 49837.762 | K10: =K7+K8+K9 -> 54118.305 | ... U10: =U7+U8+U9 -> 64887.582
A11: 1.2 | B11: 在建工程（建设期累计投资含利息） | C11: 万元 | D11: =IF(D$4="建设",3_资金筹措!D$8+3_资金筹措!D$9,0) -> 123953.26 | E11: =IF(E$4="建设",IF(1=0,0,D11)+3_资金筹措!E$8+3_资金筹措!E$9,0) -> 0 | F11: =IF(F$4="建设",IF(2=0,0,E11)+3_资金筹措!F$8+3_资金筹措!F$9,0) -> 0 | G11: =IF(G$4="建设",IF(3=0,0,F11)+3_资金筹措!G$8+3_资金筹措!G$9,0) -> 0 | H11: =IF(H$4="建设",IF(4=0,0,G11)+3_资金筹措!H$8+3_资金筹措!H$9,0) -> 0 | I11: =IF(I$4="建设",IF(5=0,0,H11)+3_资金筹措!I$8+3_资金筹措!I$9,0) -> 0 | J11: =IF(J$4="建设",IF(6=0,0,I11)+3_资金筹措!J$8+3_资金筹措!J$9,0) -> 0 | K11: =IF(K$4="建设",IF(7=0,0,J11)+3_资金筹措!K$8+3_资金筹措!K$9,0) -> 0 | L11: =IF(L$4="建设",IF(8=0,0,K11)+3_资金筹措!L$8+3_资金筹措!L$9,0) -> 0 | M11: =IF(M$4="建设",IF(9=0,0,L11)+3_资金筹措!M$8+3_资金筹措!M$9,0) -> 0 | N11: =IF(N$4="建设",IF(10=0,0,M11)+3_资金筹措!N$8+3_资金筹措!N$9,0) -> 0 | O11: =IF(O$4="建设",IF(11=0,0,N11)+3_资金筹措!O$8+3_资金筹措!O$9,0) -> 0 | P11: =IF(P$4="建设",IF(12=0,0,O11)+3_资金筹措!P$8+3_资金筹措!P$9,0) -> 0 | Q11: =IF(Q$4="建设",IF(13=0,0,P11)+3_资金筹措!Q$8+3_资金筹措!Q$9,0) -> 0 | R11: =IF(R$4="建设",IF(14=0,0,Q11)+3_资金筹措!R$8+3_资金筹措!R$9,0) -> 0 | S11: =IF(S$4="建设",IF(15=0,0,R11)+3_资金筹措!S$8+3_资金筹措!S$9,0) -> 0 | T11: =IF(T$4="建设",IF(16=0,0,S11)+3_资金筹措!T$8+3_资金筹措!T$9,0) -> 0 | U11: =IF(U$4="建设",IF(17=0,0,T11)+3_资金筹措!U$8+3_资金筹措!U$9,0) -> 0
A12: 1.3 | B12: 固定资产净值 | C12: 万元 | D12: =IF(D$4="运营",5_折旧摊销!D$28,0) -> 0 | E12: =IF(E$4="运营",5_折旧摊销!E$28,0) -> 92275.048 | F12: =IF(F$4="运营",5_折旧摊销!F$28,0) -> 73256.045 | G12: =IF(G$4="运营",5_折旧摊销!G$28,0) -> 54237.041 | H12: =IF(H$4="运营",5_折旧摊销!H$28,0) -> 35218.038 | I12: =IF(I$4="运营",5_折旧摊销!I$28,0) -> 16199.035 | J12: =IF(J$4="运营",5_折旧摊销!J$28,0) -> 15205.288 | K12: =IF(K$4="运营",5_折旧摊销!K$28,0) -> 14211.541 | ... U12: =IF(U$4="运营",5_折旧摊销!U$28,0) -> 0
A13: 1.4 | B13: 递延资产净值 | C13: 万元 | D13: =IF(D$4="运营",5_折旧摊销!D$32,0) -> 0 | E13: =IF(E$4="运营",5_折旧摊销!E$32,0) -> 33.84 | F13: =IF(F$4="运营",5_折旧摊销!F$32,0) -> 25.38 | G13: =IF(G$4="运营",5_折旧摊销!G$32,0) -> 16.92 | H13: =IF(H$4="运营",5_折旧摊销!H$32,0) -> 8.46 | I13: =IF(I$4="运营",5_折旧摊销!I$32,0) -> 0 | J13: =IF(J$4="运营",5_折旧摊销!J$32,0) -> 0 | K13: =IF(K$4="运营",5_折旧摊销!K$32,0) -> 0 | ... U13: =IF(U$4="运营",5_折旧摊销!U$32,0) -> 0
A14: 1.5 | B14: 期末留抵进项税额 | C14: 万元 | D14: =6_收入税金!D$16 -> 0 | E14: =6_收入税金!E$16 -> 11531.509 | F14: =6_收入税金!F$16 -> 10296.521 | G14: =6_收入税金!G$16 -> 9061.5331 | H14: =6_收入税金!H$16 -> 7879.8941 | I14: =6_收入税金!I$16 -> 6698.2552 | J14: =6_收入税金!J$16 -> 5516.6163 | K14: =6_收入税金!K$16 -> 4388.3264 | ... U14: =6_收入税金!U$16 -> 0
A15: 1 | B15: 资产总计 | C15: 万元 | D15: =D10+D11+D12+D13+D14 -> 123953.26 | E15: =E10+E11+E12+E13+E14 -> 111491.75 | F15: =F10+F11+F12+F13+F14 -> 100251.28 | G15: =G10+G11+G12+G13+G14 -> 89091.543 | H15: =H10+H11+H12+H13+H14 -> 77354.515 | I15: =I10+I11+I12+I13+I14 -> 65929.347 | J15: =J10+J11+J12+J13+J14 -> 70559.666 | K15: =K10+K11+K12+K13+K14 -> 72718.172 | ... U15: =U10+U11+U12+U13+U14 -> 64887.582
A16: 2.1 | B16: 流动负债（应付账款） | C16: 万元 | D16: =2_流动资金!D$11 -> 0 | E16: =2_流动资金!E$11 -> 147.83833 | F16: =2_流动资金!F$11 -> 154.35874 | G16: =2_流动资金!G$11 -> 154.35874 | H16: =2_流动资金!H$11 -> 154.35874 | I16: =2_流动资金!I$11 -> 154.35874 | J16: =2_流动资金!J$11 -> 154.35874 | K16: =2_流动资金!K$11 -> 154.35874 | ... U16: =2_流动资金!U$11 -> 0
A17: 2.2 | B17: 建设投资借款余额 | C17: 万元 | D17: =11_还本付息!D$12 -> 103953.26 | E17: =11_还本付息!E$12 -> 93557.935 | F17: =11_还本付息!F$12 -> 83162.609 | G17: =11_还本付息!G$12 -> 72767.283 | H17: =11_还本付息!H$12 -> 62371.957 | I17: =11_还本付息!I$12 -> 51976.631 | J17: =11_还本付息!J$12 -> 41581.304 | K17: =11_还本付息!K$12 -> 31185.978 | ... U17: =11_还本付息!U$12 -> 0
A18: 2.3 | B18: 流动资金借款余额 | C18: 万元 | D18: =11_还本付息!D$18 -> 0 | E18: =11_还本付息!E$18 -> 1212.2983 | F18: =11_还本付息!F$18 -> 1367.6191 | G18: =11_还本付息!G$18 -> 1367.6191 | H18: =11_还本付息!H$18 -> 1367.6191 | I18: =11_还本付息!I$18 -> 1367.6191 | J18: =11_还本付息!J$18 -> 1367.6191 | K18: =11_还本付息!K$18 -> 1367.6191 | ... U18: =11_还本付息!U$18 -> 0
A19: 2 | B19: 负债小计 | C19: 万元 | D19: =D16+D17+D18 -> 103953.26 | E19: =E16+E17+E18 -> 94918.072 | F19: =F16+F17+F18 -> 84684.587 | G19: =G16+G17+G18 -> 74289.261 | H19: =H16+H17+H18 -> 63893.934 | I19: =I16+I17+I18 -> 53498.608 | J19: =J16+J17+J18 -> 43103.282 | K19: =K16+K17+K18 -> 32707.956 | ... U19: =U16+U17+U18 -> 0
A20: 3.1 | B20: 资本金（累计） | C20: 万元 | D20: =3_资金筹措!D$15 -> 20000 | E20: =IF(1=0,0,D20)+3_资金筹措!E$15 -> 20519.556 | F20: =IF(2=0,0,E20)+3_资金筹措!F$15 -> 20586.122 | G20: =IF(3=0,0,F20)+3_资金筹措!G$15 -> 20586.122 | H20: =IF(4=0,0,G20)+3_资金筹措!H$15 -> 20586.122 | I20: =IF(5=0,0,H20)+3_资金筹措!I$15 -> 20586.122 | J20: =IF(6=0,0,I20)+3_资金筹措!J$15 -> 20586.122 | K20: =IF(7=0,0,J20)+3_资金筹措!K$15 -> 20586.122 | L20: =IF(8=0,0,K20)+3_资金筹措!L$15 -> 20586.122 | M20: =IF(9=0,0,L20)+3_资金筹措!M$15 -> 20586.122 | N20: =IF(10=0,0,M20)+3_资金筹措!N$15 -> 20586.122 | O20: =IF(11=0,0,N20)+3_资金筹措!O$15 -> 20586.122 | P20: =IF(12=0,0,O20)+3_资金筹措!P$15 -> 20586.122 | Q20: =IF(13=0,0,P20)+3_资金筹措!Q$15 -> 20586.122 | R20: =IF(14=0,0,Q20)+3_资金筹措!R$15 -> 20586.122 | S20: =IF(15=0,0,R20)+3_资金筹措!S$15 -> 20586.122 | T20: =IF(16=0,0,S20)+3_资金筹措!T$15 -> 20586.122 | U20: =IF(17=0,0,T20)+3_资金筹措!U$15 -> 20586.122
A21: 3.2 | B21: 累计盈余公积金 | C21: 万元 | D21: =7_利润!D$17 -> 0 | E21: =7_利润!E$17 -> 0 | F21: =7_利润!F$17 -> 0 | G21: =7_利润!G$17 -> 0 | H21: =7_利润!H$17 -> 0 | I21: =7_利润!I$17 -> 0 | J21: =7_利润!J$17 -> 1502.5646 | K21: =7_利润!K$17 -> 2757.9478 | ... U21: =7_利润!U$17 -> 6664.4342
A22: 3.3 | B22: 累计未分配利润 | C22: 万元 | D22: =7_利润!D$19 -> 0 | E22: =7_利润!E$19 -> -3945.8757 | F22: =7_利润!F$19 -> -5019.4285 | G22: =7_利润!G$19 -> -5783.8396 | H22: =7_利润!H$19 -> -7125.5418 | I22: =7_利润!I$19 -> -8155.3843 | J22: =7_利润!J$19 -> 5367.6971 | K22: =7_利润!K$19 -> 16666.146 | ... U22: =7_利润!U$19 -> 51824.523
A23: 3 | B23: 所有者权益小计 | C23: 万元 | D23: =D20+D21+D22 -> 20000 | E23: =E20+E21+E22 -> 16573.681 | F23: =F20+F21+F22 -> 15566.694 | G23: =G20+G21+G22 -> 14802.283 | H23: =H20+H21+H22 -> 13460.581 | I23: =I20+I21+I22 -> 12430.738 | J23: =J20+J21+J22 -> 27456.384 | K23: =K20+K21+K22 -> 40010.216 | ... U23: =U20+U21+U22 -> 79075.08
B24: 负债及所有者权益总计 | C24: 万元 | D24: =D19+D23 -> 123953.26 | E24: =E19+E23 -> 111491.75 | F24: =F19+F23 -> 100251.28 | G24: =G19+G23 -> 89091.543 | H24: =H19+H23 -> 77354.515 | I24: =I19+I23 -> 65929.347 | J24: =J19+J23 -> 70559.666 | K24: =K19+K23 -> 72718.172 | ... U24: =U19+U23 -> 79075.08
B25: 校核：资产 − 负债 − 权益（应为 0） | C25: 万元 | D25: =IF(D$4="",0,D15-D24) -> 0 | E25: =IF(E$4="",0,E15-E24) -> 0 | F25: =IF(F$4="",0,F15-F24) -> 0 | G25: =IF(G$4="",0,G15-G24) -> 0 | H25: =IF(H$4="",0,H15-H24) -> 0 | I25: =IF(I$4="",0,I15-I24) -> 0 | J25: =IF(J$4="",0,J15-J24) -> 0 | K25: =IF(K$4="",0,K15-K24) -> 0 | ... U25: =IF(U$4="",0,U15-U24) -> 0
B26: 资产负债率 | D26: =IF(D15>0,D19/D15,0) -> 0.83864886 | E26: =IF(E15>0,E19/E15,0) -> 0.85134613 | F26: =IF(F15>0,F19/F15,0) -> 0.84472324 | G26: =IF(G15>0,G19/G15,0) -> 0.83385311 | H26: =IF(H15>0,H19/H15,0) -> 0.82598843 | I26: =IF(I15>0,I19/I15,0) -> 0.81145364 | J26: =IF(J15>0,J19/J15,0) -> 0.61087707 | K26: =IF(K15>0,K19/K15,0) -> 0.44979068 | ... U26: =IF(U15>0,U19/U15,0) -> 0
B27: 运营期最高资产负债率 | V27: =MAX(D26:U26) -> 0.85134613

Sheet 11_还本付息
A1: 附表 11 借款还本付息计算表
A2: 单位：万元。建设期利息 = (年初本息累计 + 本年借款/2) × 利率；运营期等额还本、利息照付；流动资金借款计算期末一次归还
A3: 序号 | B3: 项目 \ 年份 | C3: 单位/说明 | D3: 1 | E3: =D3+1 -> 2 | F3: =E3+1 -> 3 | G3: =F3+1 -> 4 | H3: =G3+1 -> 5 | I3: =H3+1 -> 6 | J3: =I3+1 -> 7 | K3: =J3+1 -> 8 | L3: =K3+1 -> 9 | ... U3: =T3+1 -> 18 | V3: 合计/平均
B4: 阶段 | D4: =IF(D$3<=0_参数!$C$9,"建设",IF(D$3<=0_参数!$C$9+0_参数!$C$10,"运营","")) -> 建设 | E4: =IF(E$3<=0_参数!$C$9,"建设",IF(E$3<=0_参数!$C$9+0_参数!$C$10,"运营","")) -> 运营 | F4: =IF(F$3<=0_参数!$C$9,"建设",IF(F$3<=0_参数!$C$9+0_参数!$C$10,"运营","")) -> 运营 | G4: =IF(G$3<=0_参数!$C$9,"建设",IF(G$3<=0_参数!$C$9+0_参数!$C$10,"运营","")) -> 运营 | H4: =IF(H$3<=0_参数!$C$9,"建设",IF(H$3<=0_参数!$C$9+0_参数!$C$10,"运营","")) -> 运营 | I4: =IF(I$3<=0_参数!$C$9,"建设",IF(I$3<=0_参数!$C$9+0_参数!$C$10,"运营","")) -> 运营 | J4: =IF(J$3<=0_参数!$C$9,"建设",IF(J$3<=0_参数!$C$9+0_参数!$C$10,"运营","")) -> 运营 | K4: =IF(K$3<=0_参数!$C$9,"建设",IF(K$3<=0_参数!$C$9+0_参数!$C$10,"运营","")) -> 运营 | ... U4: =IF(U$3<=0_参数!$C$9,"建设",IF(U$3<=0_参数!$C$9+0_参数!$C$10,"运营",""))
B5: 运营年序号 | D5: =IF(D$4="运营",D$3-0_参数!$C$9,0) -> 0 | E5: =IF(E$4="运营",E$3-0_参数!$C$9,0) -> 1 | F5: =IF(F$4="运营",F$3-0_参数!$C$9,0) -> 2 | G5: =IF(G$4="运营",G$3-0_参数!$C$9,0) -> 3 | H5: =IF(H$4="运营",H$3-0_参数!$C$9,0) -> 4 | I5: =IF(I$4="运营",I$3-0_参数!$C$9,0) -> 5 | J5: =IF(J$4="运营",J$3-0_参数!$C$9,0) -> 6 | K5: =IF(K$4="运营",K$3-0_参数!$C$9,0) -> 7 | ... U5: =IF(U$4="运营",U$3-0_参数!$C$9,0) -> 0
B6: 建设年序号 | D6: =IF(D$4="建设",D$3,0) -> 1 | E6: =IF(E$4="建设",E$3,0) -> 0 | F6: =IF(F$4="建设",F$3,0) -> 0 | G6: =IF(G$4="建设",G$3,0) -> 0 | H6: =IF(H$4="建设",H$3,0) -> 0 | I6: =IF(I$4="建设",I$3,0) -> 0 | J6: =IF(J$4="建设",J$3,0) -> 0 | K6: =IF(K$4="建设",K$3,0) -> 0 | ... U6: =IF(U$4="建设",U$3,0) -> 0
A7: 1.1 | B7: 长期借款 年初本息累计 | C7: 万元 | D7: =0 -> 0 | E7: =IF(1=0,0,D12) -> 103953.26 | F7: =IF(2=0,0,E12) -> 93557.935 | G7: =IF(3=0,0,F12) -> 83162.609 | H7: =IF(4=0,0,G12) -> 72767.283 | I7: =IF(5=0,0,H12) -> 62371.957 | J7: =IF(6=0,0,I12) -> 51976.631 | K7: =IF(7=0,0,J12) -> 41581.304 | L7: =IF(8=0,0,K12) -> 31185.978 | M7: =IF(9=0,0,L12) -> 20790.652 | N7: =IF(10=0,0,M12) -> 10395.326 | O7: =IF(11=0,0,N12) -> 0 | P7: =IF(12=0,0,O12) -> 0 | Q7: =IF(13=0,0,P12) -> 0 | R7: =IF(14=0,0,Q12) -> 0 | S7: =IF(15=0,0,R12) -> 0 | T7: =IF(16=0,0,S12) -> 0 | U7: =IF(17=0,0,T12) -> 0
A8: 1.2 | B8: 本年借款（建设投资部分） | C8: 万元 | D8: =3_资金筹措!D$16 -> 102417.01 | E8: =3_资金筹措!E$16 -> 0 | F8: =3_资金筹措!F$16 -> 0 | G8: =3_资金筹措!G$16 -> 0 | H8: =3_资金筹措!H$16 -> 0 | I8: =3_资金筹措!I$16 -> 0 | J8: =3_资金筹措!J$16 -> 0 | K8: =3_资金筹措!K$16 -> 0 | ... U8: =3_资金筹措!U$16 -> 0 | V8: =SUM(D8:U8) -> 102417.01
A9: 1.3 | B9: 建设期利息 | C9: 万元 | D9: =IF(D$4="建设",(D7+D8/2)*0_参数!$C$90,0) -> 1536.2551 | E9: =IF(E$4="建设",(E7+E8/2)*0_参数!$C$90,0) -> 0 | F9: =IF(F$4="建设",(F7+F8/2)*0_参数!$C$90,0) -> 0 | G9: =IF(G$4="建设",(G7+G8/2)*0_参数!$C$90,0) -> 0 | H9: =IF(H$4="建设",(H7+H8/2)*0_参数!$C$90,0) -> 0 | I9: =IF(I$4="建设",(I7+I8/2)*0_参数!$C$90,0) -> 0 | J9: =IF(J$4="建设",(J7+J8/2)*0_参数!$C$90,0) -> 0 | K9: =IF(K$4="建设",(K7+K8/2)*0_参数!$C$90,0) -> 0 | ... U9: =IF(U$4="建设",(U7+U8/2)*0_参数!$C$90,0) -> 0 | V9: =SUM(D9:U9) -> 1536.2551
A10: 1.4 | B10: 运营期利息 | C10: 万元 | D10: =IF(D$4="运营",D7*0_参数!$C$90,0) -> 0 | E10: =IF(E$4="运营",E7*0_参数!$C$90,0) -> 3118.5978 | F10: =IF(F$4="运营",F7*0_参数!$C$90,0) -> 2806.7381 | G10: =IF(G$4="运营",G7*0_参数!$C$90,0) -> 2494.8783 | H10: =IF(H$4="运营",H7*0_参数!$C$90,0) -> 2183.0185 | I10: =IF(I$4="运营",I7*0_参数!$C$90,0) -> 1871.1587 | J10: =IF(J$4="运营",J7*0_参数!$C$90,0) -> 1559.2989 | K10: =IF(K$4="运营",K7*0_参数!$C$90,0) -> 1247.4391 | ... U10: =IF(U$4="运营",U7*0_参数!$C$90,0) -> 0 | V10: =SUM(D10:U10) -> 17152.288
A11: 1.5 | B11: 还本 | C11: 万元 | D11: =IF(AND(D$4="运营",D$5<=0_参数!$C$91),$V$13/0_参数!$C$91,0) -> 0 | E11: =IF(AND(E$4="运营",E$5<=0_参数!$C$91),$V$13/0_参数!$C$91,0) -> 10395.326 | F11: =IF(AND(F$4="运营",F$5<=0_参数!$C$91),$V$13/0_参数!$C$91,0) -> 10395.326 | G11: =IF(AND(G$4="运营",G$5<=0_参数!$C$91),$V$13/0_参数!$C$91,0) -> 10395.326 | H11: =IF(AND(H$4="运营",H$5<=0_参数!$C$91),$V$13/0_参数!$C$91,0) -> 10395.326 | I11: =IF(AND(I$4="运营",I$5<=0_参数!$C$91),$V$13/0_参数!$C$91,0) -> 10395.326 | J11: =IF(AND(J$4="运营",J$5<=0_参数!$C$91),$V$13/0_参数!$C$91,0) -> 10395.326 | K11: =IF(AND(K$4="运营",K$5<=0_参数!$C$91),$V$13/0_参数!$C$91,0) -> 10395.326 | ... U11: =IF(AND(U$4="运营",U$5<=0_参数!$C$91),$V$13/0_参数!$C$91,0) -> 0 | V11: =SUM(D11:U11) -> 103953.26
A12: 1.6 | B12: 期末本息累计（余额） | C12: 万元 | D12: =D7+D8+IF(0_参数!$C$92=1,D9,0)-D11 -> 103953.26 | E12: =E7+E8+IF(0_参数!$C$92=1,E9,0)-E11 -> 93557.935 | F12: =F7+F8+IF(0_参数!$C$92=1,F9,0)-F11 -> 83162.609 | G12: =G7+G8+IF(0_参数!$C$92=1,G9,0)-G11 -> 72767.283 | H12: =H7+H8+IF(0_参数!$C$92=1,H9,0)-H11 -> 62371.957 | I12: =I7+I8+IF(0_参数!$C$92=1,I9,0)-I11 -> 51976.631 | J12: =J7+J8+IF(0_参数!$C$92=1,J9,0)-J11 -> 41581.304 | K12: =K7+K8+IF(0_参数!$C$92=1,K9,0)-K11 -> 31185.978 | ... U12: =U7+U8+IF(0_参数!$C$92=1,U9,0)-U11 -> 0 | V12: =INDEX(D12:U12,0_参数!$C$9+0_参数!$C$10) -> 0
B13: 运营期初长期借款本金（建设期末余额） | V13: =INDEX(D12:U12,0_参数!$C$9) -> 103953.26
B14: （预留）
A15: 2.1 | B15: 流动资金借款 年初余额 | C15: 万元 | D15: =0 -> 0 | E15: =IF(1=0,0,D18) -> 0 | F15: =IF(2=0,0,E18) -> 1212.2983 | G15: =IF(3=0,0,F18) -> 1367.6191 | H15: =IF(4=0,0,G18) -> 1367.6191 | I15: =IF(5=0,0,H18) -> 1367.6191 | J15: =IF(6=0,0,I18) -> 1367.6191 | K15: =IF(7=0,0,J18) -> 1367.6191 | L15: =IF(8=0,0,K18) -> 1367.6191 | M15: =IF(9=0,0,L18) -> 1367.6191 | N15: =IF(10=0,0,M18) -> 1367.6191 | O15: =IF(11=0,0,N18) -> 0 | P15: =IF(12=0,0,O18) -> 0 | Q15: =IF(13=0,0,P18) -> 0 | R15: =IF(14=0,0,Q18) -> 0 | S15: =IF(15=0,0,R18) -> 0 | T15: =IF(16=0,0,S18) -> 0 | U15: =IF(17=0,0,T18) -> 0
A16: 2.2 | B16: 本年借款 | C16: 万元 | D16: =2_流动资金!D$17 -> 0 | E16: =2_流动资金!E$17 -> 1212.2983 | F16: =2_流动资金!F$17 -> 155.32075 | G16: =2_流动资金!G$17 -> 0 | H16: =2_流动资金!H$17 -> 0 | I16: =2_流动资金!I$17 -> 0 | J16: =2_流动资金!J$17 -> 0 | K16: =2_流动资金!K$17 -> 0 | ... U16: =2_流动资金!U$17 -> 0 | V16: =SUM(D16:U16) -> 1367.6191
A17: 2.3 | B17: 本年归还（计算期末） | C17: 万元 | D17: =IF(D$3=0_参数!$C$9+0_参数!$C$10,D15+D16,0) -> 0 | E17: =IF(E$3=0_参数!$C$9+0_参数!$C$10,E15+E16,0) -> 0 | F17: =IF(F$3=0_参数!$C$9+0_参数!$C$10,F15+F16,0) -> 0 | G17: =IF(G$3=0_参数!$C$9+0_参数!$C$10,G15+G16,0) -> 0 | H17: =IF(H$3=0_参数!$C$9+0_参数!$C$10,H15+H16,0) -> 0 | I17: =IF(I$3=0_参数!$C$9+0_参数!$C$10,I15+I16,0) -> 0 | J17: =IF(J$3=0_参数!$C$9+0_参数!$C$10,J15+J16,0) -> 0 | K17: =IF(K$3=0_参数!$C$9+0_参数!$C$10,K15+K16,0) -> 0 | ... U17: =IF(U$3=0_参数!$C$9+0_参数!$C$10,U15+U16,0) -> 0 | V17: =SUM(D17:U17) -> 1367.6191
A18: 2.4 | B18: 期末余额 | C18: 万元 | D18: =D15+D16-D17 -> 0 | E18: =E15+E16-E17 -> 1212.2983 | F18: =F15+F16-F17 -> 1367.6191 | G18: =G15+G16-G17 -> 1367.6191 | H18: =H15+H16-H17 -> 1367.6191 | I18: =I15+I16-I17 -> 1367.6191 | J18: =J15+J16-J17 -> 1367.6191 | K18: =K15+K16-K17 -> 1367.6191 | ... U18: =U15+U16-U17 -> 0 | V18: =INDEX(D18:U18,0_参数!$C$9+0_参数!$C$10) -> 0
A19: 2.5 | B19: 流动资金借款利息 | C19: 万元 | D19: =(D15+D16/2)*0_参数!$C$94 -> 0 | E19: =(E15+E16/2)*0_参数!$C$94 -> 21.21522 | F19: =(F15+F16/2)*0_参数!$C$94 -> 45.148554 | G19: =(G15+G16/2)*0_参数!$C$94 -> 47.866667 | H19: =(H15+H16/2)*0_参数!$C$94 -> 47.866667 | I19: =(I15+I16/2)*0_参数!$C$94 -> 47.866667 | J19: =(J15+J16/2)*0_参数!$C$94 -> 47.866667 | K19: =(K15+K16/2)*0_参数!$C$94 -> 47.866667 | ... U19: =(U15+U16/2)*0_参数!$C$94 -> 0 | V19: =SUM(D19:U19) -> 449.29711
B20: （预留）
A21: 3 | B21: 偿还借款本金的资金来源（净利润 + 折旧 + 摊销） | C21: 万元 | D21: =7_利润!D$15+5_折旧摊销!D$27+5_折旧摊销!D$31 -> 0 | E21: =7_利润!E$15+5_折旧摊销!E$27+5_折旧摊销!E$31 -> 15081.587 | F21: =7_利润!F$15+5_折旧摊销!F$27+5_折旧摊销!F$31 -> 17953.91 | G21: =7_利润!G$15+5_折旧摊销!G$27+5_折旧摊销!G$31 -> 18263.052 | H21: =7_利润!H$15+5_折旧摊销!H$27+5_折旧摊销!H$31 -> 17685.761 | I21: =7_利润!I$15+5_折旧摊销!I$27+5_折旧摊销!I$31 -> 17997.621 | J21: =7_利润!J$15+5_折旧摊销!J$27+5_折旧摊销!J$31 -> 16019.393 | K21: =7_利润!K$15+5_折旧摊销!K$27+5_折旧摊销!K$31 -> 13547.579 | ... U21: =7_利润!U$15+5_折旧摊销!U$27+5_折旧摊销!U$31 -> 0 | V21: =SUM(D21:U21) -> 158595.01
B22: 还本后资金余额 | C22: 万元 | D22: =D21-D11-D17 -> 0 | E22: =E21-E11-E17 -> 4686.2613 | F22: =F21-F11-F17 -> 7558.5842 | G22: =G21-G11-G17 -> 7867.7259 | H22: =H21-H11-H17 -> 7290.4347 | I22: =I21-I11-I17 -> 7602.2945 | J22: =J21-J11-J17 -> 5624.0671 | K22: =K21-K11-K17 -> 3152.2526 | ... U22: =U21-U11-U17 -> 0 | V22: =SUM(D22:U22) -> 53274.128
A23: 4 | B23: 利息备付率 = (利润总额 + 利息) / 利息 | C23: 倍 | D23: =IF(AND(D$4="运营",(D10+D19)>0),(7_利润!D$12+D10+D19)/(D10+D19),"") | E23: =IF(AND(E$4="运营",(E10+E19)>0),(7_利润!E$12+E10+E19)/(E10+E19),"") -> -0.25672314 | F23: =IF(AND(F$4="运营",(F10+F19)>0),(7_利润!F$12+F10+F19)/(F10+F19),"") -> 0.62356401 | G23: =IF(AND(G$4="运营",(G10+G19)>0),(7_利润!G$12+G10+G19)/(G10+G19),"") -> 0.69937563 | H23: =IF(AND(H$4="运营",(H10+H19)>0),(7_利润!H$12+H10+H19)/(H10+H19),"") -> 0.39857852 | I23: =IF(AND(I$4="运营",(I10+I19)>0),(7_利润!I$12+I10+I19)/(I10+I19),"") -> 0.4633513 | J23: =IF(AND(J$4="运营",(J10+J19)>0),(7_利润!J$12+J10+J19)/(J10+J19),"") -> 11.774082 | K23: =IF(AND(K$4="运营",(K10+K19)>0),(7_利润!K$12+K10+K19)/(K10+K19),"") -> 13.922386 | ... U23: =IF(AND(U$4="运营",(U10+U19)>0),(7_利润!U$12+U10+U19)/(U10+U19),"")
A24: 5 | B24: 偿债备付率 = (利润总额 + 折旧 + 摊销 + 利息 − 所得税) / (还本 + 付息) | C24: 倍 | D24: =IF(AND(D$4="运营",(D11+D10+D19)>0),(7_利润!D$12+5_折旧摊销!D$27+5_折旧摊销!D$31+D10+D19-7_利润!D$14)/(D11+D10+D19),"") | E24: =IF(AND(E$4="运营",(E11+E10+E19)>0),(7_利润!E$12+5_折旧摊销!E$27+5_折旧摊销!E$31+E10+E19-7_利润!E$14)/(E11+E10+E19),"") -> 1.3462293 | F24: =IF(AND(F$4="运营",(F11+F10+F19)>0),(7_利润!F$12+5_折旧摊销!F$27+5_折旧摊销!F$31+F10+F19-7_利润!F$14)/(F11+F10+F19),"") -> 1.5705792 | G24: =IF(AND(G$4="运营",(G11+G10+G19)>0),(7_利润!G$12+5_折旧摊销!G$27+5_折旧摊销!G$31+G10+G19-7_利润!G$14)/(G11+G10+G19),"") -> 1.6081066 | H24: =IF(AND(H$4="运营",(H11+H10+H19)>0),(7_利润!H$12+5_折旧摊销!H$27+5_折旧摊销!H$31+H10+H19-7_利润!H$14)/(H11+H10+H19),"") -> 1.5774048 | I24: =IF(AND(I$4="运营",(I11+I10+I19)>0),(7_利润!I$12+5_折旧摊销!I$27+5_折旧摊销!I$31+I10+I19-7_利润!I$14)/(I11+I10+I19),"") -> 1.6173524 | J24: =IF(AND(J$4="运营",(J11+J10+J19)>0),(7_利润!J$12+5_折旧摊销!J$27+5_折旧摊销!J$31+J10+J19-7_利润!J$14)/(J11+J10+J19),"") -> 1.468575 | K24: =IF(AND(K$4="运营",(K11+K10+K19)>0),(7_利润!K$12+5_折旧摊销!K$27+5_折旧摊销!K$31+K10+K19-7_利润!K$14)/(K11+K10+K19),"") -> 1.2696392 | ... U24: =IF(AND(U$4="运营",(U11+U10+U19)>0),(7_利润!U$12+5_折旧摊销!U$27+5_折旧摊销!U$31+U10+U19-7_利润!U$14)/(U11+U10+U19),"")
B25: 运营期最低利息备付率 / 偿债备付率 | V25: =MIN(D23:U23) -> -0.25672314
B26: 运营期最低偿债备付率 | V26: =MIN(D24:U24) -> 1.2696392

Sheet 12_敏感性
A1: 附表 12 敏感性分析（单因素）
A2: 机制：C6:C10 为五个因素的乘数（基准 1.00），参数页 D2/D5–D8 引用它们；下方各表为 Excel 数据表（模拟分析→数据表），Excel 打开后自动重算。注意：本页不可用 LibreOffice 另存，否则数据表失效
B4: 基准结果
B5: 因素 / 乘数（正常运行时全部保持 1.00） | C5: 乘数 | E5: 指标 | F5: 基准值
B6: 算力单价 | C6: 1 | E6: 税后 IRR | F6: =8_现金流量!$D$30 -> 0.080255495
B7: 售卖比例（上架率） | C7: 1 | E7: 税前 IRR | F7: =8_现金流量!$D$29 -> 0.10281066
B8: 电价 | C8: 1 | E8: 税后 NPV（万元） | F8: =8_现金流量!$D$32 -> 130.51575
B9: 算力设备价格 | C9: 1 | E9: 税后动态回收期（年） | F9: =8_现金流量!$D$36 -> 10.989015
B10: 基础设施设备价格 | C10: 1 | E10: 基准收益率 ic | F10: =0_参数!$C$14 -> 0.08
B12: 单因素敏感性数据表（列输入单元格 = 对应因素乘数）
B13: 因素：算力单价
C14: 变化率 | D14: 税后 IRR | E14: 税前 IRR | F14: 税后 NPV | G14: 税前 NPV
B15: 乘数 →（表头公式行，勿改） | D15: =8_现金流量!$D$30 -> 0.080255495 | E15: =8_现金流量!$D$29 -> 0.10281066 | F15: =8_现金流量!$D$32 -> 130.51575 | G15: =8_现金流量!$D$31 -> 12574.909 | I15: 敏感度系数（税后 IRR，±10%） | J15: =IFERROR(((D19-D17)/$F$6)/0.2,0) -> 2.8298078
B16: -20% | C16: 0.8 | D16: 0.028563177 | E16: 0.048180539 | F16: -25036.365 | G16: -16577.797 | I16: 临界变化率（税后 IRR = ic，线性近似） | J16: =IFERROR(($F$10-$F$6)/((D19-D17)/0.2),0) -> -0.0011249932
B17: -10% | C17: 0.9 | D17: 0.056017734 | E17: 0.076271896 | F17: -11967.384 | G17: -2001.4442
B18: +0% | C18: 1 | D18: 0.080255495 | E18: 0.10281066 | F18: 130.51575 | G18: 12574.909
B19: +10% | C19: 1.1 | D19: 0.10143926 | E19: 0.12807103 | F19: 11198.36 | G19: 27129.729
B20: +20% | C20: 1.2 | D20: 0.12135464 | E20: 0.15225184 | F20: 22053.393 | G20: 41631.158
B23: 因素：售卖比例（上架率）
C24: 变化率 | D24: 税后 IRR | E24: 税前 IRR | F24: 税后 NPV | G24: 税前 NPV
B25: 乘数 →（表头公式行，勿改） | D25: =8_现金流量!$D$30 -> 0.080255495 | E25: =8_现金流量!$D$29 -> 0.10281066 | F25: =8_现金流量!$D$32 -> 130.51575 | G25: =8_现金流量!$D$31 -> 12574.909 | I25: 敏感度系数（税后 IRR，±10%） | J25: =IFERROR(((D29-D27)/$F$6)/0.2,0) -> 2.7432519
B26: -20% | C26: 0.8 | D26: 0.030222551 | E26: 0.049887517 | F26: -24263.323 | G26: -15716.163 | I26: 临界变化率（税后 IRR = ic，线性近似） | J26: =IFERROR(($F$10-$F$6)/((D29-D27)/0.2),0) -> -0.0011604893
B27: -10% | C27: 0.9 | D27: 0.056806973 | E27: 0.077076646 | F27: -11580.863 | G27: -1570.6271
B28: +0% | C28: 1 | D28: 0.080255495 | E28: 0.10281066 | F28: 130.51575 | G28: 12574.909
B29: +10% | C29: 1.1 | D29: 0.10083918 | E29: 0.12734311 | F29: 10878.741 | G29: 26703.571
B30: +20% | C30: 1.2 | D30: 0.10540362 | E30: 0.13315429 | F30: 13217.071 | G30: 29827.801
B33: 因素：电价
C34: 变化率 | D34: 税后 IRR | E34: 税前 IRR | F34: 税后 NPV | G34: 税前 NPV
B35: 乘数 →（表头公式行，勿改） | D35: =8_现金流量!$D$30 -> 0.080255495 | E35: =8_现金流量!$D$29 -> 0.10281066 | F35: =8_现金流量!$D$32 -> 130.51575 | G35: =8_现金流量!$D$31 -> 12574.909 | I35: 敏感度系数（税后 IRR，±10%） | J35: =IFERROR(((D39-D37)/$F$6)/0.2,0) -> -0.083186198
B36: -20% | C36: 0.8 | D36: 0.081589115 | E36: 0.10436109 | F36: 812.75608 | G36: 13448.247 | I36: 临界变化率（税后 IRR = ic，线性近似） | J36: =IFERROR(($F$10-$F$6)/((D39-D37)/0.2),0) -> 0.038269743
B37: -10% | C37: 0.9 | D37: 0.080922706 | E37: 0.10358639 | F37: 471.63592 | G37: 13011.578
B38: +0% | C38: 1 | D38: 0.080255495 | E38: 0.10281066 | F38: 130.51575 | G38: 12574.909
B39: +10% | C39: 1.1 | D39: 0.079587476 | E39: 0.1020339 | F39: -210.60441 | G39: 12138.24
B40: +20% | C40: 1.2 | D40: 0.078918646 | E40: 0.10125609 | F40: -551.72458 | G40: 11701.571
B43: 因素：算力设备价格
C44: 变化率 | D44: 税后 IRR | E44: 税前 IRR | F44: 税后 NPV | G44: 税前 NPV
B45: 乘数 →（表头公式行，勿改） | D45: =8_现金流量!$D$30 -> 0.080255495 | E45: =8_现金流量!$D$29 -> 0.10281066 | F45: =8_现金流量!$D$32 -> 130.51575 | G45: =8_现金流量!$D$31 -> 12574.909 | I45: 敏感度系数（税后 IRR，±10%） | J45: =IFERROR(((D49-D47)/$F$6)/0.2,0) -> -2.1730608
B46: -20% | C46: 0.8 | D46: 0.11840723 | E46: 0.14903601 | F46: 17071.604 | G46: 33084.22 | I46: 临界变化率（税后 IRR = ic，线性近似） | J46: =IFERROR(($F$10-$F$6)/((D49-D47)/0.2),0) -> 0.001464991
B47: -10% | C47: 0.9 | D47: 0.098218165 | E47: 0.12430647 | F47: 8707.0915 | G47: 22855.746
B48: +0% | C48: 1 | D48: 0.080255495 | E48: 0.10281066 | F48: 130.51575 | G48: 12574.909
B49: +10% | C49: 1.1 | D49: 0.06333815 | E49: 0.083901092 | F49: -9053.6976 | G49: 2285.2048
B50: +20% | C50: 1.2 | D50: 0.046646493 | E50: 0.067079877 | F50: -19208.932 | G50: -8004.4515
B53: 因素：基础设施设备价格
C54: 变化率 | D54: 税后 IRR | E54: 税前 IRR | F54: 税后 NPV | G54: 税前 NPV
B55: 乘数 →（表头公式行，勿改） | D55: =8_现金流量!$D$30 -> 0.080255495 | E55: =8_现金流量!$D$29 -> 0.10281066 | F55: =8_现金流量!$D$32 -> 130.51575 | G55: =8_现金流量!$D$31 -> 12574.909 | I55: 敏感度系数（税后 IRR，±10%） | J55: =IFERROR(((D59-D57)/$F$6)/0.2,0) -> -0.26986515
B56: -20% | C56: 0.8 | D56: 0.084693406 | E56: 0.10791373 | F56: 2339.8015 | G56: 15046.247 | I56: 临界变化率（税后 IRR = ic，线性近似） | J56: =IFERROR(($F$10-$F$6)/((D59-D57)/0.2),0) -> 0.011796686
B57: -10% | C57: 0.9 | D57: 0.082447411 | E57: 0.10533353 | F57: 1235.1607 | G57: 13810.581
B58: +0% | C58: 1 | D58: 0.080255495 | E58: 0.10281066 | F58: 130.51575 | G58: 12574.909
B59: +10% | C59: 1.1 | D59: 0.078115779 | E59: 0.10034322 | F59: -974.13327 | G59: 11339.23
B60: +20% | C60: 1.2 | D60: 0.076026469 | E60: 0.097929402 | F60: -2078.7862 | G60: 10103.545
B63: 读法：敏感度系数绝对值越大越敏感；临界变化率 = 使税后 IRR 降到基准收益率所需的该因素变化幅度（线性近似，正式稿可用单变量求解精确化）。
B64: 若 Excel 未自动计算数据表：公式 → 计算选项 → 自动（含数据表），或按 F9。

Sheet 13_一致性校核
A1: 一致性校核表（出稿前必须全部 OK）
A2: 每条校核对应可研自检清单；ERR 时不得出稿
A4: 编号 | B4: 校核项 | C4: 计算值 | D4: 结果 | E4: 说明
A5: C1 | B5: 建设投资各年投入比例之和 = 100% | C5: =0_参数!$C$11+0_参数!$C$12+0_参数!$C$13 -> 1 | D5: =IF(ABS(C5-1)<0.0001,"OK","ERR") -> OK | E5: 参数 A6–A8
A6: C2 | B6: 建设期 ≤ 3 且 运营期 ≤ 15 且 正常年 ≤ 运营期 且 还款年限 ≤ 运营期 | C6: =AND(0_参数!$C$9<=3,0_参数!$C$9>=1,0_参数!$C$10<=15,0_参数!$C$15<=0_参数!$C$10,0_参数!$C$91<=0_参数!$C$10) -> TRUE | D6: =IF(C6,"OK","ERR") -> OK | E6: 模型年份列上限 18
A7: C3 | B7: 附表 1-2 GPU 服务器数量 = 参数 B6；模块数量 = 参数 B1 | C7: =AND('1-2_设备及软件'!$D$6=0_参数!$C$23,'1-2_设备及软件'!$D$15=0_参数!$C$18) -> TRUE | D7: =IF(C7,"OK","ERR") -> OK | E7: 规模口径三件套同源
A8: C4 | B8: 附表 3 建设投资合计 = 附表 1 工程建设投资 | C8: =3_资金筹措!$V$8-1_总投资估算!$G$29 -> 0 | D8: =IF(ABS(C8)<0.01,"OK","ERR") -> OK
A9: C5 | B9: 附表 3 资金筹措 − 总资金 = 0（各年） | C9: =SUMPRODUCT(ABS(3_资金筹措!D21:U21)) -> 0 | D9: =IF(ABS(C9)<0.01,"OK","ERR") -> OK
A10: C6 | B10: 附表 10 资产 − 负债 − 权益 = 0（各年绝对差之和） | C10: =SUMPRODUCT(ABS(10_资产负债!D25:U25)) -> 0 | D10: =IF(ABS(C10)<0.5,"OK","ERR") -> OK | E10: 允许 0.5 万元舍入
A11: C7 | B11: 附表 9 累计盈余资金全程 ≥ 0（最小值） | C11: =MIN(9_财务计划现金流量!D32:U32) -> 0 | D11: =IF(C11>=-0.01,"OK","ERR") -> OK | E11: ERR = 资金缺口，需调融资或流动资金
A12: C8 | B12: 投产比例非递减且 ≤ 1；售卖比例 ≤ 1 | C12: =AND(SUMPRODUCT(--(0_参数!$E$126:$R$126<0_参数!$D$126:$Q$126))=0,MAX(0_参数!$D$126:$R$126)<=1,MAX(0_参数!$D$127:$R$127)<=1) -> TRUE | D12: =IF(C12,"OK","ERR") -> OK | E12: 参数 K1 / K2
A13: C9 | B13: 长期借款计算期末余额 = 0 | C13: =11_还本付息!$V$12 -> 0 | D13: =IF(ABS(C13)<0.01,"OK","ERR") -> OK | E13: 还款年限 ≤ 运营期时应为 0
A14: C10 | B14: 货币与税口径 = 人民币（含税） | C14: =0_参数!$C$7 -> 人民币（含税） | D14: =IF(C14="人民币（含税）","OK","ERR") -> OK | E14: 国内铁律；海外项目不得使用本模板
A15: C11 | B15: 设计 PUE ≥ 1.0 且 ≤ 1.25（国家新建大型数据中心红线） | C15: =0_参数!$C$29 -> 1.18 | D15: =IF(AND(C15>=1,C15<=1.25),"OK","ERR") -> OK | E15: 枢纽节点 ≤ 1.2 另核
A16: C12 | B16: 附表 1-2 所有单价已填（无空白） | C16: =COUNTBLANK('1-2_设备及软件'!$E$6:$E$11)+COUNTBLANK('1-2_设备及软件'!$E$15:$E$21) -> 0 | D16: =IF(C16=0,"OK","ERR") -> OK
A17: C13 | B17: 税后 IRR ≥ 基准收益率 ic（可行性判据） | C17: =8_现金流量!$D$30-0_参数!$C$14 -> 0.00025549453 | D17: =IF(C17>=0,"OK","WARN") -> OK | E17: WARN = 财务不可行，需调方案而非改数
A18: C14 | B18: 附表 8 建设投资合计 = 附表 1 工程建设投资 | C18: =8_现金流量!$V$12-1_总投资估算!$G$29 -> 0 | D18: =IF(ABS(C18)<0.01,"OK","ERR") -> OK
A19: C15 | B19: 附表 4 折旧合计 = 固定资产原值 × (1 − 残值率)（折旧年限 ≤ 运营期时）或 ≤ 该值 | C19: =5_折旧摊销!$V$27-5_折旧摊销!$C$15*(1-0_参数!$C$75) -> -5665.5971 | D19: =IF(C19<=0.01,"OK","ERR") -> OK | E19: 累计折旧不得超过应计折旧
B21: ERR 数量 | C21: =COUNTIF(D5:D19,"ERR") -> 0
B22: WARN 数量 | C22: =COUNTIF(D5:D19,"WARN") -> 0
B23: 总体结论 | C23: =IF(C21=0,"可出稿","不得出稿") -> 可出稿
